Workbook

Sheet Read Me
A1: Southern Water Corp. Financial Analysis
A11: In this unit, you've learned about the fundamentals of financial analysis spanning revenues, expenses and profitability.
A12: In this case study, we'll seek to unpack these concepts, combining the financial analysis skills you've learned and have you apply this through your budding Excel capabilities!
A13: This case study will emphasise both your use of Pivot Tables as well as your charting capabilities, where you'll use these charts for a PowerPoint presentation you'll create at the end of this analysis!
A14: Good luck and let's get started!
A16: What do the tab colours in this workbook mean?
A17: Throughout the Case Study, we've split this into three sections. As you cover the relevant financial concepts, you'll apply what you've learned in the exercise tabs. The order of completion is below: 1) Revenue Sub Unit - Revenue Analysis 2) Expense Sub Unit - Expense Analysis 3) Profitability Sub Unit - Profitability (EBIT) Analysis
A18: Unpacking the Data Repository Table
A19: The data repository table might look scary at first, but all the data is logically grouped in a manner where the table can be read left-to-right.
A20: We've included an example below to break down how you can interpret this information.
A32: Definitions
A33: We've included a high-level breakdown that explains the different columns you will deal with in the data repository table. Please read through this and familiarise yourself with what these columns mean.
A35: Account Type | B35: This column provides information on whether the dataset is referencing either a Revenue Generating Activity (Revenues) or Cost Generating Activity (Expenses) or Water Actuals (Volume of Water Produced).
A36: Unit | B36: There are three desalination units or plants (facilities) owned by Southern Water Corp. These are the Kootha, Surjek and Jutik desalination units. The Unit column indicates, for that row of data, which Unit it applies towards.
A37: Month | B37: This represents the month that data was calculated for.
A38: Month (Number) | B38: This represents the month in numerical form.
A39: Accounting Code Centre | B39: Every row is mapped to an Accounting Code Centre. Based off the Accounting Code Centre (ACC) and the textual description, we know that all ACC's that mention Sales, are Profit Centres, and all ACC's that mention Costs, are Cost Centres. In Financial Accounting, Revenue Generating Activities are mapped to Profit Centres (i.e. They generate profit), whilst Cost Generating Activities are mapped to Cost Centres (i.e. They generate costs).
A40: Accounting Code Centre Element | B40: An Accounting Code Centre Element (ACCE) is made up of 'elements' which tie into the Accounting Code Centre.
A41: Unit of Measure | B41: Every Row of Data has a Unit of Measure (UoM) associated with this. E.g. Financial data is measured in dollars, whilst Water Production data is measure in Giga-Litres.
A42: Row Data | B42: This is the unique value that is stored for every row entry.
A45: Account Types
A46: Below we've included the breakdown for Account Types Revenues and Expenses to better help you understand how the dataset is all connected. Use this if you're feeling unsure of how to calculate Revenues or Expenses.
A48: Revenues | I48: Expenses

Sheet Data Repository Table
A1: Account Type | B1: Unit | C1: Month | D1: Month (Number) | E1: Accounting Code Centre | F1: Accounting Code Centre Element | G1: Unit of Measure | H1: Values
A2: Revenue | B2: Kootha | C2: 41456 | D2: =MONTH(C2) -> 7 | E2: 001 Private Water Hedge Sales | F2: W-Transact (0211) - Soft | G2: $ | H2: 1473589 | I2: Unit | J2: 46216 | K2: 46247 | L2: 46278 | M2: 46308 | N2: 46339 | O2: 46369 | P2: 46036 | Q2: 46067 | R2: 46095 | S2: 46126 | T2: 46156 | U2: 46187 | V2: Total
A3: Revenue | B3: Kootha | C3: 41487 | D3: =MONTH(C3) -> 8 | E3: 001 Private Water Hedge Sales | F3: W-Transact (0211) - Soft | G3: $ | H3: 1419296.1 | I3: Kootha | J3: 2456292.3 | K3: 918310.89 | L3: 1519674.8 | M3: 1671126.7 | N3: 1867603.7 | O3: 1873668.8 | P3: 2572779.4 | Q3: 2504532 | R3: 2888063.9 | S3: 912936.1 | T3: 702117.95 | U3: -165973.35 | V3: 19721133
A4: Revenue | B4: Kootha | C4: 41518 | D4: =MONTH(C4) -> 9 | E4: 001 Private Water Hedge Sales | F4: W-Transact (0211) - Soft | G4: $ | H4: 1310673.2 | I4: Surjek | J4: 5988499.8 | K4: 943434.1 | L4: 2328952.4 | M4: -3360291.1 | N4: -6192464.3 | O4: 2604017 | P4: 8366591.3 | Q4: 2112457.6 | R4: 4631100.2 | S4: 2132932 | T4: -4294074.8 | U4: 7675096 | V4: 22936250
A5: Revenue | B5: Kootha | C5: 41548 | D5: =MONTH(C5) -> 10 | E5: 001 Private Water Hedge Sales | F5: W-Transact (0211) - Soft | G5: $ | H5: 1301024.7 | I5: Jutik | J5: 4547848.2 | K5: 6542227.6 | L5: 4438176.9 | M5: 4415960.6 | N5: 5589126.6 | O5: 5264580.3 | P5: 8292411.6 | Q5: 8295134.3 | R5: 5460903 | S5: 8279084.2 | T5: 6175874.2 | U5: 5640408.6 | V5: 72941736
A6: Revenue | B6: Kootha | C6: 41579 | D6: =MONTH(C6) -> 11 | E6: 001 Private Water Hedge Sales | F6: W-Transact (0211) - Soft | G6: $ | H6: 1373822.9
A7: Revenue | B7: Kootha | C7: 41609 | D7: =MONTH(C7) -> 12 | E7: 001 Private Water Hedge Sales | F7: W-Transact (0211) - Soft | G7: $ | H7: 1340623
A8: Revenue | B8: Kootha | C8: 41640 | D8: =MONTH(C8) -> 1 | E8: 001 Private Water Hedge Sales | F8: W-Transact (0211) - Soft | G8: $ | H8: 1948962.6
A9: Revenue | B9: Kootha | C9: 41671 | D9: =MONTH(C9) -> 2 | E9: 001 Private Water Hedge Sales | F9: W-Transact (0211) - Soft | G9: $ | H9: 1725161.7
A10: Revenue | B10: Kootha | C10: 41699 | D10: =MONTH(C10) -> 3 | E10: 001 Private Water Hedge Sales | F10: W-Transact (0211) - Soft | G10: $ | H10: 1818208.6
A11: Revenue | B11: Kootha | C11: 41730 | D11: =MONTH(C11) -> 4 | E11: 001 Private Water Hedge Sales | F11: W-Transact (0211) - Soft | G11: $ | H11: 1328501.7
A12: Revenue | B12: Kootha | C12: 41760 | D12: =MONTH(C12) -> 5 | E12: 001 Private Water Hedge Sales | F12: W-Transact (0211) - Soft | G12: $ | H12: 1344117.3
A13: Revenue | B13: Kootha | C13: 41791 | D13: =MONTH(C13) -> 6 | E13: 001 Private Water Hedge Sales | F13: W-Transact (0211) - Soft | G13: $ | H13: 1291609.1
A14: Revenue | B14: Kootha | C14: 41456 | D14: =MONTH(C14) -> 7 | E14: 001 Private Water Hedge Sales | F14: W-Transact (0212) - Hard | G14: $ | H14: 1620948
A15: Revenue | B15: Kootha | C15: 41487 | D15: =MONTH(C15) -> 8 | E15: 001 Private Water Hedge Sales | F15: W-Transact (0212) - Hard | G15: $ | H15: 1561225.7
A16: Revenue | B16: Kootha | C16: 41518 | D16: =MONTH(C16) -> 9 | E16: 001 Private Water Hedge Sales | F16: W-Transact (0212) - Hard | G16: $ | H16: 1441740.5
A17: Revenue | B17: Kootha | C17: 41548 | D17: =MONTH(C17) -> 10 | E17: 001 Private Water Hedge Sales | F17: W-Transact (0212) - Hard | G17: $ | H17: 1431127.2
... A373: Expenses | B373: Surjek | C373: 41791 | D373: =MONTH(C373) -> 6 | E373: Labour Costs | F373: Labour-Costs (001) | G373: $ | H373: 1891504.3
A374: Expenses | B374: Jutik | C374: 41456 | D374: 7 | E374: Chemical Costs | F374: Chem-Exp (001) | G374: $ | H374: 1625596.3
A375: Expenses | B375: Jutik | C375: 41487 | D375: 8 | E375: Chemical Costs | F375: Chem-Exp (001) | G375: $ | H375: 1295067.8
A376: Expenses | B376: Jutik | C376: 41518 | D376: 9 | E376: Chemical Costs | F376: Chem-Exp (001) | G376: $ | H376: 1750624.9
A377: Expenses | B377: Jutik | C377: 41548 | D377: 10 | E377: Chemical Costs | F377: Chem-Exp (001) | G377: $ | H377: 1472529.4
A378: Expenses | B378: Jutik | C378: 41579 | D378: 11 | E378: Chemical Costs | F378: Chem-Exp (001) | G378: $ | H378: 1252200.5
A379: Expenses | B379: Jutik | C379: 41609 | D379: 12 | E379: Chemical Costs | F379: Chem-Exp (001) | G379: $ | H379: 1406782.7
A380: Expenses | B380: Jutik | C380: 41640 | D380: 1 | E380: Chemical Costs | F380: Chem-Exp (001) | G380: $ | H380: 1877449.5
A381: Expenses | B381: Jutik | C381: 41671 | D381: 2 | E381: Chemical Costs | F381: Chem-Exp (001) | G381: $ | H381: 1912219.2
A382: Expenses | B382: Jutik | C382: 41699 | D382: 3 | E382: Chemical Costs | F382: Chem-Exp (001) | G382: $ | H382: 2266625.2
A383: Expenses | B383: Jutik | C383: 41730 | D383: 4 | E383: Chemical Costs | F383: Chem-Exp (001) | G383: $ | H383: 2234200.6
A384: Expenses | B384: Jutik | C384: 41760 | D384: 5 | E384: Chemical Costs | F384: Chem-Exp (001) | G384: $ | H384: 2593715.6
A385: Expenses | B385: Jutik | C385: 41791 | D385: 6 | E385: Chemical Costs | F385: Chem-Exp (001) | G385: $ | H385: 2274807.8
... A505: Water Production Actuals | B505: Jutik | C505: 41791 | D505: 6 | E505: None | F505: None | G505: Giga-Litre | H505: 220.38033

Sheet Revenue Analysis
A1: Revenue Analysis - Part I
A2: In Financial Data Analysis, Revenue Analysis speaks primarily to understanding which product(s) generate the most revenues and whether we can identify any aspect of seasonality towards these trends or not.
A3: The importance of this is that we are able to clearly understand which product(s) generate the most revenues and least revenues and this forms the first part of our puzzle.
A4: If a product generates a lot of revenues, but the expenses are greater than the revenues - this isn't a good news story.
A5: However, if the product generates a lot of revenues, and the expenses are well below the revenues - we may have a product which is performing well.
A6: Let's take a look at how Southern Water Corps Revenue Analysis looks like by calculating the Revenues for each of the products and asking ourselves - what does the data tell us?
A7: Let's get started!
A8: Q1. For each of the three Southern Water Corp. Desalination Plants, they produce desalinated water which is then consumed via private, public or residential usage. Please calculate the monthly revenues for Kootha, Surjek and Jutik and put this in the table below.
A9: To do this you should create a Pivot Table in a new worksheet you will call "Pivot Table 1", then copy the results from that Pivot Table into the proper place in the table below.
A10: 1) You will need to create a filter in the Pivot Table that allows you to filter the results to include only the items corresponding to the Revenue Value Driver.
A11: 2) If you structure your Pivot Table correctly and select which rows to subtotal, you should be able to copy and paste everything in one copy and paste.
A12: Unit | B12: Account Type | C12: Accounting Code Centre | D12: Accounting Code Centre Element | E12: 41456 | F12: 41487 | G12: 41518 | H12: 41548 | I12: 41579 | J12: 41609 | K12: 41640 | L12: 41671 | M12: 41699 | N12: 41730 | O12: 41760 | P12: 41791
Q13: Total
A14: Kootha | B14: Revenue | C14: 001 Private Water Hedge Sales | D14: W-Transact (0211) - Soft | E14: 1473589 | F14: 1419296.1 | G14: 1310673.2 | H14: 1301024.7 | I14: 1373822.9 | J14: 1340623 | K14: 1948962.6 | L14: 1725161.7 | M14: 1818208.6 | N14: 1328501.7 | O14: 1344117.3 | P14: 1291609.1 | Q14: 17675590
A15: Kootha | B15: Revenue | C15: 001 Private Water Hedge Sales | D15: W-Transact (0212) - Hard | E15: 1620948 | F15: 1561225.7 | G15: 1441740.5 | H15: 1431127.2 | I15: 1511205.1 | J15: 1474685.3 | K15: 2143858.8 | L15: 1897677.9 | M15: 2000029.5 | N15: 1461351.9 | O15: 1478529 | P15: 1420770 | Q15: 19443149
A16: Kootha | B16: Revenue | C16: 002 Public Sales | D16: W-Transact (0211) - Soft | E16: 567331.78 | F16: 546429 | G16: 504609.19 | H16: 500894.52 | I16: 528921.8 | J16: 516139.87 | K16: 750350.58 | L16: 664187.25 | M16: 700010.32 | N16: 511473.15 | O16: 517485.15 | P16: 497269.52 | Q16: 6805102.1
A17: Kootha | B17: Revenue | C17: 002 Public Sales | D17: W-Transact (0212) - Hard | E17: 955954.05 | F17: 920732.86 | G17: 850266.48 | H17: 844007.27 | I17: 891233.24 | J17: 869695.68 | K17: 1264340.7 | L17: 1119155.5 | M17: 1179517.4 | N17: 861832.25 | O17: 871962.48 | P17: 837899.14 | Q17: 11466597
A18: Kootha | B18: Revenue | C18: 003 Residential Sales | D18: W-Transact (0211) - Soft | E18: 1296758.4 | F18: 1248980.6 | G18: 1153392.4 | H18: 1144901.8 | I18: 1208964.1 | J18: 1179748.3 | K18: 1715087 | L18: 1518142.3 | M18: 1600023.6 | N18: 1169081.5 | O18: 1182823.2 | P18: 1136616 | Q18: 15554519
D19: Total Kootha | E19: 5914581.2 | F19: 5696664.2 | G19: 5260681.8 | H19: 5221955.5 | I19: 5514147.2 | J19: 5380892.2 | K19: 7822599.7 | L19: 6924324.6 | M19: 7297789.4 | N19: 5332240.4 | O19: 5394917.1 | P19: 5184163.9 | Q19: 70944957
A20: Surjek | B20: Revenue | C20: 001 Private Water Hedge Sales | D20: W-Transact (0211) - Soft | E20: 2406673.7 | F20: 2028377 | G20: 2241097.2 | H20: 2104393.5 | I20: 1921236.2 | J20: 2161522.2 | K20: 3104730.2 | L20: 2116798.7 | M20: 2728427.9 | N20: 2259504.9 | O20: 2031569.2 | P20: 2245023.2 | Q20: 27349354
A21: Surjek | B21: Revenue | C21: 001 Private Water Hedge Sales | D21: W-Transact (0212) - Hard | E21: 4813347.5 | F21: 4056754 | G21: 4482194.5 | H21: 4208787 | I21: 3842472.4 | J21: 4323044.3 | K21: 6209460.5 | L21: 4633597.4 | M21: 5456855.8 | N21: 4519009.7 | O21: 4063138.5 | P21: 4490046.5 | Q21: 55098708
A22: Surjek | B22: Revenue | C22: 002 Public Sales | D22: W-Transact (0211) - Soft | E22: 2117872.9 | F22: 1784971.8 | G22: 1972165.6 | H22: 1851866.3 | I22: 1690687.9 | J22: 1902139.5 | K22: 2732162.6 | L22: 2478782.9 | M22: 2401016.5 | N22: 1988364.3 | O22: 1787780.9 | P22: 1975620.4 | Q22: 24683432
A23: Surjek | B23: Revenue | C23: 002 Public Sales | D23: W-Transact (0212) - Hard | E23: 3850678 | F23: 3245403.2 | G23: 3585755.6 | H23: 3367029.6 | I23: 3073978 | J23: 3458435.5 | K23: 4967568.4 | L23: 4506877.9 | M23: 4365484.6 | N23: 4615207.8 | O23: 3250510.8 | P23: 3592037.2 | Q23: 45878966
A24: Surjek | B24: Revenue | C24: 003 Residential Sales | D24: W-Transact (0211) - Soft | E24: 4139478.8 | F24: 3488808.4 | G24: 3854687.3 | H24: 3619556.8 | I24: 3304526.3 | J24: 3717818.1 | K24: 5340136 | L24: 4844893.8 | M24: 4692896 | N24: 4886348.4 | O24: 3494299.1 | P24: 3861440 | Q24: 49244889
D25: Total Surjek | E25: 17328051 | F25: 14604314 | G25: 16135900 | H25: 15151633 | I25: 13832901 | J25: 15562960 | K25: 22354058 | L25: 18580951 | M25: 19644681 | N25: 18268435 | O25: 14627298 | P25: 16164167 | Q25: 2.0225535e+08
A26: Jutik | B26: Revenue | C26: 001 Private Water Hedge Sales | D26: W-Transact (0211) - Soft | E26: 1766228.7 | F26: 1951422.8 | G26: 1699371.2 | H26: 1502189.2 | I26: 1650239.5 | J26: 1406546.1 | K26: 2151540.2 | L26: 2191228.2 | M26: 1965526.6 | N26: 2084911.4 | O26: 2053699.4 | P26: 2197266.9 | Q26: 22620170
A27: Jutik | B27: Revenue | C27: 001 Private Water Hedge Sales | D27: W-Transact (0212) - Hard | E27: 3532457.4 | F27: 3902845.5 | G27: 3398742.5 | H27: 3004378.4 | I27: 3300479 | J27: 2813092.2 | K27: 4303080.4 | L27: 4382456.5 | M27: 3931053.2 | N27: 4169822.7 | O27: 4107398.7 | P27: 4394533.8 | Q27: 45240340
A28: Jutik | B28: Revenue | C28: 002 Public Sales | D28: W-Transact (0211) - Soft | E28: 1554281.3 | F28: 1717252 | G28: 1495446.7 | H28: 1321926.5 | I28: 1452210.8 | J28: 1237760.6 | K28: 1893355.4 | L28: 1928280.8 | M28: 1729663.4 | N28: 1834722 | O28: 1807255.4 | P28: 1933594.9 | Q28: 19905750
A29: Jutik | B29: Revenue | C29: 002 Public Sales | D29: W-Transact (0212) - Hard | E29: 2825966 | F29: 2122276.4 | G29: 3718994 | H29: 3403502.7 | I29: 2640383.2 | J29: 3250473.7 | K29: 3442464.3 | L29: 3505965.2 | M29: 3144842.6 | N29: 3335858.2 | O29: 3285919 | P29: 3515627.1 | Q29: 38192272
A30: Jutik | B30: Revenue | C30: 003 Residential Sales | D30: W-Transact (0211) - Soft | E30: 3037913.4 | F30: 3356447.1 | G30: 2922918.5 | H30: 2583765.4 | I30: 2838412 | J30: 2419259.3 | K30: 3700649.1 | L30: 3768912.5 | M30: 3380705.8 | N30: 3586047.5 | O30: 3032362.9 | P30: 3079299.1 | Q30: 37706693
D31: Total Jutik | E31: 12716847 | F31: 13050244 | G31: 13235473 | H31: 11815762 | I31: 11881724 | J31: 11127132 | K31: 15491089 | L31: 15776843 | M31: 14151792 | N31: 15011362 | O31: 14286635 | P31: 15120322 | Q31: 1.6366523e+08
A34: You've now calculated the Revenues for each of the three desalination plants (Kootha, Surjek and Jutik). This has given you a micro-view of the trends, but let's take a look at the macro-revenue trends and view all this information aggregated together. In the next question, you're aggregating the revenues at the Accounting Code Centre Level, where in the previous question, we went all the way to the Accounting Code Centre Element Level.
A35: Q2. Now, revise , use the SUM Function, calculate the monthly revenues for Kootha, Surjek and Jutik at the Accounting Code Centre Level and put this in the table below. You should make one formula for each cell in column E, then drag it across to populate the remaining columns
A36: Unit | B36: Account Type | C36: Accounting Code Centre | D36: 41456 | E36: 41487 | F36: 41518 | G36: 41548 | H36: 41579 | I36: 41609 | J36: 41640 | K36: 41671 | L36: 41699 | M36: 41730 | N36: 41760 | O36: 41791
P37: Total
A38: Kootha | B38: Revenue | C38: 001 Private Water Hedge Sales | D38: =SUM(E14:E15) -> 3094537 | E38: =SUM(F14:F15) -> 2980521.8 | F38: =SUM(G14:G15) -> 2752413.7 | G38: =SUM(H14:H15) -> 2732151.9 | H38: =SUM(I14:I15) -> 2885028 | I38: =SUM(J14:J15) -> 2815308.4 | J38: =SUM(K14:K15) -> 4092821.4 | K38: =SUM(L14:L15) -> 3622839.6 | ... O38: =SUM(P14:P15) -> 2712379.2 | P38: =SUM(D38:O38) -> 37118739
A39: Kootha | B39: Revenue | C39: 002 Public Sales | D39: =SUM(E16:E17) -> 1523285.8 | E39: =SUM(F16:F17) -> 1467161.9 | F39: =SUM(G16:G17) -> 1354875.7 | G39: =SUM(H16:H17) -> 1344901.8 | H39: =SUM(I16:I17) -> 1420155 | I39: =SUM(J16:J17) -> 1385835.5 | J39: =SUM(K16:K17) -> 2014691.3 | K39: =SUM(L16:L17) -> 1783342.8 | ... O39: =SUM(P16:P17) -> 1335168.7 | P39: =SUM(D39:O39) -> 18271699
A40: Kootha | B40: Revenue | C40: 003 Residential Sales | D40: =SUM(E18) -> 1296758.4 | E40: =SUM(F18) -> 1248980.6 | F40: =SUM(G18) -> 1153392.4 | G40: =SUM(H18) -> 1144901.8 | H40: =SUM(I18) -> 1208964.1 | I40: =SUM(J18) -> 1179748.3 | J40: =SUM(K18) -> 1715087 | K40: =SUM(L18) -> 1518142.3 | ... O40: =SUM(P18) -> 1136616 | P40: =SUM(D40:O40) -> 15554519
A41: Surjek | B41: Revenue | C41: 001 Private Water Hedge Sales | D41: =SUM(E20:E21) -> 7220021.2 | E41: =SUM(F20:F21) -> 6085131 | F41: =SUM(G20:G21) -> 6723291.7 | G41: =SUM(H20:H21) -> 6313180.5 | H41: =SUM(I20:I21) -> 5763708.7 | I41: =SUM(J20:J21) -> 6484566.5 | J41: =SUM(K20:K21) -> 9314190.7 | K41: =SUM(L20:L21) -> 6750396.1 | ... O41: =SUM(P20:P21) -> 6735069.7 | P41: =SUM(D41:O41) -> 82448062
A42: Surjek | B42: Revenue | C42: 002 Public Sales | D42: =SUM(E22:E23) -> 5968550.9 | E42: =SUM(F22:F23) -> 5030375 | F42: =SUM(G22:G23) -> 5557921.2 | G42: =SUM(H22:H23) -> 5218895.9 | H42: =SUM(I22:I23) -> 4764665.8 | I42: =SUM(J22:J23) -> 5360575 | J42: =SUM(K22:K23) -> 7699731 | K42: =SUM(L22:L23) -> 6985660.8 | ... O42: =SUM(P22:P23) -> 5567657.6 | P42: =SUM(D42:O42) -> 70562398
A43: Surjek | B43: Revenue | C43: 003 Residential Sales | D43: =SUM(E24) -> 4139478.8 | E43: =SUM(F24) -> 3488808.4 | F43: =SUM(G24) -> 3854687.3 | G43: =SUM(H24) -> 3619556.8 | H43: =SUM(I24) -> 3304526.3 | I43: =SUM(J24) -> 3717818.1 | J43: =SUM(K24) -> 5340136 | K43: =SUM(L24) -> 4844893.8 | ... O43: =SUM(P24) -> 3861440 | P43: =SUM(D43:O43) -> 49244889
A44: Jutik | B44: Revenue | C44: 001 Private Water Hedge Sales | D44: =SUM(E26:E27) -> 5298686.2 | E44: =SUM(F26:F27) -> 5854268.3 | F44: =SUM(G26:G27) -> 5098113.7 | G44: =SUM(H26:H27) -> 4506567.6 | H44: =SUM(I26:I27) -> 4950718.5 | I44: =SUM(J26:J27) -> 4219638.3 | J44: =SUM(K26:K27) -> 6454620.6 | K44: =SUM(L26:L27) -> 6573684.7 | ... O44: =SUM(P26:P27) -> 6591800.8 | P44: =SUM(D44:O44) -> 67860511
A45: Jutik | B45: Revenue | C45: 002 Public Sales | D45: =SUM(E28:E29) -> 4380247.2 | E45: =SUM(F28:F29) -> 3839528.4 | F45: =SUM(G28:G29) -> 5214440.7 | G45: =SUM(H28:H29) -> 4725429.2 | H45: =SUM(I28:I29) -> 4092594 | I45: =SUM(J28:J29) -> 4488234.3 | J45: =SUM(K28:K29) -> 5335819.7 | K45: =SUM(L28:L29) -> 5434246 | ... O45: =SUM(P28:P29) -> 5449222 | P45: =SUM(D45:O45) -> 58098022
A46: Jutik | B46: Revenue | C46: 003 Residential Sales | D46: =SUM(E30) -> 3037913.4 | E46: =SUM(F30) -> 3356447.1 | F46: =SUM(G30) -> 2922918.5 | G46: =SUM(H30) -> 2583765.4 | H46: =SUM(I30) -> 2838412 | I46: =SUM(J30) -> 2419259.3 | J46: =SUM(K30) -> 3700649.1 | K46: =SUM(L30) -> 3768912.5 | ... O46: =SUM(P30) -> 3079299.1 | P46: =SUM(D46:O46) -> 37706693
A49: Having performed some basic time series analysis where we've analyzed the data at a monthly level; it's time to visualize this using some charts.
A50: Whilst tables are an excellent way to visualize data, charts are more intuitive and allow us to identify specific trends that aren't as apparent in tabular form.
A51: Q3. Create one line chart for each unit (Kootha, Surjek, Jutik) depicting the sales for 001 Private Water Hedge Sales, 002 Public Sales and 003 Residential Sales from the July-13 to Jun-14 period. Do you notice any period where sales are particularly high?
A52: Note: you must redo all the example charts throughout this assignment. The examples are there just to help you see if you are going in the right direction.
A65: In the previous exercise we've picked up some trends from observing the monthly revenues trended over a twelve month period.
A66: Specifically, it's clear that one of the Unit(s) generates the majority of the revenues for Southern Water Corp.
A67: However, it's important for us to understand the contribution each customer segment provides from a % standpoint as well as a dollar stand point.
A68: Let's close out the Revenue Analysis with the below question. This question has three parts.
A69: Q4, Part 1: Using the results from the totals column in Q2 above, create sums for each cell in the table below using the SUM function.
B71: 001 Private Water Hedge Sales | C71: 002 Public Sales | D71: 003 Residential Sales | E71: Total
A72: Kootha | B72: =SUM(P38) -> 37118739 | C72: =SUM(P39) -> 18271699 | D72: =SUM(P40) -> 15554519 | E72: =SUM(B72:D72) -> 70944957
A73: Surjek | B73: =SUM(P41) -> 82448062 | C73: =SUM(P42) -> 70562398 | D73: =SUM(P43) -> 49244889 | E73: =SUM(B73:D73) -> 2.0225535e+08
A74: Jutik | B74: =SUM(P44) -> 67860511 | C74: =+SUM(P45) -> 58098022 | D74: =SUM(P46) -> 37706693 | E74: =SUM(B74:D74) -> 1.6366523e+08
A76: Q4, Part 2: Now, using the table you created in Part 1, calculate the overall % contribution of each customer segment for each of the three (3) units listed below by creating an excel formula. You will be dividing each item in columns B, C and D in Part 1 by the amount in the Total column in Part 1
A77: Challenge: Use absolute referrencing and/or mixed referencing in your formulas to minimize the amount of times you need to recreate the formula
B79: 001 Private Water Hedge Sales | C79: 002 Public Sales | D79: 003 Residential Sales | E79: Total
A80: Kootha | B80: =B72/E72 -> 0.52320475 | C80: =C72/E72 -> 0.25754754 | D80: =D72/E72 -> 0.21924771 | E80: =SUM(B80:D80) -> 1
A81: Surjek | B81: =B73/E73 -> 0.40764342 | C81: =C73/E73 -> 0.34887778 | D81: =D73/E73 -> 0.2434788 | E81: =SUM(B81:D81) -> 1
A82: Jutik | B82: =B74/E74 -> 0.41462999 | C82: =C74/E74 -> 0.35498086 | D82: =D74/E74 -> 0.23038915 | E82: =SUM(B82:D82) -> 1
A84: Q4, Part 3: Create two (2) stacked column chart showing the contributions that each customer segment provides per unit on a dollar basis, and a percentage basis. Then create the charts shown below on your own.
A85: Reminder: you must redo all the example charts throughout this entire assignment. The examples are there just to help you see if you are going in the right direction.

Sheet Expenses Analysis
A1: Expenses Analysis - Part II
A2: Expense Analysis speaks primarily to understanding which product(s) are the most expensive to operate and maintain.
A3: Think about this as your personal budget; You want to know exactly where your money is being spent.
A4: As we mentioned in the last section; we've calculated the revenues and know which of our products generate the most revenues at a Unit Level (Kootha, Surjek, Jutik). But it is equally important for us to understand what is our expenses at a unit level. If our expenses outweigh our revenues - this is not a good outcome.If a product generates a lot of revenues, but the expenses are greater than the revenues - this isn't a good news story.
A6: Now let's take a look at how Southern Water Corps Expenses look like by calculating the Expenses for each of the Units and asking ourselves - what does the data tell us?
A7: Note: You may notice some trends with respect to higher costs for those units which produce a specific type of water.
A8: Let's get started!
A10: Q5. For each of the three Southern Water Corp. Desalination Plants, they produce desalinated water which is then consumed via private, public or residential usage. These costs are then aggregated at a Unit Level, separated into Chemical Costs, Facility Costs, Operational Maintenance Costs and Labour Costs. Please calculate the monthly expenses for Kootha, Surjek and Jutik and put this in the table below.
A11: To make fill in this chart, use the same Pivot Table you created previously which should be in the Tab you created "Pivot Table 1" but now filter it to include only the Expense Value Driver
A12: Unit | B12: Account Type | C12: Accounting Code Centre | D12: Accounting Code Centre Element | F12: 41456 | G12: 41487 | H12: 41518 | I12: 41548 | J12: 41579 | K12: 41609 | L12: 41640 | M12: 41671 | N12: 41699 | O12: 41730 | P12: 41760 | Q12: 41791 | R12: Total
A15: Kootha | B15: Expenses | C15: Chemical Costs | D15: Chem-Exp (001) | F15: 593751.84 | G15: 820393.03 | H15: 642291.58 | I15: 609639.97 | J15: 626073.17 | K15: 602153.38 | L15: 1146144 | M15: 964931.84 | N15: 962733.96 | O15: 964825.22 | P15: 1024534.8 | Q15: 1168045.2 | R15: =SUM(F15:Q15) -> 10125518
A16: Kootha | B16: Expenses | C16: Facility Costs | D16: Utility-Exp (002) - Heating | F16: 276807.38 | G16: 382467.61 | H16: 299436.64 | I16: 284214.44 | J16: 291875.6 | K16: 280724.19 | L16: 534332.86 | M16: 449851.67 | N16: 448827.02 | O16: 449801.97 | P16: 477638.59 | Q16: 544543.23 | R16: =SUM(F16:Q16) -> 4720521.2
A17: Kootha | B17: Expenses | C17: Facility Costs | D17: Utility-Exp (002) - Electricity | F17: 415211.08 | G17: 573701.42 | H17: 449154.95 | I17: 426321.66 | J17: 437813.4 | K17: 421086.28 | L17: 801499.29 | M17: 674777.51 | N17: 673240.53 | O17: 674702.95 | P17: 716457.89 | Q17: 816814.84 | R17: =SUM(F17:Q17) -> 7080781.8
A18: Kootha | B18: Expenses | C18: Operational Maintenance Costs | D18: Plant Maintenance (001) | F18: 360688.41 | G18: 498366.89 | H18: 390175.01 | I18: 370340.03 | J18: 380322.76 | K18: 365792.12 | L18: 459526.26 | M18: 386872.44 | N18: 385991.24 | O18: 386829.69 | P18: 410769.19 | Q18: 468307.18 | R18: =SUM(F18:Q18) -> 4863981.2
A19: Kootha | B19: Expenses | C19: Operational Maintenance Costs | D19: Plant Outages (002) | F19: 226478.77 | G19: 312928.05 | H19: 244993.61 | I19: 232539.09 | J19: 238807.31 | K19: 229683.42 | L19: 288539.74 | M19: 242919.9 | N19: 242366.59 | O19: 242893.06 | P19: 257924.84 | Q19: 294053.34 | R19: =SUM(F19:Q19) -> 3054127.7
A20: Kootha | B20: Expenses | C20: Operational Maintenance Costs | D20: Plant Op. Costs (003) | F20: 255837.13 | G20: 353492.8 | H20: 276752.04 | I20: 262683.04 | J20: 269763.82 | K20: 259457.2 | L20: 325943.04 | M20: 274409.52 | N20: 273784.48 | O20: 274379.2 | P20: 291359.54 | Q20: 332171.37 | R20: =SUM(F20:Q20) -> 3450033.2
A21: Kootha | B21: Expenses | C21: Operational Maintenance Costs | D21: Plant Admin Costs (004) | F21: 176150.15 | G21: 243388.48 | H21: 190550.59 | I21: 180863.73 | J21: 185739.02 | K21: 178642.66 | L21: 224419.8 | M21: 188937.7 | N21: 188507.35 | O21: 188916.83 | P21: 200608.21 | Q21: 228708.16 | R21: =SUM(F21:Q21) -> 2375432.7
A22: Kootha | B22: Expenses | C22: Labour Costs | D22: Labour-Costs (001) | F22: 1153364.1 | G22: 1593615.1 | H22: 1247652.6 | I22: 1184226.8 | J22: 1216148.3 | K22: 1169684.1 | L22: 1469415.4 | M22: 1237092.1 | N22: 1234274.3 | O22: 1236955.4 | P22: 1313506.1 | Q22: 1497493.9 | R22: =SUM(F22:Q22) -> 15553428
A23: Total | D23: Total | F23: =SUM(F15:F22) -> 3458288.9 | G23: =SUM(G15:G22) -> 4778353.4 | H23: =SUM(H15:H22) -> 3741007.1 | I23: =SUM(I15:I22) -> 3550828.8 | J23: =SUM(J15:J22) -> 3646543.4 | K23: =SUM(K15:K22) -> 3507223.4 | L23: =SUM(L15:L22) -> 5249820.3 | M23: =SUM(M15:M22) -> 4419792.7 | ... R23: =SUM(R15:R22) -> 51223824
A24: Surjek | B24: Expenses | C24: Chemical Costs | D24: Chem-Exp (001) | F24: 2533034.5 | G24: 3051574.2 | H24: 3084202.8 | I24: 4135202.8 | J24: 4473275.9 | K24: 3464957.9 | L24: 4049642.8 | M24: 4767948.2 | N24: 4346722.8 | O24: 4671541.1 | P24: 5478104.6 | Q24: 2269805.2 | R24: =SUM(F24:Q24) -> 46326013
A25: Surjek | B25: Expenses | C25: Facility Costs | D25: Utility-Exp (002) - Heating | F25: 1266517.3 | G25: 1525787.1 | H25: 1542101.4 | I25: 2067601.4 | J25: 2236637.9 | K25: 1732479 | L25: 2024821.4 | M25: 2383974.1 | N25: 2173361.4 | O25: 2335770.6 | P25: 2739052.3 | Q25: 1134902.6 | R25: =SUM(F25:Q25) -> 23163006
A26: Surjek | B26: Expenses | C26: Facility Costs | D26: Utility-Exp (002) - Electricity | F26: 1055431 | G26: 1271489.2 | H26: 1285084.5 | I26: 1723001.2 | J26: 1863865 | K26: 1443732.5 | L26: 1687351.2 | M26: 1986645.1 | N26: 1811134.5 | O26: 1946475.5 | P26: 2282543.6 | Q26: 945752.15 | R26: =SUM(F26:Q26) -> 19302505
A27: Surjek | B27: Expenses | C27: Operational Maintenance Costs | D27: Plant Maintenance (001) | F27: 996326.91 | G27: 1200285.8 | H27: 1213119.8 | I27: 1626513.1 | J27: 1759488.5 | K27: 1362883.5 | L27: 1592859.5 | M27: 1875393 | N27: 1709711 | O27: 1837472.8 | P27: 2154721.1 | Q27: 892790.03 | R27: =SUM(F27:Q27) -> 18221565
A28: Surjek | B28: Expenses | C28: Operational Maintenance Costs | D28: Plant Outages (002) | F28: 869931.04 | G28: 1048015.4 | H28: 1059221.1 | I28: 1420170.6 | J28: 1536276.6 | K28: 785390.46 | L28: 734335.23 | M28: 864587.94 | N28: 788205.74 | O28: 847106.12 | P28: 993362.97 | Q28: 514489.17 | R28: =SUM(F28:Q28) -> 11461092
A29: Surjek | B29: Expenses | C29: Operational Maintenance Costs | D29: Plant Op. Costs (003) | F29: 921103.46 | G29: 1109663.3 | H29: 1121528.3 | I29: 1503710.1 | J29: 1626645.8 | K29: 831589.9 | L29: 777531.42 | M29: 915446.06 | N29: 834570.78 | O29: 896935.9 | P29: 1051796.1 | Q29: 544753.24 | R29: =SUM(F29:Q29) -> 12135274
A30: Surjek | B30: Expenses | C30: Operational Maintenance Costs | D30: Plant Admin Costs (004) | F30: 498931.04 | G30: 601067.64 | H30: 607494.48 | I30: 814509.64 | J30: 881099.8 | K30: 450444.53 | L30: 421162.85 | M30: 495866.62 | N30: 452059.17 | O30: 485840.28 | P30: 569722.88 | Q30: 295074.67 | R30: =SUM(F30:Q30) -> 6573273.6
A31: Surjek | B31: Expenses | C31: Labour Costs | D31: Labour-Costs (001) | F31: 3198275.9 | G31: 3852997.7 | H31: 3894195.4 | I31: 5221215.6 | J31: 5648075.6 | K31: 2887464.9 | L31: 2699761.9 | M31: 3178632.1 | N31: 2897815.2 | O31: 3114360.8 | P31: 3652069.7 | Q31: 1891504.3 | R31: =SUM(F31:Q31) -> 42136369
D32: Total | F32: =SUM(F24:F31) -> 11339551 | G32: =SUM(G24:G31) -> 13660880 | H32: =SUM(H24:H31) -> 13806948 | I32: =SUM(I24:I31) -> 18511924 | J32: =SUM(J24:J31) -> 20025365 | K32: =SUM(K24:K31) -> 12958943 | L32: =SUM(L24:L31) -> 13987466 | M32: =SUM(M24:M31) -> 16468493 | ... R32: =SUM(R24:R31) -> 1.793191e+08
A33: Jutik | B33: Expenses | C33: Chemical Costs | D33: Chem-Exp (001) | F33: 1625596.3 | G33: 1295067.8 | H33: 1750624.9 | I33: 1472529.4 | J33: 1252200.5 | K33: 1406782.7 | L33: 1877449.5 | M33: 1912219.2 | N33: 2266625.2 | O33: 2234200.6 | P33: 2593715.6 | Q33: 2274807.8 | R33: =SUM(F33:Q33) -> 21961819
A34: Jutik | B34: Expenses | C34: Facility Costs | D34: Utility-Exp (002) - Heating | F34: 895736.76 | G34: 713608.81 | H34: 964630.04 | I34: 811393.74 | J34: 689988.03 | K34: 775165.96 | L34: 1034513 | M34: 888365.67 | N34: 1248956.7 | O34: 680069.7 | P34: 878169.84 | Q34: 1253465.5 | R34: =SUM(F34:Q34) -> 10834064
A35: Jutik | B35: Expenses | C35: Facility Costs | D35: Utility-Exp (002) - Electricity | F35: 829385.89 | G35: 660748.9 | H35: 893175.96 | I35: 751290.5 | J35: 638877.8 | K35: 717746.26 | L35: 957882.4 | M35: 822560.8 | N35: 1156441.4 | O35: 629694.17 | P35: 813120.23 | Q35: 1160616.2 | R35: =SUM(F35:Q35) -> 10031541
A36: Jutik | B36: Expenses | C36: Operational Maintenance Costs | D36: Plant Maintenance (001) | F36: 716589.41 | G36: 570887.05 | H36: 771704.03 | I36: 649115 | J36: 551990.42 | K36: 620132.77 | L36: 827610.39 | M36: 710692.53 | N36: 999165.39 | O36: 544055.76 | P36: 702535.88 | Q36: 1002772.4 | R36: =SUM(F36:Q36) -> 8667251
A37: Jutik | B37: Expenses | C37: Operational Maintenance Costs | D37: Plant Outages (002) | F37: 251329.06 | G37: 200226.94 | H37: 270659.38 | I37: 227663.79 | J37: 193599.33 | K37: 143549.25 | L37: 153261.18 | M37: 131609.73 | N37: 185030.63 | O37: 100751.07 | P37: 130099.24 | Q37: 232123.24 | R37: =SUM(F37:Q37) -> 2219902.8
A38: Jutik | B38: Expenses | C38: Operational Maintenance Costs | D38: Plant Op. Costs (003) | F38: 623296.06 | G38: 496562.81 | H38: 671235.27 | I38: 564606.2 | J38: 480126.35 | K38: 356002.15 | L38: 380087.74 | M38: 326392.13 | N38: 458875.96 | O38: 249862.65 | P38: 322646.11 | Q38: 575665.64 | R38: =SUM(F38:Q38) -> 5505359
A39: Jutik | B39: Expenses | C39: Operational Maintenance Costs | D39: Plant Admin Costs (004) | F39: 211116.41 | G39: 168190.63 | H39: 227353.88 | I39: 191237.58 | J39: 162623.44 | K39: 120581.37 | L39: 128739.39 | M39: 110552.17 | N39: 155425.73 | O39: 84630.897 | P39: 109283.36 | Q39: 194983.52 | R39: =SUM(F39:Q39) -> 1864718.4
A40: Jutik | B40: Expenses | C40: Labour Costs | D40: Labour-Costs (001) | F40: 3015948.7 | G40: 2402723.3 | H40: 3247912.6 | I40: 2731965.5 | J40: 2323192 | K40: 1722591 | L40: 1839134.2 | M40: 2579316.7 | N40: 2220367.5 | O40: 2209012.8 | P40: 2561190.8 | Q40: 2785478.9 | R40: =SUM(F40:Q40) -> 29638834
D41: Total | F41: =SUM(F33:F40) -> 8168998.6 | G41: =SUM(G33:G40) -> 6508016.3 | H41: =SUM(H33:H40) -> 8797296 | I41: =SUM(I33:I40) -> 7399801.7 | J41: =SUM(J33:J40) -> 6292597.9 | K41: =SUM(K33:K40) -> 5862551.5 | L41: =SUM(L33:L40) -> 7198677.8 | M41: =SUM(M33:M40) -> 7481709 | ... R41: =SUM(R33:R40) -> 90723489
A42: You've now calculated the Expenses for each of the three desalination plants (Kootha, Surjek and Jutik). This has given you a micro-view of the trends, but let's take a look at the macro-expenses trends and view all this information aggregated together (Kootha + Surjek + Jutik) and then. Is there any particular trend(s) that we can pick up with respect to which water product(s) have the highest expenses overall?
A43: Q6, Part 1. Using the tables you created in Q5, complete the table below, aggregating all the costs for all units for the respective Accounting Code Centre and Accounting Code Centre Elements. You should be able to create one formula using the SUM function and then drag it across and down to populate the entire table.
B44: Unit | C44: Account Type | D44: Accounting Code Centre | E44: Accounting Code Centre Element | F44: 41456 | G44: 41487 | H44: 41518 | I44: 41548 | J44: 41579 | K44: 41609 | L44: 41640 | M44: 41671 | N44: 41699 | O44: 41730 | P44: 41760 | Q44: 41791
R45: Total
B46: All | C46: Expenses | D46: Chemical Costs | E46: Chem-Exp (001) | F46: =SUM(F15,F24,F33) -> 4752382.7 | G46: =SUM(G15,G24,G33) -> 5167035 | H46: =SUM(H15,H24,H33) -> 5477119.2 | I46: =SUM(I15,I24,I33) -> 6217372.1 | J46: =SUM(J15,J24,J33) -> 6351549.6 | K46: =SUM(K15,K24,K33) -> 5473894 | L46: =SUM(L15,L24,L33) -> 7073236.3 | M46: =SUM(M15,M24,M33) -> 7645099.2 | ... Q46: =SUM(Q15,Q24,Q33) -> 5712658.2 | R46: =SUM(F46:Q46) -> 78413350
B47: All | C47: Expenses | D47: Facility Costs | E47: Utility-Exp (002) - Heating | F47: =SUM(F16,F25,F34) -> 2439061.4 | G47: =SUM(G16,G25,G34) -> 2621863.5 | H47: =SUM(H16,H25,H34) -> 2806168.1 | I47: =SUM(I16,I25,I34) -> 3163209.6 | J47: =SUM(J16,J25,J34) -> 3218501.6 | K47: =SUM(K16,K25,K34) -> 2788369.1 | L47: =SUM(L16,L25,L34) -> 3593667.3 | M47: =SUM(M16,M25,M34) -> 3722191.5 | ... Q47: =SUM(Q16,Q25,Q34) -> 2932911.3 | R47: =SUM(F47:Q47) -> 38717591
B48: All | C48: Expenses | D48: Facility Costs | E48: Utility-Exp (002) - Electricity | F48: =SUM(F17,F26,F35) -> 2300028 | G48: =SUM(G17,G26,G35) -> 2505939.6 | H48: =SUM(H17,H26,H35) -> 2627415.4 | I48: =SUM(I17,I26,I35) -> 2900613.3 | J48: =SUM(J17,J26,J35) -> 2940556.2 | K48: =SUM(K17,K26,K35) -> 2582565 | L48: =SUM(L17,L26,L35) -> 3446732.9 | M48: =SUM(M17,M26,M35) -> 3483983.4 | ... Q48: =SUM(Q17,Q26,Q35) -> 2923183.2 | R48: =SUM(F48:Q48) -> 36414828
B49: All | C49: Expenses | D49: Operational Maintenance Costs | E49: Plant Maintenance (001) | F49: =SUM(F18,F27,F36) -> 2073604.7 | G49: =SUM(G18,G27,G36) -> 2269539.8 | H49: =SUM(H18,H27,H36) -> 2374998.8 | I49: =SUM(I18,I27,I36) -> 2645968.1 | J49: =SUM(J18,J27,J36) -> 2691801.7 | K49: =SUM(K18,K27,K36) -> 2348808.3 | L49: =SUM(L18,L27,L36) -> 2879996.2 | M49: =SUM(M18,M27,M36) -> 2972957.9 | ... Q49: =SUM(Q18,Q27,Q36) -> 2363869.6 | R49: =SUM(F49:Q49) -> 31752797
B50: All | C50: Expenses | D50: Operational Maintenance Costs | E50: Plant Outages (002) | F50: =SUM(F19,F28,F37) -> 1347738.9 | G50: =SUM(G19,G28,G37) -> 1561170.4 | H50: =SUM(H19,H28,H37) -> 1574874.1 | I50: =SUM(I19,I28,I37) -> 1880373.5 | J50: =SUM(J19,J28,J37) -> 1968683.2 | K50: =SUM(K19,K28,K37) -> 1158623.1 | L50: =SUM(L19,L28,L37) -> 1176136.2 | M50: =SUM(M19,M28,M37) -> 1239117.6 | ... Q50: =SUM(Q19,Q28,Q37) -> 1040665.8 | R50: =SUM(F50:Q50) -> 16735123
B51: All | C51: Expenses | D51: Operational Maintenance Costs | E51: Plant Op. Costs (003) | F51: =SUM(F20,F29,F38) -> 1800236.6 | G51: =SUM(G20,G29,G38) -> 1959718.9 | H51: =SUM(H20,H29,H38) -> 2069515.6 | I51: =SUM(I20,I29,I38) -> 2330999.3 | J51: =SUM(J20,J29,J38) -> 2376535.9 | K51: =SUM(K20,K29,K38) -> 1447049.3 | L51: =SUM(L20,L29,L38) -> 1483562.2 | M51: =SUM(M20,M29,M38) -> 1516247.7 | ... Q51: =SUM(Q20,Q29,Q38) -> 1452590.3 | R51: =SUM(F51:Q51) -> 21090667
B52: All | C52: Expenses | D52: Operational Maintenance Costs | E52: Plant Admin Costs (004) | F52: =SUM(F21,F30,F39) -> 886197.6 | G52: =SUM(G21,G30,G39) -> 1012646.7 | H52: =SUM(H21,H30,H39) -> 1025398.9 | I52: =SUM(I21,I30,I39) -> 1186611 | J52: =SUM(J21,J30,J39) -> 1229462.3 | K52: =SUM(K21,K30,K39) -> 749668.57 | L52: =SUM(L21,L30,L39) -> 774322.05 | M52: =SUM(M21,M30,M39) -> 795356.49 | ... Q52: =SUM(Q21,Q30,Q39) -> 718766.35 | R52: =SUM(F52:Q52) -> 10813425
B53: All | C53: Expenses | D53: Labour Costs | E53: Labour-Costs (001) | F53: =SUM(F22,F31,F40) -> 7367588.7 | G53: =SUM(G22,G31,G40) -> 7849336 | H53: =SUM(H22,H31,H40) -> 8389760.6 | I53: =SUM(I22,I31,I40) -> 9137407.9 | J53: =SUM(J22,J31,J40) -> 9187416 | K53: =SUM(K22,K31,K40) -> 5779740.1 | L53: =SUM(L22,L31,L40) -> 6008311.5 | M53: =SUM(M22,M31,M40) -> 6995041 | ... Q53: =SUM(Q22,Q31,Q40) -> 6174477.1 | R53: =SUM(F53:Q53) -> 87328632
B54: Total | C54: Total | D54: Total | E54: Total | F54: =SUM(F46:F53) -> 22966839 | G54: =SUM(G46:G53) -> 24947250 | H54: =SUM(H46:H53) -> 26345251 | I54: =SUM(I46:I53) -> 29462555 | J54: =SUM(J46:J53) -> 29964506 | K54: =SUM(K46:K53) -> 22328717 | L54: =SUM(L46:L53) -> 26435964 | M54: =SUM(M46:M53) -> 28369995 | ... Q54: =SUM(Q46:Q53) -> 23319122 | R54: =SUM(F54:Q54) -> 3.2126641e+08
A57: Utility Exp (002) - Heating etc.). Check your work against the sample chart below.
A64: In the previous question we've now calculated the aggregate costs per month for all our desalination units (Kootha + Surjek+ Jutik).
A65: Let's now seek to visualize how the aggregate costs per month, compare to the individual unit costs per month.
A66: This helps us to better understand which units are contributing the most expenses.
A67: Q7. Using the total rows from Q5, first populate the table below. Then create one line chart that displays for the Jul-13 to Jun-14 Period, the total costs per month for each unit, Kootha, Surjek and Jutik, as well as the Overall Total per month.
A68: Visualizing the data in this manner - do you see any particular unit that appears to contribute the majority of the costs? (i.e. One unit should emerge as the major contributor.)
D70: Unit | E70: Account Type | F70: 41456 | G70: 41487 | H70: 41518 | I70: 41548 | J70: 41579 | K70: 41609 | L70: 41640 | M70: 41671 | N70: 41699 | O70: 41730 | P70: 41760 | Q70: 41791 | R70: Total
D71: Kootha | E71: Expenses | F71: =SUM(F15:F22) -> 3458288.9 | G71: =SUM(G15:G22) -> 4778353.4 | H71: =SUM(H15:H22) -> 3741007.1 | I71: =SUM(I15:I22) -> 3550828.8 | J71: =SUM(J15:J22) -> 3646543.4 | K71: =SUM(K15:K22) -> 3507223.4 | L71: =SUM(L15:L22) -> 5249820.3 | M71: =SUM(M15:M22) -> 4419792.7 | ... Q71: =SUM(Q15:Q22) -> 5350137.2 | R71: 51223824
D72: Surjek | E72: Expenses | F72: =SUM(F24:F31) -> 11339551 | G72: =SUM(G24:G31) -> 13660880 | H72: =SUM(H24:H31) -> 13806948 | I72: =SUM(I24:I31) -> 18511924 | J72: =SUM(J24:J31) -> 20025365 | K72: =SUM(K24:K31) -> 12958943 | L72: =SUM(L24:L31) -> 13987466 | M72: =SUM(M24:M31) -> 16468493 | ... Q72: =SUM(Q24:Q31) -> 8489071.3 | R72: 1.793191e+08
D73: Jutik | E73: Expenses | F73: =SUM(F33:F40) -> 8168998.6 | G73: =SUM(G33:G40) -> 6508016.3 | H73: =SUM(H33:H40) -> 8797296 | I73: =SUM(I33:I40) -> 7399801.7 | J73: =SUM(J33:J40) -> 6292597.9 | K73: =SUM(K33:K40) -> 5862551.5 | L73: =SUM(L33:L40) -> 7198677.8 | M73: =SUM(M33:M40) -> 7481709 | ... Q73: =SUM(Q33:Q40) -> 9479913.3 | R73: 90723489
D74: Overall | E74: Expenses | F74: =SUM(F23,F32,F41) -> 22966839 | G74: =SUM(G23,G32,G41) -> 24947250 | H74: =SUM(H23,H32,H41) -> 26345251 | I74: =SUM(I23,I32,I41) -> 29462555 | J74: =SUM(J23,J32,J41) -> 29964506 | K74: =SUM(K23,K32,K41) -> 22328717 | L74: =SUM(L23,L32,L41) -> 26435964 | M74: =SUM(M23,M32,M41) -> 28369995 | ... P74: =SUM(P23,P32,P41) -> 31724934 | Q74: =SUM(Q23,Q76,Q41) -> 14830050 | R74: 3.2126641e+08
A94: In the previous question, we've calculated the expenses at an aggregate level. You would have noticed some particularly high-costs for certain units that you'd be keen to dive into in more detail from a visual stand point. Let's do so!
A95: Q8. Using the Totals for the Year Column (Column R) for each Unit (Kootha, Surjek and Jutik), create a chart which clearly shows the Total Costs for each Cost Element. This is similar to Q6, Part 2 except now you are doing it for each Unit rather than the company as a whole. You will end up with three (3) Column Charts that will let you see which of the Units Accounting Code Centre Elements drive the majority of costs. What trends have you noticed?
A120: We've analysed the expenses data and we have a few questions. The costs for two of our Cost Elements is particularly high - could this potentially be related to the periods of high water production?
A121: We can answer this question by using the Water Production Data that is available in the Data Repository Table.
A122: However, it is important to note that for the water production data, it has been aggregated. This means we cannot see the separation between Soft / Hard Water Production.
A123: This means in the analysis you will complete below, you can only make logical assumptions. As a Data Analyst, you will not always have all the data you need to make a conclusion.
A124: In cases like the one below, you will have to draw on logical conclusions from the data available to you and make a conclusion.
A126: Q9. For this question, you will need to create a new Pivot Table which you should do in a new tab called "Pivot Table 2." Use that to complete the table below that will show the monthly water production for each Unit as well as the monthly chemical expenditure. Use Pivot Table filters for Account Type and Accounting Code Centre Element to help you find the right row Once the table is complete, create two charts for each unit, showing the Chemical Costs and Water Production. What trends emerge when looking at the data in this manner? We've included an example for you so you can see what the Chart should look like!
A128: Account Type | B128: Unit | C128: Accounting Code Centre | D128: Accounting Code Centre Element | E128: 41456 | F128: 41487 | G128: 41518 | H128: 41548 | I128: 41579 | J128: 41609 | K128: 41640 | L128: 41671 | M128: 41699 | N128: 41730 | O128: 41760 | P128: 41791
A129: Expenses | B129: Kootha | C129: Chemical Costs | D129: Chem-Exp (001) | E129: 593751.84 | F129: 820393.03 | G129: 642291.58 | H129: 609639.97 | I129: 626073.17 | J129: 602153.38 | K129: 1146144 | L129: 964931.84 | M129: 962733.96 | N129: 964825.22 | O129: 1024534.8 | P129: 1168045.2
A130: Water Production Actuals | B130: Kootha | C130: None | D130: None | E130: 181.93329 | F130: 187.44394 | G130: 184.77366 | H130: 191.54109 | I130: 98.096062 | J130: 185.30685 | K130: 186.90144 | L130: 158.58677 | M130: 191.40368 | N130: 171.05786 | O130: 169.287 | P130: 142.50872
A131: Expenses | B131: Surjek | C131: Chemical Costs | D131: Chem-Exp (001) | E131: 2533034.5 | F131: 3051574.2 | G131: 3084202.8 | H131: 4135202.8 | I131: 4473275.9 | J131: 3464957.9 | K131: 4049642.8 | L131: 4767948.2 | M131: 4346722.8 | N131: 4671541.1 | O131: 5478104.6 | P131: 2269805.2
A132: Water Production Actuals | B132: Surjek | C132: None | D132: None | E132: 214.969 | F132: 228.19905 | G132: 216.53647 | H132: 236.76028 | I132: 232.05286 | J132: 240.21016 | K132: 288.16055 | L132: 306.88452 | M132: 367.65101 | N132: 351.99017 | O132: 362.822 | P132: 260.3123
A133: Expenses | B133: Jutik | C133: Chemical Costs | D133: Chem-Exp (001) | E133: 1625596.3 | F133: 1295067.8 | G133: 1750624.9 | H133: 1472529.4 | I133: 1252200.5 | J133: 1406782.7 | K133: 1877449.5 | L133: 1912219.2 | M133: 2266625.2 | N133: 2234200.6 | O133: 2593715.6 | P133: 2274807.8
A134: Water Production Actuals | B134: Jutik | C134: None | D134: None | E134: 250.24199 | F134: 206.7407 | G134: 201.23546 | H134: 174.36957 | I134: 204.09105 | J134: 146.35667 | K134: 204.2025 | L134: 217.4302 | M134: 230.9822 | N134: 236.44114 | O134: 241.40737 | P134: 220.38033
F137: Kootha Chemical Cost Column Chart | K137: Surjek Chemical Cost Column Chart | P137: Jutik Chemical Cost Column Chart
F157: Kootha Water Production Volumes | K157: Surjek Water Production Volumes | P157: Jutik Water Production Volumes

Sheet Profitability EBIT Analysis
A1: EBIT Analysis - Part III.
A2: In Financial Data Analysis, EBIT Analysis, also known as Profitability Analysis, speaks primarily to understanding which product(s) are the most cashflow positive.
A3: We're now at the final stage of the puzzle (Woo!); We've got the Revenues. We've got the Expenses. All that is now left is the EBIT and we're done!
A4: Once we subtract our Expenses from our Revenues - we can find out how financially sound Southern Water Corp's Units actually are. Let's take one final look at Southern Water Corp's Data for the 2013 - 2014 Period and find out just how profitable the Unit(s) actually are. Additionally, we'll explore how we can use Ratio's to help us show which Unit(s) are most cost-effective from a Revenue to Expenses perspective.
A6: Let's get started!
A8: EBIT can be simply calculated as Revenues - COGS - Operating Expenses.
A9: In the Southern Water Corp. Case Study, we have opted to wrap up our COGS as part of our overall Expenses to simplify the calculation for you.
A10: Hence, the EBIT you will calculate will simply be: Revenues - Operating Expenses.
A12: Q10. Using the results from Q1 and Q5, populate Part A: the Revenue rows in the table below. Part B: the Expenses rows in the table below. Part C: Calculate EBIT using the formula EBIT = Revenues - Expenses. You should create a formula in Column E and then drag it across
A13: Upon completion of the table, please create two visuals that showcase: 1) Column Chart showing the Total EBIT (Profit) for Kootha, Surjek and Jutik 2) Line Chart showing the Monthly EBIT (Profit) for Kootha, Surjek and Jutik Are there any particular trend(s) that you're able to pick up / take note of with respect to the EBIT?
A14: Unit | E14: 41456 | F14: 41487 | G14: 41518 | H14: 41548 | I14: 41579 | J14: 41609 | K14: 41640 | L14: 41671 | M14: 41699 | N14: 41730 | O14: 41760 | P14: 41791 | Q14: Total
A15: Part A: Calculate Revenues (Use the results of Q2)
A16: Kootha | E16: =SUM('Revenue Analysis'!D38:D40) -> 5914581.2 | F16: =SUM('Revenue Analysis'!E38:E40) -> 5696664.2 | G16: =SUM('Revenue Analysis'!F38:F40) -> 5260681.8 | H16: =SUM('Revenue Analysis'!G38:G40) -> 5221955.5 | I16: =SUM('Revenue Analysis'!H38:H40) -> 5514147.2 | J16: =SUM('Revenue Analysis'!I38:I40) -> 5380892.2 | K16: =SUM('Revenue Analysis'!J38:J40) -> 7822599.7 | L16: =SUM('Revenue Analysis'!K38:K40) -> 6924324.6 | ... P16: =SUM('Revenue Analysis'!O38:O40) -> 5184163.9 | Q16: =SUM(E16:P16) -> 70944957
A17: Surjek | E17: =SUM('Revenue Analysis'!D41:D43) -> 17328051 | F17: =SUM('Revenue Analysis'!E41:E43) -> 14604314 | G17: =SUM('Revenue Analysis'!F41:F43) -> 16135900 | H17: =SUM('Revenue Analysis'!G41:G43) -> 15151633 | I17: =SUM('Revenue Analysis'!H41:H43) -> 13832901 | J17: =SUM('Revenue Analysis'!I41:I43) -> 15562960 | K17: =SUM('Revenue Analysis'!J41:J43) -> 22354058 | L17: =SUM('Revenue Analysis'!K41:K43) -> 18580951 | ... P17: =SUM('Revenue Analysis'!O41:O43) -> 16164167 | Q17: =SUM(E17:P17) -> 2.0225535e+08
A18: Jutik | E18: =SUM('Revenue Analysis'!D44:D46) -> 12716847 | F18: =SUM('Revenue Analysis'!E44:E46) -> 13050244 | G18: =SUM('Revenue Analysis'!F44:F46) -> 13235473 | H18: =SUM('Revenue Analysis'!G44:G46) -> 11815762 | I18: =SUM('Revenue Analysis'!H44:H46) -> 11881724 | J18: =SUM('Revenue Analysis'!I44:I46) -> 11127132 | K18: =SUM('Revenue Analysis'!J44:J46) -> 15491089 | L18: =SUM('Revenue Analysis'!K44:K46) -> 15776843 | ... P18: =SUM('Revenue Analysis'!O44:O46) -> 15120322 | Q18: =SUM(E18:P18) -> 1.6366523e+08
A19: Part B: Calculate Expenses (Use the results of Q5)
A20: Kootha | E20: =SUM('Expenses Analysis'!F15:F22) -> 3458288.9 | F20: =SUM('Expenses Analysis'!G15:G22) -> 4778353.4 | G20: =SUM('Expenses Analysis'!H15:H22) -> 3741007.1 | H20: =SUM('Expenses Analysis'!I15:I22) -> 3550828.8 | I20: =SUM('Expenses Analysis'!J15:J22) -> 3646543.4 | J20: =SUM('Expenses Analysis'!K15:K22) -> 3507223.4 | K20: =SUM('Expenses Analysis'!L15:L22) -> 5249820.3 | L20: =SUM('Expenses Analysis'!M15:M22) -> 4419792.7 | ... P20: =SUM('Expenses Analysis'!Q15:Q22) -> 5350137.2 | Q20: =SUM(E20:P20) -> 51223824
A21: Surjek | E21: =SUM('Expenses Analysis'!F24:F31) -> 11339551 | F21: =SUM('Expenses Analysis'!G24:G31) -> 13660880 | G21: =SUM('Expenses Analysis'!H24:H31) -> 13806948 | H21: =SUM('Expenses Analysis'!I24:I31) -> 18511924 | I21: =SUM('Expenses Analysis'!J24:J31) -> 20025365 | J21: =SUM('Expenses Analysis'!K24:K31) -> 12958943 | K21: =SUM('Expenses Analysis'!L24:L31) -> 13987466 | L21: =SUM('Expenses Analysis'!M24:M31) -> 16468493 | ... P21: =SUM('Expenses Analysis'!Q24:Q31) -> 8489071.3 | Q21: =SUM(E21:P21) -> 1.793191e+08
A22: Jutik | E22: =SUM('Expenses Analysis'!F33:F40) -> 8168998.6 | F22: =SUM('Expenses Analysis'!G33:G40) -> 6508016.3 | G22: =SUM('Expenses Analysis'!H33:H40) -> 8797296 | H22: =SUM('Expenses Analysis'!I33:I40) -> 7399801.7 | I22: =SUM('Expenses Analysis'!J33:J40) -> 6292597.9 | J22: =SUM('Expenses Analysis'!K33:K40) -> 5862551.5 | K22: =SUM('Expenses Analysis'!L33:L40) -> 7198677.8 | L22: =SUM('Expenses Analysis'!M33:M40) -> 7481709 | ... P22: =SUM('Expenses Analysis'!Q33:Q40) -> 9479913.3 | Q22: =SUM(E22:P22) -> 90723489
A23: Part C: Make a formula to calculate EBIT (EBIT = Revenues - Expenses)
A24: Kootha | E24: =SUM(E16-E20) -> 2456292.3 | F24: =SUM(F16-F20) -> 918310.89 | G24: =SUM(G16-G20) -> 1519674.8 | H24: =SUM(H16-H20) -> 1671126.7 | I24: =SUM(I16-I20) -> 1867603.7 | J24: =SUM(J16-J20) -> 1873668.8 | K24: =SUM(K16-K20) -> 2572779.4 | L24: =SUM(L16-L20) -> 2504531.9 | ... Q24: =SUM(Q16-Q20) -> 19721133
A25: Surjek | E25: =SUM(E17-E21) -> 5988499.8 | F25: =SUM(F17-F21) -> 943434.1 | G25: =SUM(G17-G21) -> 2328952.4 | H25: =SUM(H17-H21) -> -3360291.1 | I25: =SUM(I17-I21) -> -6192464.3 | J25: =SUM(J17-J21) -> 2604017 | K25: =SUM(K17-K21) -> 8366591.3 | L25: =SUM(L17-L21) -> 2112457.6 | ... Q25: =SUM(Q17-Q21) -> 22936250
A26: Jutik | E26: =SUM(E18-E22) -> 4547848.2 | F26: =SUM(F18-F22) -> 6542227.6 | G26: =SUM(G18-G22) -> 4438176.9 | H26: =SUM(H18-H22) -> 4415960.6 | I26: =SUM(I18-I22) -> 5589126.6 | J26: =SUM(J18-J22) -> 5264580.3 | K26: =SUM(K18-K22) -> 8292411.6 | L26: =SUM(L18-L22) -> 8295134.3 | ... Q26: =SUM(Q18-Q22) -> 72941736
S35: Jutik is the most stable and consistently profitable unit.
S36: Kootha shows moderate stability but ends the period with weakening profitability.
S37: Surjek is the most unpredictable, with large losses followed by strong rebounds.
A44: It's pretty clear from our EBIT Analysis, that Jutik generates the highest EBIT. However, total EBIT is only part of the story. EBIT Margin is calculated as EBIT / Revenue. It measures on a percentage basis how much of the revenues is left in the company after paying out expenses. Out of Kootha, Surjek and Jutik - which has the highest overall EBIT Margins? Let's close out our EBIT Analysis and find out!
A45: Q11. Calculate the EBIT Margin for each of the Units below by using the results in Q10. Remember EBIT Margin = EBIT / Revenue. Upon completion of the table, please create two visuals that showcase: 1) Column Chart showing the Total EBIT (Profit) for Kootha, Surjek and Jutik 2) Line Chart showing the Monthly EBIT (Profit) for Kootha, Surjek and Jutik What do you conclude?
A47: EBIT Margin
E48: 41456 | F48: 41487 | G48: 41518 | H48: 41548 | I48: 41579 | J48: 41609 | K48: 41640 | L48: 41671 | M48: 41699 | N48: 41730 | O48: 41760 | P48: 41791 | Q48: Total
A49: Unit
A50: Kootha | E50: =E24/E16 -> 0.41529438 | F50: =F24/F16 -> 0.16120151 | G50: =G24/G16 -> 0.28887411 | H50: =H24/H16 -> 0.32001933 | I50: =I24/I16 -> 0.33869313 | J50: =J24/J16 -> 0.34820784 | K50: =K24/K16 -> 0.32889058 | L50: =L24/L16 -> 0.36170054 | ... Q50: =Q24/Q16 -> 0.27797794
A51: Surjek | E51: =E25/E17 -> 0.34559569 | F51: =F25/F17 -> 0.064599684 | G51: =G25/G17 -> 0.14433359 | H51: =H25/H17 -> -0.22177748 | I51: =I25/I17 -> -0.44766202 | J51: =J25/J17 -> 0.16732145 | K51: =K25/K17 -> 0.37427618 | L51: =L25/L17 -> 0.11368942 | ... Q51: =Q25/Q17 -> 0.11340244
A52: Jutik | E52: =E26/E18 -> 0.35762389 | F52: =F26/F18 -> 0.50131075 | G52: =G26/G18 -> 0.33532439 | H52: =H26/H18 -> 0.37373472 | I52: =I26/I18 -> 0.47039692 | J52: =J26/J18 -> 0.47313004 | K52: =K26/K18 -> 0.53530203 | L52: =L26/L18 -> 0.52577909 | ... Q52: =Q26/Q18 -> 0.44567645
A72: Jutik is the most profitable and operationally efficient unit.
A73: Kootha is moderately profitable but shows signs of declining performance.
A74: Surjek carries the highest risk due to extreme volatility and frequent losses

Sheet Pivot Table 1
A4: Sum of Values2 | E4: Month
A5: Unit | B5: Account Type | C5: Accounting Code Centre | D5: Accounting Code Centre Element | E5: 41456 | F5: 41487 | G5: 41518 | H5: 41548 | I5: 41579 | J5: 41609 | K5: 41640 | L5: 41671 | M5: 41699 | N5: 41730 | O5: 41760 | P5: 41791 | Q5: Grand Total
A6: A) Kootha | B6: Expenses | C6: A)Chemical Costs | D6: Chem-Exp (001) | E6: 593751.84 | F6: 820393.03 | G6: 642291.58 | H6: 609639.97 | I6: 626073.17 | J6: 602153.38 | K6: 1146144 | L6: 964931.84 | M6: 962733.96 | N6: 964825.22 | O6: 1024534.8 | P6: 1168045.2 | Q6: 10125518
C7: B) Facility Costs | D7: Utility-Exp (002) - Heating | E7: 276807.38 | F7: 382467.61 | G7: 299436.64 | H7: 284214.44 | I7: 291875.6 | J7: 280724.19 | K7: 534332.86 | L7: 449851.67 | M7: 448827.02 | N7: 449801.97 | O7: 477638.59 | P7: 544543.23 | Q7: 4720521.2
D8: Utility-Exp (002) - Electricity | E8: 415211.08 | F8: 573701.42 | G8: 449154.95 | H8: 426321.66 | I8: 437813.4 | J8: 421086.28 | K8: 801499.29 | L8: 674777.51 | M8: 673240.53 | N8: 674702.95 | O8: 716457.89 | P8: 816814.84 | Q8: 7080781.8
C9: C) Operational Maintenance Costs | D9: Plant Maintenance (001) | E9: 360688.41 | F9: 498366.89 | G9: 390175.01 | H9: 370340.03 | I9: 380322.76 | J9: 365792.12 | K9: 459526.26 | L9: 386872.44 | M9: 385991.24 | N9: 386829.69 | O9: 410769.19 | P9: 468307.18 | Q9: 4863981.2
D10: Plant Outages (002) | E10: 226478.77 | F10: 312928.05 | G10: 244993.61 | H10: 232539.09 | I10: 238807.31 | J10: 229683.42 | K10: 288539.74 | L10: 242919.9 | M10: 242366.59 | N10: 242893.06 | O10: 257924.84 | P10: 294053.34 | Q10: 3054127.7
D11: Plant Op. Costs (003) | E11: 255837.13 | F11: 353492.8 | G11: 276752.04 | H11: 262683.04 | I11: 269763.82 | J11: 259457.2 | K11: 325943.04 | L11: 274409.52 | M11: 273784.48 | N11: 274379.2 | O11: 291359.54 | P11: 332171.37 | Q11: 3450033.2
D12: Plant Admin Costs (004) | E12: 176150.15 | F12: 243388.48 | G12: 190550.59 | H12: 180863.73 | I12: 185739.02 | J12: 178642.66 | K12: 224419.8 | L12: 188937.7 | M12: 188507.35 | N12: 188916.83 | O12: 200608.21 | P12: 228708.16 | Q12: 2375432.7
C13: D) Labour Costs | D13: Labour-Costs (001) | E13: 1153364.1 | F13: 1593615.1 | G13: 1247652.6 | H13: 1184226.8 | I13: 1216148.3 | J13: 1169684.1 | K13: 1469415.4 | L13: 1237092.1 | M13: 1234274.3 | N13: 1236955.4 | O13: 1313506.1 | P13: 1497493.9 | Q13: 15553428
A14: A) Kootha Total | E14: 3458288.9 | F14: 4778353.4 | G14: 3741007.1 | H14: 3550828.8 | I14: 3646543.4 | J14: 3507223.4 | K14: 5249820.3 | L14: 4419792.7 | M14: 4409725.5 | N14: 4419304.3 | O14: 4692799.2 | P14: 5350137.2 | Q14: 51223824
A15: B) Surjek | B15: Expenses | C15: A)Chemical Costs | D15: Chem-Exp (001) | E15: 2533034.5 | F15: 3051574.2 | G15: 3084202.8 | H15: 4135202.8 | I15: 4473275.9 | J15: 3464957.9 | K15: 4049642.8 | L15: 4767948.2 | M15: 4346722.8 | N15: 4671541.1 | O15: 5478104.6 | P15: 2269805.2 | Q15: 46326013
C16: B) Facility Costs | D16: Utility-Exp (002) - Heating | E16: 1266517.3 | F16: 1525787.1 | G16: 1542101.4 | H16: 2067601.4 | I16: 2236637.9 | J16: 1732479 | K16: 2024821.4 | L16: 2383974.1 | M16: 2173361.4 | N16: 2335770.6 | O16: 2739052.3 | P16: 1134902.6 | Q16: 23163006
D17: Utility-Exp (002) - Electricity | E17: 1055431 | F17: 1271489.2 | G17: 1285084.5 | H17: 1723001.2 | I17: 1863865 | J17: 1443732.5 | K17: 1687351.2 | L17: 1986645.1 | M17: 1811134.5 | N17: 1946475.5 | O17: 2282543.6 | P17: 945752.15 | Q17: 19302505
C18: C) Operational Maintenance Costs | D18: Plant Maintenance (001) | E18: 996326.91 | F18: 1200285.8 | G18: 1213119.8 | H18: 1626513.1 | I18: 1759488.5 | J18: 1362883.5 | K18: 1592859.5 | L18: 1875393 | M18: 1709711 | N18: 1837472.8 | O18: 2154721.1 | P18: 892790.03 | Q18: 18221565
D19: Plant Outages (002) | E19: 869931.04 | F19: 1048015.4 | G19: 1059221.1 | H19: 1420170.6 | I19: 1536276.6 | J19: 785390.46 | K19: 734335.23 | L19: 864587.94 | M19: 788205.74 | N19: 847106.12 | O19: 993362.97 | P19: 514489.17 | Q19: 11461092
D20: Plant Op. Costs (003) | E20: 921103.46 | F20: 1109663.3 | G20: 1121528.3 | H20: 1503710.1 | I20: 1626645.8 | J20: 831589.9 | K20: 777531.42 | L20: 915446.06 | M20: 834570.78 | N20: 896935.9 | O20: 1051796.1 | P20: 544753.24 | Q20: 12135274
D21: Plant Admin Costs (004) | E21: 498931.04 | F21: 601067.64 | G21: 607494.48 | H21: 814509.64 | I21: 881099.8 | J21: 450444.53 | K21: 421162.85 | L21: 495866.62 | M21: 452059.17 | N21: 485840.28 | O21: 569722.88 | P21: 295074.67 | Q21: 6573273.6
C22: D) Labour Costs | D22: Labour-Costs (001) | E22: 3198275.9 | F22: 3852997.7 | G22: 3894195.4 | H22: 5221215.6 | I22: 5648075.6 | J22: 2887464.9 | K22: 2699761.9 | L22: 3178632.1 | M22: 2897815.2 | N22: 3114360.8 | O22: 3652069.7 | P22: 1891504.3 | Q22: 42136369
A23: B) Surjek Total | E23: 11339551 | F23: 13660880 | G23: 13806948 | H23: 18511924 | I23: 20025365 | J23: 12958943 | K23: 13987466 | L23: 16468493 | M23: 15013581 | N23: 16135503 | O23: 18921373 | P23: 8489071.3 | Q23: 1.793191e+08
A24: C) Jutik | B24: Expenses | C24: A)Chemical Costs | D24: Chem-Exp (001) | E24: 1625596.3 | F24: 1295067.8 | G24: 1750624.9 | H24: 1472529.4 | I24: 1252200.5 | J24: 1406782.7 | K24: 1877449.5 | L24: 1912219.2 | M24: 2266625.2 | N24: 2234200.6 | O24: 2593715.6 | P24: 2274807.8 | Q24: 21961819
C25: B) Facility Costs | D25: Utility-Exp (002) - Heating | E25: 895736.76 | F25: 713608.81 | G25: 964630.04 | H25: 811393.74 | I25: 689988.03 | J25: 775165.96 | K25: 1034513 | L25: 888365.67 | M25: 1248956.7 | N25: 680069.7 | O25: 878169.84 | P25: 1253465.5 | Q25: 10834064
D26: Utility-Exp (002) - Electricity | E26: 829385.89 | F26: 660748.9 | G26: 893175.96 | H26: 751290.5 | I26: 638877.8 | J26: 717746.26 | K26: 957882.4 | L26: 822560.8 | M26: 1156441.4 | N26: 629694.17 | O26: 813120.23 | P26: 1160616.2 | Q26: 10031541
C27: C) Operational Maintenance Costs | D27: Plant Maintenance (001) | E27: 716589.41 | F27: 570887.05 | G27: 771704.03 | H27: 649115 | I27: 551990.42 | J27: 620132.77 | K27: 827610.39 | L27: 710692.53 | M27: 999165.39 | N27: 544055.76 | O27: 702535.88 | P27: 1002772.4 | Q27: 8667251
D28: Plant Outages (002) | E28: 251329.06 | F28: 200226.94 | G28: 270659.38 | H28: 227663.79 | I28: 193599.33 | J28: 143549.25 | K28: 153261.18 | L28: 131609.73 | M28: 185030.63 | N28: 100751.07 | O28: 130099.24 | P28: 232123.24 | Q28: 2219902.8
D29: Plant Op. Costs (003) | E29: 623296.06 | F29: 496562.81 | G29: 671235.27 | H29: 564606.2 | I29: 480126.35 | J29: 356002.15 | K29: 380087.74 | L29: 326392.13 | M29: 458875.96 | N29: 249862.65 | O29: 322646.11 | P29: 575665.64 | Q29: 5505359
D30: Plant Admin Costs (004) | E30: 211116.41 | F30: 168190.63 | G30: 227353.88 | H30: 191237.58 | I30: 162623.44 | J30: 120581.37 | K30: 128739.39 | L30: 110552.17 | M30: 155425.73 | N30: 84630.897 | O30: 109283.36 | P30: 194983.52 | Q30: 1864718.4
C31: D) Labour Costs | D31: Labour-Costs (001) | E31: 3015948.7 | F31: 2402723.3 | G31: 3247912.6 | H31: 2731965.5 | I31: 2323192 | J31: 1722591 | K31: 1839134.2 | L31: 2579316.7 | M31: 2220367.5 | N31: 2209012.8 | O31: 2561190.8 | P31: 2785478.9 | Q31: 29638834
A32: C) Jutik Total | E32: 8168998.6 | F32: 6508016.3 | G32: 8797296 | H32: 7399801.7 | I32: 6292597.9 | J32: 5862551.5 | K32: 7198677.8 | L32: 7481709 | M32: 8690888.6 | N32: 6732277.6 | O32: 8110761.1 | P32: 9479913.3 | Q32: 90723489
A33: Grand Total | E33: 22966839 | F33: 24947250 | G33: 26345251 | H33: 29462555 | I33: 29964506 | J33: 22328717 | K33: 26435964 | L33: 28369995 | M33: 28114195 | N33: 27287085 | O33: 31724934 | P33: 23319122 | Q33: 3.2126641e+08

Sheet Pivot Table 2
A3: Sum of Values2 | E3: Month
A4: Account Type | B4: Unit | C4: Accounting Code Centre | D4: Accounting Code Centre Element | E4: 41456 | F4: 41487 | G4: 41518 | H4: 41548 | I4: 41579 | J4: 41609 | K4: 41640 | L4: 41671 | M4: 41699 | N4: 41730 | O4: 41760 | P4: 41791 | Q4: Grand Total
A5: Expenses | B5: Kootha | C5: Chemical Costs | D5: Chem-Exp (001) | E5: 593751.84 | F5: 820393.03 | G5: 642291.58 | H5: 609639.97 | I5: 626073.17 | J5: 602153.38 | K5: 1146144 | L5: 964931.84 | M5: 962733.96 | N5: 964825.22 | O5: 1024534.8 | P5: 1168045.2 | Q5: 10125518
B6: Surjek | C6: Chemical Costs | D6: Chem-Exp (001) | E6: 2533034.5 | F6: 3051574.2 | G6: 3084202.8 | H6: 4135202.8 | I6: 4473275.9 | J6: 3464957.9 | K6: 4049642.8 | L6: 4767948.2 | M6: 4346722.8 | N6: 4671541.1 | O6: 5478104.6 | P6: 2269805.2 | Q6: 46326013
B7: Jutik | C7: Chemical Costs | D7: Chem-Exp (001) | E7: 1625596.3 | F7: 1295067.8 | G7: 1750624.9 | H7: 1472529.4 | I7: 1252200.5 | J7: 1406782.7 | K7: 1877449.5 | L7: 1912219.2 | M7: 2266625.2 | N7: 2234200.6 | O7: 2593715.6 | P7: 2274807.8 | Q7: 21961819
A8: Water Production Actuals | B8: Kootha | C8: None | D8: None | E8: 181.93329 | F8: 187.44394 | G8: 184.77366 | H8: 191.54109 | I8: 98.096062 | J8: 185.30685 | K8: 186.90144 | L8: 158.58677 | M8: 191.40368 | N8: 171.05786 | O8: 169.287 | P8: 142.50872 | Q8: 2048.8404
B9: Surjek | C9: None | D9: None | E9: 214.969 | F9: 228.19905 | G9: 216.53647 | H9: 236.76028 | I9: 232.05286 | J9: 240.21016 | K9: 288.16055 | L9: 306.88452 | M9: 367.65101 | N9: 351.99017 | O9: 362.822 | P9: 260.3123 | Q9: 3306.5484
B10: Jutik | C10: None | D10: None | E10: 250.24199 | F10: 206.7407 | G10: 201.23546 | H10: 174.36957 | I10: 204.09105 | J10: 146.35667 | K10: 204.2025 | L10: 217.4302 | M10: 230.9822 | N10: 236.44114 | O10: 241.40737 | P10: 220.38033 | Q10: 2533.8792
A11: Grand Total | E11: 4753029.8 | F11: 5167657.4 | G11: 5477721.8 | H11: 6217974.8 | I11: 6352083.8 | J11: 5474465.9 | K11: 7073915.6 | L11: 7645782.1 | M11: 7576872 | N11: 7871326.4 | O11: 9097128.5 | P11: 5713281.4 | Q11: 78421240

Sheet Variance Analysis
A1: Budget - Actual Analysis (Variance).
A2: Why do we care about Budget Variance? In the earlier exercise, you have calculated the summarised actual costs that Southern Water Corp has incurred over the 2013 to 2014 Period. In every business, when there is an actual, a budget also exists as a counter-weight to see how accurately the business has stuck to it's budget. If the business has exceeded its budget on Revenues - that is good news. We made more than expected. However, if the business has SPENT more than it has earned or budgeted for - this is not an ideal outcome. In this Tab, we are going to ask you to calculate the Variance (Difference between Budget subtract Actuals) for Revenues, Production Costs and Other Production Costs. This is not to be confused with Statistical Variance which is a measure of dispersion. Now that we know why variance is important - let's proceed with calculating this!
A4: Q1a. Populate the Revenues Section of the Table below with the Budgeted Values from the Financial BUDGET Tab Do NOT paste the values in the Financial Budget but use Formulas to reference the Financial BUDGET Values for Kootha, Surjek And Jutik. This is because IF you simply paste - it is very easy to make mistakes which are inconsistent with the rest of the Spreadsheet.
A6: Q2a. Popuate the Production, Production Other and Overheads Section of the Table below with the Budgeted Values from the Financial Budget Tab.
A7: Budget
A8: Desalination Plants [All] | C8: 2013/Jul | D8: 2013/Aug | E8: 2013/Sep | F8: 2013/Oct | G8: 2013/Nov | H8: 2013/Dec | I8: 2014/Jan | J8: 2014/Feb | K8: 2014/Mar | L8: 2014/Apr | M8: 2014/May | N8: 2014/Jun
A9: Kootha (1 Major Desal Unit) | B9: Revenue | C9: =SUMIFS(#REF!,#REF!,'Variance Analysis'!$B9,#REF!,'Variance Analysis'!$A9) -> #REF! | D9: =SUMIFS(#REF!,#REF!,'Variance Analysis'!$B9,#REF!,'Variance Analysis'!$A9) -> #REF! | E9: =SUMIFS(#REF!,#REF!,'Variance Analysis'!$B9,#REF!,'Variance Analysis'!$A9) -> #REF! | F9: =SUMIFS(#REF!,#REF!,'Variance Analysis'!$B9,#REF!,'Variance Analysis'!$A9) -> #REF! | G9: =SUMIFS(#REF!,#REF!,'Variance Analysis'!$B9,#REF!,'Variance Analysis'!$A9) -> #REF! | H9: =SUMIFS(#REF!,#REF!,'Variance Analysis'!$B9,#REF!,'Variance Analysis'!$A9) -> #REF! | I9: =SUMIFS(#REF!,#REF!,'Variance Analysis'!$B9,#REF!,'Variance Analysis'!$A9) -> #REF! | J9: =SUMIFS(#REF!,#REF!,'Variance Analysis'!$B9,#REF!,'Variance Analysis'!$A9) -> #REF! | ... N9: =SUMIFS(#REF!,#REF!,'Variance Analysis'!$B9,#REF!,'Variance Analysis'!$A9) -> #REF!
A10: Kootha (1 Major Desal Unit) | B10: Production | C10: =SUMIFS(#REF!,#REF!,'Variance Analysis'!$B10,#REF!,'Variance Analysis'!$A10) -> #REF! | D10: =SUMIFS(#REF!,#REF!,'Variance Analysis'!$B10,#REF!,'Variance Analysis'!$A10) -> #REF! | E10: =SUMIFS(#REF!,#REF!,'Variance Analysis'!$B10,#REF!,'Variance Analysis'!$A10) -> #REF! | F10: =SUMIFS(#REF!,#REF!,'Variance Analysis'!$B10,#REF!,'Variance Analysis'!$A10) -> #REF! | G10: =SUMIFS(#REF!,#REF!,'Variance Analysis'!$B10,#REF!,'Variance Analysis'!$A10) -> #REF! | H10: =SUMIFS(#REF!,#REF!,'Variance Analysis'!$B10,#REF!,'Variance Analysis'!$A10) -> #REF! | I10: =SUMIFS(#REF!,#REF!,'Variance Analysis'!$B10,#REF!,'Variance Analysis'!$A10) -> #REF! | J10: =SUMIFS(#REF!,#REF!,'Variance Analysis'!$B10,#REF!,'Variance Analysis'!$A10) -> #REF! | ... N10: =SUMIFS(#REF!,#REF!,'Variance Analysis'!$B10,#REF!,'Variance Analysis'!$A10) -> #REF!
A11: Kootha (1 Major Desal Unit) | B11: Production Other | C11: =SUMIFS(#REF!,#REF!,'Variance Analysis'!$B11,#REF!,'Variance Analysis'!$A11) -> #REF! | D11: =SUMIFS(#REF!,#REF!,'Variance Analysis'!$B11,#REF!,'Variance Analysis'!$A11) -> #REF! | E11: =SUMIFS(#REF!,#REF!,'Variance Analysis'!$B11,#REF!,'Variance Analysis'!$A11) -> #REF! | F11: =SUMIFS(#REF!,#REF!,'Variance Analysis'!$B11,#REF!,'Variance Analysis'!$A11) -> #REF! | G11: =SUMIFS(#REF!,#REF!,'Variance Analysis'!$B11,#REF!,'Variance Analysis'!$A11) -> #REF! | H11: =SUMIFS(#REF!,#REF!,'Variance Analysis'!$B11,#REF!,'Variance Analysis'!$A11) -> #REF! | I11: =SUMIFS(#REF!,#REF!,'Variance Analysis'!$B11,#REF!,'Variance Analysis'!$A11) -> #REF! | J11: =SUMIFS(#REF!,#REF!,'Variance Analysis'!$B11,#REF!,'Variance Analysis'!$A11) -> #REF! | ... N11: =SUMIFS(#REF!,#REF!,'Variance Analysis'!$B11,#REF!,'Variance Analysis'!$A11) -> #REF!
A12: Kootha (1 Major Desal Unit) | B12: Overheads | C12: =SUMIFS(#REF!,#REF!,$A$12) -> #REF! | D12: =SUMIFS(#REF!,#REF!,$A$12) -> #REF! | E12: =SUMIFS(#REF!,#REF!,$A$12) -> #REF! | F12: =SUMIFS(#REF!,#REF!,$A$12) -> #REF! | G12: =SUMIFS(#REF!,#REF!,$A$12) -> #REF! | H12: =SUMIFS(#REF!,#REF!,$A$12) -> #REF! | I12: =SUMIFS(#REF!,#REF!,$A$12) -> #REF! | J12: =SUMIFS(#REF!,#REF!,$A$12) -> #REF! | ... N12: =SUMIFS(#REF!,#REF!,$A$12) -> #REF!
A13: Surjek (4 Major Desal. Plants) | B13: Revenue | C13: =SUMIFS(#REF!,#REF!,'Variance Analysis'!$B13,#REF!,'Variance Analysis'!$A13) -> #REF! | D13: =SUMIFS(#REF!,#REF!,'Variance Analysis'!$B13,#REF!,'Variance Analysis'!$A13) -> #REF! | E13: =SUMIFS(#REF!,#REF!,'Variance Analysis'!$B13,#REF!,'Variance Analysis'!$A13) -> #REF! | F13: =SUMIFS(#REF!,#REF!,'Variance Analysis'!$B13,#REF!,'Variance Analysis'!$A13) -> #REF! | G13: =SUMIFS(#REF!,#REF!,'Variance Analysis'!$B13,#REF!,'Variance Analysis'!$A13) -> #REF! | H13: =SUMIFS(#REF!,#REF!,'Variance Analysis'!$B13,#REF!,'Variance Analysis'!$A13) -> #REF! | I13: =SUMIFS(#REF!,#REF!,'Variance Analysis'!$B13,#REF!,'Variance Analysis'!$A13) -> #REF! | J13: =SUMIFS(#REF!,#REF!,'Variance Analysis'!$B13,#REF!,'Variance Analysis'!$A13) -> #REF! | ... N13: =SUMIFS(#REF!,#REF!,'Variance Analysis'!$B13,#REF!,'Variance Analysis'!$A13) -> #REF!
A14: Surjek (4 Major Desal. Plants) | B14: Production | C14: =SUMIFS(#REF!,#REF!,'Variance Analysis'!$B14,#REF!,'Variance Analysis'!$A14) -> #REF! | D14: =SUMIFS(#REF!,#REF!,'Variance Analysis'!$B14,#REF!,'Variance Analysis'!$A14) -> #REF! | E14: =SUMIFS(#REF!,#REF!,'Variance Analysis'!$B14,#REF!,'Variance Analysis'!$A14) -> #REF! | F14: =SUMIFS(#REF!,#REF!,'Variance Analysis'!$B14,#REF!,'Variance Analysis'!$A14) -> #REF! | G14: =SUMIFS(#REF!,#REF!,'Variance Analysis'!$B14,#REF!,'Variance Analysis'!$A14) -> #REF! | H14: =SUMIFS(#REF!,#REF!,'Variance Analysis'!$B14,#REF!,'Variance Analysis'!$A14) -> #REF! | I14: =SUMIFS(#REF!,#REF!,'Variance Analysis'!$B14,#REF!,'Variance Analysis'!$A14) -> #REF! | J14: =SUMIFS(#REF!,#REF!,'Variance Analysis'!$B14,#REF!,'Variance Analysis'!$A14) -> #REF! | ... N14: =SUMIFS(#REF!,#REF!,'Variance Analysis'!$B14,#REF!,'Variance Analysis'!$A14) -> #REF!
A15: Surjek (4 Major Desal. Plants) | B15: Production Other | C15: =SUMIFS(#REF!,#REF!,'Variance Analysis'!$B15,#REF!,'Variance Analysis'!$A15) -> #REF! | D15: =SUMIFS(#REF!,#REF!,'Variance Analysis'!$B15,#REF!,'Variance Analysis'!$A15) -> #REF! | E15: =SUMIFS(#REF!,#REF!,'Variance Analysis'!$B15,#REF!,'Variance Analysis'!$A15) -> #REF! | F15: =SUMIFS(#REF!,#REF!,'Variance Analysis'!$B15,#REF!,'Variance Analysis'!$A15) -> #REF! | G15: =SUMIFS(#REF!,#REF!,'Variance Analysis'!$B15,#REF!,'Variance Analysis'!$A15) -> #REF! | H15: =SUMIFS(#REF!,#REF!,'Variance Analysis'!$B15,#REF!,'Variance Analysis'!$A15) -> #REF! | I15: =SUMIFS(#REF!,#REF!,'Variance Analysis'!$B15,#REF!,'Variance Analysis'!$A15) -> #REF! | J15: =SUMIFS(#REF!,#REF!,'Variance Analysis'!$B15,#REF!,'Variance Analysis'!$A15) -> #REF! | ... N15: =SUMIFS(#REF!,#REF!,'Variance Analysis'!$B15,#REF!,'Variance Analysis'!$A15) -> #REF!
A16: Surjek (4 Major Desal. Plants) | B16: Overheads | C16: =SUMIFS(#REF!,#REF!,$A$16) -> #REF! | D16: =SUMIFS(#REF!,#REF!,$A$16) -> #REF! | E16: =SUMIFS(#REF!,#REF!,$A$16) -> #REF! | F16: =SUMIFS(#REF!,#REF!,$A$16) -> #REF! | G16: =SUMIFS(#REF!,#REF!,$A$16) -> #REF! | H16: =SUMIFS(#REF!,#REF!,$A$16) -> #REF! | I16: =SUMIFS(#REF!,#REF!,$A$16) -> #REF! | J16: =SUMIFS(#REF!,#REF!,$A$16) -> #REF! | ... N16: =SUMIFS(#REF!,#REF!,$A$16) -> #REF!
A17: Jutik Desalination Plant [Newest Desalination Plant] | B17: Revenue | C17: =SUMIFS(#REF!,#REF!,'Variance Analysis'!$B17,#REF!,'Variance Analysis'!$A17) -> #REF! | D17: =SUMIFS(#REF!,#REF!,'Variance Analysis'!$B17,#REF!,'Variance Analysis'!$A17) -> #REF! | E17: =SUMIFS(#REF!,#REF!,'Variance Analysis'!$B17,#REF!,'Variance Analysis'!$A17) -> #REF! | F17: =SUMIFS(#REF!,#REF!,'Variance Analysis'!$B17,#REF!,'Variance Analysis'!$A17) -> #REF! | G17: =SUMIFS(#REF!,#REF!,'Variance Analysis'!$B17,#REF!,'Variance Analysis'!$A17) -> #REF! | H17: =SUMIFS(#REF!,#REF!,'Variance Analysis'!$B17,#REF!,'Variance Analysis'!$A17) -> #REF! | I17: =SUMIFS(#REF!,#REF!,'Variance Analysis'!$B17,#REF!,'Variance Analysis'!$A17) -> #REF! | J17: =SUMIFS(#REF!,#REF!,'Variance Analysis'!$B17,#REF!,'Variance Analysis'!$A17) -> #REF! | ... N17: =SUMIFS(#REF!,#REF!,'Variance Analysis'!$B17,#REF!,'Variance Analysis'!$A17) -> #REF!
A18: Jutik Desalination Plant [Newest Desalination Plant] | B18: Production | C18: =SUMIFS(#REF!,#REF!,'Variance Analysis'!$B18,#REF!,'Variance Analysis'!$A18) -> #REF! | D18: =SUMIFS(#REF!,#REF!,'Variance Analysis'!$B18,#REF!,'Variance Analysis'!$A18) -> #REF! | E18: =SUMIFS(#REF!,#REF!,'Variance Analysis'!$B18,#REF!,'Variance Analysis'!$A18) -> #REF! | F18: =SUMIFS(#REF!,#REF!,'Variance Analysis'!$B18,#REF!,'Variance Analysis'!$A18) -> #REF! | G18: =SUMIFS(#REF!,#REF!,'Variance Analysis'!$B18,#REF!,'Variance Analysis'!$A18) -> #REF! | H18: =SUMIFS(#REF!,#REF!,'Variance Analysis'!$B18,#REF!,'Variance Analysis'!$A18) -> #REF! | I18: =SUMIFS(#REF!,#REF!,'Variance Analysis'!$B18,#REF!,'Variance Analysis'!$A18) -> #REF! | J18: =SUMIFS(#REF!,#REF!,'Variance Analysis'!$B18,#REF!,'Variance Analysis'!$A18) -> #REF! | ... N18: =SUMIFS(#REF!,#REF!,'Variance Analysis'!$B18,#REF!,'Variance Analysis'!$A18) -> #REF!
A19: Jutik Desalination Plant [Newest Desalination Plant] | B19: Production Other | C19: =SUMIFS(#REF!,#REF!,'Variance Analysis'!$B19,#REF!,'Variance Analysis'!$A19) -> #REF! | D19: =SUMIFS(#REF!,#REF!,'Variance Analysis'!$B19,#REF!,'Variance Analysis'!$A19) -> #REF! | E19: =SUMIFS(#REF!,#REF!,'Variance Analysis'!$B19,#REF!,'Variance Analysis'!$A19) -> #REF! | F19: =SUMIFS(#REF!,#REF!,'Variance Analysis'!$B19,#REF!,'Variance Analysis'!$A19) -> #REF! | G19: =SUMIFS(#REF!,#REF!,'Variance Analysis'!$B19,#REF!,'Variance Analysis'!$A19) -> #REF! | H19: =SUMIFS(#REF!,#REF!,'Variance Analysis'!$B19,#REF!,'Variance Analysis'!$A19) -> #REF! | I19: =SUMIFS(#REF!,#REF!,'Variance Analysis'!$B19,#REF!,'Variance Analysis'!$A19) -> #REF! | J19: =SUMIFS(#REF!,#REF!,'Variance Analysis'!$B19,#REF!,'Variance Analysis'!$A19) -> #REF! | ... N19: =SUMIFS(#REF!,#REF!,'Variance Analysis'!$B19,#REF!,'Variance Analysis'!$A19) -> #REF!
A20: Jutik Desalination Plant [Newest Desalination Plant] | B20: Overheads | C20: =SUMIFS(#REF!,#REF!,$A$20) -> #REF! | D20: =SUMIFS(#REF!,#REF!,$A$20) -> #REF! | E20: =SUMIFS(#REF!,#REF!,$A$20) -> #REF! | F20: =SUMIFS(#REF!,#REF!,$A$20) -> #REF! | G20: =SUMIFS(#REF!,#REF!,$A$20) -> #REF! | H20: =SUMIFS(#REF!,#REF!,$A$20) -> #REF! | I20: =SUMIFS(#REF!,#REF!,$A$20) -> #REF! | J20: =SUMIFS(#REF!,#REF!,$A$20) -> #REF! | ... N20: =SUMIFS(#REF!,#REF!,$A$20) -> #REF!
A21: Desalination Plants [All] | B21: Revenue | C21: =SUMIFS(C$9:C$20,$B$9:$B$20,$B21) -> #REF! | D21: =SUMIFS(D$9:D$20,$B$9:$B$20,$B21) -> #REF! | E21: =SUMIFS(E$9:E$20,$B$9:$B$20,$B21) -> #REF! | F21: =SUMIFS(F$9:F$20,$B$9:$B$20,$B21) -> #REF! | G21: =SUMIFS(G$9:G$20,$B$9:$B$20,$B21) -> #REF! | H21: =SUMIFS(H$9:H$20,$B$9:$B$20,$B21) -> #REF! | I21: =SUMIFS(I$9:I$20,$B$9:$B$20,$B21) -> #REF! | J21: =SUMIFS(J$9:J$20,$B$9:$B$20,$B21) -> #REF! | ... N21: =SUMIFS(N$9:N$20,$B$9:$B$20,$B21) -> #REF!
A22: Desalination Plants [All] | B22: Production | C22: =SUMIFS(C$9:C$20,$B$9:$B$20,$B22) -> #REF! | D22: =SUMIFS(D$9:D$20,$B$9:$B$20,$B22) -> #REF! | E22: =SUMIFS(E$9:E$20,$B$9:$B$20,$B22) -> #REF! | F22: =SUMIFS(F$9:F$20,$B$9:$B$20,$B22) -> #REF! | G22: =SUMIFS(G$9:G$20,$B$9:$B$20,$B22) -> #REF! | H22: =SUMIFS(H$9:H$20,$B$9:$B$20,$B22) -> #REF! | I22: =SUMIFS(I$9:I$20,$B$9:$B$20,$B22) -> #REF! | J22: =SUMIFS(J$9:J$20,$B$9:$B$20,$B22) -> #REF! | ... N22: =SUMIFS(N$9:N$20,$B$9:$B$20,$B22) -> #REF!
A23: Desalination Plants [All] | B23: Production Other | C23: =SUMIFS(C$9:C$20,$B$9:$B$20,$B23) -> #REF! | D23: =SUMIFS(D$9:D$20,$B$9:$B$20,$B23) -> #REF! | E23: =SUMIFS(E$9:E$20,$B$9:$B$20,$B23) -> #REF! | F23: =SUMIFS(F$9:F$20,$B$9:$B$20,$B23) -> #REF! | G23: =SUMIFS(G$9:G$20,$B$9:$B$20,$B23) -> #REF! | H23: =SUMIFS(H$9:H$20,$B$9:$B$20,$B23) -> #REF! | I23: =SUMIFS(I$9:I$20,$B$9:$B$20,$B23) -> #REF! | J23: =SUMIFS(J$9:J$20,$B$9:$B$20,$B23) -> #REF! | ... N23: =SUMIFS(N$9:N$20,$B$9:$B$20,$B23) -> #REF!
A24: Desalination Plants [All] | B24: Overheads | C24: =SUMIFS(C$9:C$20,$B$9:$B$20,$B24) -> #REF! | D24: =SUMIFS(D$9:D$20,$B$9:$B$20,$B24) -> #REF! | E24: =SUMIFS(E$9:E$20,$B$9:$B$20,$B24) -> #REF! | F24: =SUMIFS(F$9:F$20,$B$9:$B$20,$B24) -> #REF! | G24: =SUMIFS(G$9:G$20,$B$9:$B$20,$B24) -> #REF! | H24: =SUMIFS(H$9:H$20,$B$9:$B$20,$B24) -> #REF! | I24: =SUMIFS(I$9:I$20,$B$9:$B$20,$B24) -> #REF! | J24: =SUMIFS(J$9:J$20,$B$9:$B$20,$B24) -> #REF! | ... N24: =SUMIFS(N$9:N$20,$B$9:$B$20,$B24) -> #REF!
A25: Actuals
A26: Q1b. Populate the Revenues Section of the Table below with the Actual Values from the Financial ACTUALS Tab Do NOT paste the values from the Financial ACTUALS Tab but use Formulas to reference the Financial ACTUALS Values for Kootha, Surjek And Jutik. This is because IF you simply paste - it is very easy to make mistakes which are inconsistent with the rest of the Spreadsheet.
A28: Q2a. Popuate the Production, Production Other and Overheads Section of the Table below with the Actual Values from the Financial Actuals Tab.
A29: Desalination Plants [All] | C29: 2013/Jul | D29: 2013/Aug | E29: 2013/Sep | F29: 2013/Oct | G29: 2013/Nov | H29: 2013/Dec | I29: 2014/Jan | J29: 2014/Feb | K29: 2014/Mar | L29: 2014/Apr | M29: 2014/May | N29: 2014/Jun
A30: Kootha (1 Major Desal Unit) | B30: Revenue | C30: =SUMIFS(#REF!,#REF!,'Variance Analysis'!$B30,#REF!,'Variance Analysis'!$A30) -> #REF! | D30: =SUMIFS(#REF!,#REF!,'Variance Analysis'!$B30,#REF!,'Variance Analysis'!$A30) -> #REF! | E30: =SUMIFS(#REF!,#REF!,'Variance Analysis'!$B30,#REF!,'Variance Analysis'!$A30) -> #REF! | F30: =SUMIFS(#REF!,#REF!,'Variance Analysis'!$B30,#REF!,'Variance Analysis'!$A30) -> #REF! | G30: =SUMIFS(#REF!,#REF!,'Variance Analysis'!$B30,#REF!,'Variance Analysis'!$A30) -> #REF! | H30: =SUMIFS(#REF!,#REF!,'Variance Analysis'!$B30,#REF!,'Variance Analysis'!$A30) -> #REF! | I30: =SUMIFS(#REF!,#REF!,'Variance Analysis'!$B30,#REF!,'Variance Analysis'!$A30) -> #REF! | J30: =SUMIFS(#REF!,#REF!,'Variance Analysis'!$B30,#REF!,'Variance Analysis'!$A30) -> #REF! | ... N30: =SUMIFS(#REF!,#REF!,'Variance Analysis'!$B30,#REF!,'Variance Analysis'!$A30) -> #REF!
A31: Kootha (1 Major Desal Unit) | B31: Production Costs | C31: =SUMIFS(#REF!,#REF!,'Variance Analysis'!$B31,#REF!,'Variance Analysis'!$A31) -> #REF! | D31: =SUMIFS(#REF!,#REF!,'Variance Analysis'!$B31,#REF!,'Variance Analysis'!$A31) -> #REF! | E31: =SUMIFS(#REF!,#REF!,'Variance Analysis'!$B31,#REF!,'Variance Analysis'!$A31) -> #REF! | F31: =SUMIFS(#REF!,#REF!,'Variance Analysis'!$B31,#REF!,'Variance Analysis'!$A31) -> #REF! | G31: =SUMIFS(#REF!,#REF!,'Variance Analysis'!$B31,#REF!,'Variance Analysis'!$A31) -> #REF! | H31: =SUMIFS(#REF!,#REF!,'Variance Analysis'!$B31,#REF!,'Variance Analysis'!$A31) -> #REF! | I31: =SUMIFS(#REF!,#REF!,'Variance Analysis'!$B31,#REF!,'Variance Analysis'!$A31) -> #REF! | J31: =SUMIFS(#REF!,#REF!,'Variance Analysis'!$B31,#REF!,'Variance Analysis'!$A31) -> #REF! | ... N31: =SUMIFS(#REF!,#REF!,'Variance Analysis'!$B31,#REF!,'Variance Analysis'!$A31) -> #REF!
A32: Kootha (1 Major Desal Unit) | B32: Other Production Costs | C32: =SUMIFS(#REF!,#REF!,'Variance Analysis'!$B32,#REF!,'Variance Analysis'!$A32) -> #REF! | D32: =SUMIFS(#REF!,#REF!,'Variance Analysis'!$B32,#REF!,'Variance Analysis'!$A32) -> #REF! | E32: =SUMIFS(#REF!,#REF!,'Variance Analysis'!$B32,#REF!,'Variance Analysis'!$A32) -> #REF! | F32: =SUMIFS(#REF!,#REF!,'Variance Analysis'!$B32,#REF!,'Variance Analysis'!$A32) -> #REF! | G32: =SUMIFS(#REF!,#REF!,'Variance Analysis'!$B32,#REF!,'Variance Analysis'!$A32) -> #REF! | H32: =SUMIFS(#REF!,#REF!,'Variance Analysis'!$B32,#REF!,'Variance Analysis'!$A32) -> #REF! | I32: =SUMIFS(#REF!,#REF!,'Variance Analysis'!$B32,#REF!,'Variance Analysis'!$A32) -> #REF! | J32: =SUMIFS(#REF!,#REF!,'Variance Analysis'!$B32,#REF!,'Variance Analysis'!$A32) -> #REF! | ... N32: =SUMIFS(#REF!,#REF!,'Variance Analysis'!$B32,#REF!,'Variance Analysis'!$A32) -> #REF!
A33: Kootha (1 Major Desal Unit) | B33: Overheads | C33: =SUMIFS(#REF!,#REF!,#REF!) -> #REF! | D33: =SUMIFS(#REF!,#REF!,#REF!) -> #REF! | E33: =SUMIFS(#REF!,#REF!,#REF!) -> #REF! | F33: =SUMIFS(#REF!,#REF!,#REF!) -> #REF! | G33: =SUMIFS(#REF!,#REF!,#REF!) -> #REF! | H33: =SUMIFS(#REF!,#REF!,#REF!) -> #REF! | I33: =SUMIFS(#REF!,#REF!,#REF!) -> #REF! | J33: =SUMIFS(#REF!,#REF!,#REF!) -> #REF! | ... N33: =SUMIFS(#REF!,#REF!,#REF!) -> #REF!
A34: Surjek (4 Major Desal. Plants) | B34: Revenue | C34: =SUMIFS(#REF!,#REF!,'Variance Analysis'!$B34,#REF!,'Variance Analysis'!$A34) -> #REF! | D34: =SUMIFS(#REF!,#REF!,'Variance Analysis'!$B34,#REF!,'Variance Analysis'!$A34) -> #REF! | E34: =SUMIFS(#REF!,#REF!,'Variance Analysis'!$B34,#REF!,'Variance Analysis'!$A34) -> #REF! | F34: =SUMIFS(#REF!,#REF!,'Variance Analysis'!$B34,#REF!,'Variance Analysis'!$A34) -> #REF! | G34: =SUMIFS(#REF!,#REF!,'Variance Analysis'!$B34,#REF!,'Variance Analysis'!$A34) -> #REF! | H34: =SUMIFS(#REF!,#REF!,'Variance Analysis'!$B34,#REF!,'Variance Analysis'!$A34) -> #REF! | I34: =SUMIFS(#REF!,#REF!,'Variance Analysis'!$B34,#REF!,'Variance Analysis'!$A34) -> #REF! | J34: =SUMIFS(#REF!,#REF!,'Variance Analysis'!$B34,#REF!,'Variance Analysis'!$A34) -> #REF! | ... N34: =SUMIFS(#REF!,#REF!,'Variance Analysis'!$B34,#REF!,'Variance Analysis'!$A34) -> #REF!
A35: Surjek (4 Major Desal. Plants) | B35: Production Costs | C35: =SUMIFS(#REF!,#REF!,'Variance Analysis'!$B35,#REF!,'Variance Analysis'!$A35) -> #REF! | D35: =SUMIFS(#REF!,#REF!,'Variance Analysis'!$B35,#REF!,'Variance Analysis'!$A35) -> #REF! | E35: =SUMIFS(#REF!,#REF!,'Variance Analysis'!$B35,#REF!,'Variance Analysis'!$A35) -> #REF! | F35: =SUMIFS(#REF!,#REF!,'Variance Analysis'!$B35,#REF!,'Variance Analysis'!$A35) -> #REF! | G35: =SUMIFS(#REF!,#REF!,'Variance Analysis'!$B35,#REF!,'Variance Analysis'!$A35) -> #REF! | H35: =SUMIFS(#REF!,#REF!,'Variance Analysis'!$B35,#REF!,'Variance Analysis'!$A35) -> #REF! | I35: =SUMIFS(#REF!,#REF!,'Variance Analysis'!$B35,#REF!,'Variance Analysis'!$A35) -> #REF! | J35: =SUMIFS(#REF!,#REF!,'Variance Analysis'!$B35,#REF!,'Variance Analysis'!$A35) -> #REF! | ... N35: =SUMIFS(#REF!,#REF!,'Variance Analysis'!$B35,#REF!,'Variance Analysis'!$A35) -> #REF!
A36: Surjek (4 Major Desal. Plants) | B36: Other Production Costs | C36: =SUMIFS(#REF!,#REF!,'Variance Analysis'!$B36,#REF!,'Variance Analysis'!$A36) -> #REF! | D36: =SUMIFS(#REF!,#REF!,'Variance Analysis'!$B36,#REF!,'Variance Analysis'!$A36) -> #REF! | E36: =SUMIFS(#REF!,#REF!,'Variance Analysis'!$B36,#REF!,'Variance Analysis'!$A36) -> #REF! | F36: =SUMIFS(#REF!,#REF!,'Variance Analysis'!$B36,#REF!,'Variance Analysis'!$A36) -> #REF! | G36: =SUMIFS(#REF!,#REF!,'Variance Analysis'!$B36,#REF!,'Variance Analysis'!$A36) -> #REF! | H36: =SUMIFS(#REF!,#REF!,'Variance Analysis'!$B36,#REF!,'Variance Analysis'!$A36) -> #REF! | I36: =SUMIFS(#REF!,#REF!,'Variance Analysis'!$B36,#REF!,'Variance Analysis'!$A36) -> #REF! | J36: =SUMIFS(#REF!,#REF!,'Variance Analysis'!$B36,#REF!,'Variance Analysis'!$A36) -> #REF! | ... N36: =SUMIFS(#REF!,#REF!,'Variance Analysis'!$B36,#REF!,'Variance Analysis'!$A36) -> #REF!
A37: Surjek (4 Major Desal. Plants) | B37: Overheads | C37: =SUMIFS(#REF!,#REF!,$A$37) -> #REF! | D37: =SUMIFS(#REF!,#REF!,$A$37) -> #REF! | E37: =SUMIFS(#REF!,#REF!,$A$37) -> #REF! | F37: =SUMIFS(#REF!,#REF!,$A$37) -> #REF! | G37: =SUMIFS(#REF!,#REF!,$A$37) -> #REF! | H37: =SUMIFS(#REF!,#REF!,$A$37) -> #REF! | I37: =SUMIFS(#REF!,#REF!,$A$37) -> #REF! | J37: =SUMIFS(#REF!,#REF!,$A$37) -> #REF! | ... N37: =SUMIFS(#REF!,#REF!,$A$37) -> #REF!
A38: Jutik (New Desalination Plant) | B38: Revenue | C38: =SUMIFS(#REF!,#REF!,'Variance Analysis'!$B38,#REF!,'Variance Analysis'!$A38) -> #REF! | D38: =SUMIFS(#REF!,#REF!,'Variance Analysis'!$B38,#REF!,'Variance Analysis'!$A38) -> #REF! | E38: =SUMIFS(#REF!,#REF!,'Variance Analysis'!$B38,#REF!,'Variance Analysis'!$A38) -> #REF! | F38: =SUMIFS(#REF!,#REF!,'Variance Analysis'!$B38,#REF!,'Variance Analysis'!$A38) -> #REF! | G38: =SUMIFS(#REF!,#REF!,'Variance Analysis'!$B38,#REF!,'Variance Analysis'!$A38) -> #REF! | H38: =SUMIFS(#REF!,#REF!,'Variance Analysis'!$B38,#REF!,'Variance Analysis'!$A38) -> #REF! | I38: =SUMIFS(#REF!,#REF!,'Variance Analysis'!$B38,#REF!,'Variance Analysis'!$A38) -> #REF! | J38: =SUMIFS(#REF!,#REF!,'Variance Analysis'!$B38,#REF!,'Variance Analysis'!$A38) -> #REF! | ... N38: =SUMIFS(#REF!,#REF!,'Variance Analysis'!$B38,#REF!,'Variance Analysis'!$A38) -> #REF!
A39: Jutik (New Desalination Plant) | B39: Production Costs | C39: =SUMIFS(#REF!,#REF!,'Variance Analysis'!$B39,#REF!,'Variance Analysis'!$A39) -> #REF! | D39: =SUMIFS(#REF!,#REF!,'Variance Analysis'!$B39,#REF!,'Variance Analysis'!$A39) -> #REF! | E39: =SUMIFS(#REF!,#REF!,'Variance Analysis'!$B39,#REF!,'Variance Analysis'!$A39) -> #REF! | F39: =SUMIFS(#REF!,#REF!,'Variance Analysis'!$B39,#REF!,'Variance Analysis'!$A39) -> #REF! | G39: =SUMIFS(#REF!,#REF!,'Variance Analysis'!$B39,#REF!,'Variance Analysis'!$A39) -> #REF! | H39: =SUMIFS(#REF!,#REF!,'Variance Analysis'!$B39,#REF!,'Variance Analysis'!$A39) -> #REF! | I39: =SUMIFS(#REF!,#REF!,'Variance Analysis'!$B39,#REF!,'Variance Analysis'!$A39) -> #REF! | J39: =SUMIFS(#REF!,#REF!,'Variance Analysis'!$B39,#REF!,'Variance Analysis'!$A39) -> #REF! | ... N39: =SUMIFS(#REF!,#REF!,'Variance Analysis'!$B39,#REF!,'Variance Analysis'!$A39) -> #REF!
A40: Jutik (New Desalination Plant) | B40: Other Production Costs | C40: =SUMIFS(#REF!,#REF!,'Variance Analysis'!$B40,#REF!,'Variance Analysis'!$A40) -> #REF! | D40: =SUMIFS(#REF!,#REF!,'Variance Analysis'!$B40,#REF!,'Variance Analysis'!$A40) -> #REF! | E40: =SUMIFS(#REF!,#REF!,'Variance Analysis'!$B40,#REF!,'Variance Analysis'!$A40) -> #REF! | F40: =SUMIFS(#REF!,#REF!,'Variance Analysis'!$B40,#REF!,'Variance Analysis'!$A40) -> #REF! | G40: =SUMIFS(#REF!,#REF!,'Variance Analysis'!$B40,#REF!,'Variance Analysis'!$A40) -> #REF! | H40: =SUMIFS(#REF!,#REF!,'Variance Analysis'!$B40,#REF!,'Variance Analysis'!$A40) -> #REF! | I40: =SUMIFS(#REF!,#REF!,'Variance Analysis'!$B40,#REF!,'Variance Analysis'!$A40) -> #REF! | J40: =SUMIFS(#REF!,#REF!,'Variance Analysis'!$B40,#REF!,'Variance Analysis'!$A40) -> #REF! | ... N40: =SUMIFS(#REF!,#REF!,'Variance Analysis'!$B40,#REF!,'Variance Analysis'!$A40) -> #REF!
A41: Jutik (New Desalination Plant) | B41: Overheads | C41: =SUMIFS(#REF!,#REF!,$A$41) -> #REF! | D41: =SUMIFS(#REF!,#REF!,$A$41) -> #REF! | E41: =SUMIFS(#REF!,#REF!,$A$41) -> #REF! | F41: =SUMIFS(#REF!,#REF!,$A$41) -> #REF! | G41: =SUMIFS(#REF!,#REF!,$A$41) -> #REF! | H41: =SUMIFS(#REF!,#REF!,$A$41) -> #REF! | I41: =SUMIFS(#REF!,#REF!,$A$41) -> #REF! | J41: =SUMIFS(#REF!,#REF!,$A$41) -> #REF! | ... N41: =SUMIFS(#REF!,#REF!,$A$41) -> #REF!
A42: Desalination Plants [All] | B42: Revenue | C42: =SUMIFS(C$30:C$41,$B$30:$B$41,$B$42) -> #REF! | D42: =SUMIFS(D$30:D$41,$B$30:$B$41,$B$42) -> #REF! | E42: =SUMIFS(E$30:E$41,$B$30:$B$41,$B$42) -> #REF! | F42: =SUMIFS(F$30:F$41,$B$30:$B$41,$B$42) -> #REF! | G42: =SUMIFS(G$30:G$41,$B$30:$B$41,$B$42) -> #REF! | H42: =SUMIFS(H$30:H$41,$B$30:$B$41,$B$42) -> #REF! | I42: =SUMIFS(I$30:I$41,$B$30:$B$41,$B$42) -> #REF! | J42: =SUMIFS(J$30:J$41,$B$30:$B$41,$B$42) -> #REF! | ... N42: =SUMIFS(N$30:N$41,$B$30:$B$41,$B$42) -> #REF!
A43: Desalination Plants [All] | B43: Production Costs | C43: =SUMIFS(C$30:C$41,$B$30:$B$41,$B$43) -> #REF! | D43: =SUMIFS(D$30:D$41,$B$30:$B$41,$B$43) -> #REF! | E43: =SUMIFS(E$30:E$41,$B$30:$B$41,$B$43) -> #REF! | F43: =SUMIFS(F$30:F$41,$B$30:$B$41,$B$43) -> #REF! | G43: =SUMIFS(G$30:G$41,$B$30:$B$41,$B$43) -> #REF! | H43: =SUMIFS(H$30:H$41,$B$30:$B$41,$B$43) -> #REF! | I43: =SUMIFS(I$30:I$41,$B$30:$B$41,$B$43) -> #REF! | J43: =SUMIFS(J$30:J$41,$B$30:$B$41,$B$43) -> #REF! | ... N43: =SUMIFS(N$30:N$41,$B$30:$B$41,$B$43) -> #REF!
A44: Desalination Plants [All] | B44: Other Production Costs | C44: =SUMIFS(C$30:C$41,$B$30:$B$41,$B$44) -> #REF! | D44: =SUMIFS(D$30:D$41,$B$30:$B$41,$B$44) -> #REF! | E44: =SUMIFS(E$30:E$41,$B$30:$B$41,$B$44) -> #REF! | F44: =SUMIFS(F$30:F$41,$B$30:$B$41,$B$44) -> #REF! | G44: =SUMIFS(G$30:G$41,$B$30:$B$41,$B$44) -> #REF! | H44: =SUMIFS(H$30:H$41,$B$30:$B$41,$B$44) -> #REF! | I44: =SUMIFS(I$30:I$41,$B$30:$B$41,$B$44) -> #REF! | J44: =SUMIFS(J$30:J$41,$B$30:$B$41,$B$44) -> #REF! | ... N44: =SUMIFS(N$30:N$41,$B$30:$B$41,$B$44) -> #REF!
A45: Desalination Plants [All] | B45: Overheads | C45: =SUMIFS(C$30:C$41,$B$30:$B$41,$B$45) -> #REF! | D45: =SUMIFS(D$30:D$41,$B$30:$B$41,$B$45) -> #REF! | E45: =SUMIFS(E$30:E$41,$B$30:$B$41,$B$45) -> #REF! | F45: =SUMIFS(F$30:F$41,$B$30:$B$41,$B$45) -> #REF! | G45: =SUMIFS(G$30:G$41,$B$30:$B$41,$B$45) -> #REF! | H45: =SUMIFS(H$30:H$41,$B$30:$B$41,$B$45) -> #REF! | I45: =SUMIFS(I$30:I$41,$B$30:$B$41,$B$45) -> #REF! | J45: =SUMIFS(J$30:J$41,$B$30:$B$41,$B$45) -> #REF! | ... N45: =SUMIFS(N$30:N$41,$B$30:$B$41,$B$45) -> #REF!
A46: Variance
A47: Q1c. Calculate the Variance for the Revenues (Actuals - Budget) for Kootha, Surjek and Jutik and populate this in the below table referencing the Budget and Actual Tables you have populated above.
A48: Q2c. Calculate the Variance for the Production Costs, Production Other Costs and Overheads for Kootha, Surjek and Jutik and populate this in the below table referencing the Budget and Actual Tables you have populated above.
A49: Note for Mentors: | B49: If the variance is negative, this is not a bad indicator. Check the numbers. i.e. If Revenue Actuals was -8.4M but Budget was -8.2M, then we have earned an additional -0.2M. Similarly, positive numbers are not necessarily a good sign.
A50: Desalination Plants [All] | C50: 2013/Jul | D50: 2013/Aug | E50: 2013/Sep | F50: 2013/Oct | G50: 2013/Nov | H50: 2013/Dec | I50: 2014/Jan | J50: 2014/Feb | K50: 2014/Mar | L50: 2014/Apr | M50: 2014/May | N50: 2014/Jun
A51: Kootha (1 Major Desal Unit) | B51: Revenue | C51: =C30-C9 -> #REF! | D51: =D30-D9 -> #REF! | E51: =E30-E9 -> #REF! | F51: =F30-F9 -> #REF! | G51: =G30-G9 -> #REF! | H51: =H30-H9 -> #REF! | I51: =I30-I9 -> #REF! | J51: =J30-J9 -> #REF! | ... N51: =N30-N9 -> #REF!
B52: Production | C52: =C31-C10 -> #REF! | D52: =D31-D10 -> #REF! | E52: =E31-E10 -> #REF! | F52: =F31-F10 -> #REF! | G52: =G31-G10 -> #REF! | H52: =H31-H10 -> #REF! | I52: =I31-I10 -> #REF! | J52: =J31-J10 -> #REF! | ... N52: =N31-N10 -> #REF!
B53: Production Other | C53: =C32-C11 -> #REF! | D53: =D32-D11 -> #REF! | E53: =E32-E11 -> #REF! | F53: =F32-F11 -> #REF! | G53: =G32-G11 -> #REF! | H53: =H32-H11 -> #REF! | I53: =I32-I11 -> #REF! | J53: =J32-J11 -> #REF! | ... N53: =N32-N11 -> #REF!
B54: Overheads | C54: =C33-C12 -> #REF! | D54: =D33-D12 -> #REF! | E54: =E33-E12 -> #REF! | F54: =F33-F12 -> #REF! | G54: =G33-G12 -> #REF! | H54: =H33-H12 -> #REF! | I54: =I33-I12 -> #REF! | J54: =J33-J12 -> #REF! | ... N54: =N33-N12 -> #REF!
A55: Surjek (4 Major Desal. Plants) | B55: Revenue | C55: =C34-C13 -> #REF! | D55: =D34-D13 -> #REF! | E55: =E34-E13 -> #REF! | F55: =F34-F13 -> #REF! | G55: =G34-G13 -> #REF! | H55: =H34-H13 -> #REF! | I55: =I34-I13 -> #REF! | J55: =J34-J13 -> #REF! | ... N55: =N34-N13 -> #REF!
B56: Production | C56: =C35-C14 -> #REF! | D56: =D35-D14 -> #REF! | E56: =E35-E14 -> #REF! | F56: =F35-F14 -> #REF! | G56: =G35-G14 -> #REF! | H56: =H35-H14 -> #REF! | I56: =I35-I14 -> #REF! | J56: =J35-J14 -> #REF! | ... N56: =N35-N14 -> #REF!
B57: Production Other | C57: =C36-C15 -> #REF! | D57: =D36-D15 -> #REF! | E57: =E36-E15 -> #REF! | F57: =F36-F15 -> #REF! | G57: =G36-G15 -> #REF! | H57: =H36-H15 -> #REF! | I57: =I36-I15 -> #REF! | J57: =J36-J15 -> #REF! | ... N57: =N36-N15 -> #REF!
B58: Overheads | C58: =C37-C16 -> #REF! | D58: =D37-D16 -> #REF! | E58: =E37-E16 -> #REF! | F58: =F37-F16 -> #REF! | G58: =G37-G16 -> #REF! | H58: =H37-H16 -> #REF! | I58: =I37-I16 -> #REF! | J58: =J37-J16 -> #REF! | ... N58: =N37-N16 -> #REF!
A59: Jutik Desalination Plant [Newest Desalination Plant] | B59: Revenue | C59: =C38-C17 -> #REF! | D59: =D38-D17 -> #REF! | E59: =E38-E17 -> #REF! | F59: =F38-F17 -> #REF! | G59: =G38-G17 -> #REF! | H59: =H38-H17 -> #REF! | I59: =I38-I17 -> #REF! | J59: =J38-J17 -> #REF! | ... N59: =N38-N17 -> #REF!
B60: Production | C60: =C39-C18 -> #REF! | D60: =D39-D18 -> #REF! | E60: =E39-E18 -> #REF! | F60: =F39-F18 -> #REF! | G60: =G39-G18 -> #REF! | H60: =H39-H18 -> #REF! | I60: =I39-I18 -> #REF! | J60: =J39-J18 -> #REF! | ... N60: =N39-N18 -> #REF!
B61: Production Other | C61: =C40-C19 -> #REF! | D61: =D40-D19 -> #REF! | E61: =E40-E19 -> #REF! | F61: =F40-F19 -> #REF! | G61: =G40-G19 -> #REF! | H61: =H40-H19 -> #REF! | I61: =I40-I19 -> #REF! | J61: =J40-J19 -> #REF! | ... N61: =N40-N19 -> #REF!
B62: Overheads | C62: =C41-C20 -> #REF! | D62: =D41-D20 -> #REF! | E62: =E41-E20 -> #REF! | F62: =F41-F20 -> #REF! | G62: =G41-G20 -> #REF! | H62: =H41-H20 -> #REF! | I62: =I41-I20 -> #REF! | J62: =J41-J20 -> #REF! | ... N62: =N41-N20 -> #REF!
A63: Desalination Plants [All] | B63: Revenue | C63: =C42-C21 -> #REF! | D63: =D42-D21 -> #REF! | E63: =E42-E21 -> #REF! | F63: =F42-F21 -> #REF! | G63: =G42-G21 -> #REF! | H63: =H42-H21 -> #REF! | I63: =I42-I21 -> #REF! | J63: =J42-J21 -> #REF! | ... N63: =N42-N21 -> #REF!
B64: Production | C64: =C43-C22 -> #REF! | D64: =D43-D22 -> #REF! | E64: =E43-E22 -> #REF! | F64: =F43-F22 -> #REF! | G64: =G43-G22 -> #REF! | H64: =H43-H22 -> #REF! | I64: =I43-I22 -> #REF! | J64: =J43-J22 -> #REF! | ... N64: =N43-N22 -> #REF!
B65: Production Other | C65: =C44-C23 -> #REF! | D65: =D44-D23 -> #REF! | E65: =E44-E23 -> #REF! | F65: =F44-F23 -> #REF! | G65: =G44-G23 -> #REF! | H65: =H44-H23 -> #REF! | I65: =I44-I23 -> #REF! | J65: =J44-J23 -> #REF! | ... N65: =N44-N23 -> #REF!
B66: Overheads | C66: =C45-C24 -> #REF! | D66: =D45-D24 -> #REF! | E66: =E45-E24 -> #REF! | F66: =F45-F24 -> #REF! | G66: =G45-G24 -> #REF! | H66: =H45-H24 -> #REF! | I66: =I45-I24 -> #REF! | J66: =J45-J24 -> #REF! | ... N66: =N45-N24 -> #REF!
A67: Variance % In the Case Study, SW Corp's Management had requested you to inform them of any costs that varied > 5% than the Budget. This is known as the Variance Percentage Difference. We calculate this as Management care more about a cost varying by a percentage, than say, a specific dollar value. For example, what is easier to note down? "Production Costs varied by 5.1% for June, and July." OR "Production Costs varied by $107,299.54 for June and $202921.19 for July". This is why Variance Reporting is generally in % as opposed to dollars.
A68: Q1d) Calculate the Variance % for Revenue using the following formula: ( Variance Result (Calculated Above) / Budget ) * 100. Don't forget to highlight the periods where variance is > 5%.
A69: Q2d) Calculate the Variance % for Production, Production Other and Overheads using the following formula: ( Variance Result (Calculated Above) / Budget ) * 100. Don't forget to highlight the periods where variance is > 5%.
A71: Desalination Plants [All] | C71: 2013/Jul | D71: 2013/Aug | E71: 2013/Sep | F71: 2013/Oct | G71: 2013/Nov | H71: 2013/Dec | I71: 2014/Jan | J71: 2014/Feb | K71: 2014/Mar | L71: 2014/Apr | M71: 2014/May | N71: 2014/Jun
A72: Kootha (1 Major Desal Unit) | B72: Revenue | C72: =(C51/C9)*100 -> #REF! | D72: =(D51/D9)*100 -> #REF! | E72: =(E51/E9)*100 -> #REF! | F72: =(F51/F9)*100 -> #REF! | G72: =(G51/G9)*100 -> #REF! | H72: =(H51/H9)*100 -> #REF! | I72: =(I51/I9)*100 -> #REF! | J72: =(J51/J9)*100 -> #REF! | ... N72: =(N51/N9)*100 -> #REF!
B73: Production | C73: =(C52/C10)*100 -> #REF! | D73: =(D52/D10)*100 -> #REF! | E73: =(E52/E10)*100 -> #REF! | F73: =(F52/F10)*100 -> #REF! | G73: =(G52/G10)*100 -> #REF! | H73: =(H52/H10)*100 -> #REF! | I73: =(I52/I10)*100 -> #REF! | J73: =(J52/J10)*100 -> #REF! | ... N73: =(N52/N10)*100 -> #REF!
B74: Production Other | C74: =(C53/C11)*100 -> #REF! | D74: =(D53/D11)*100 -> #REF! | E74: =(E53/E11)*100 -> #REF! | F74: =(F53/F11)*100 -> #REF! | G74: =(G53/G11)*100 -> #REF! | H74: =(H53/H11)*100 -> #REF! | I74: =(I53/I11)*100 -> #REF! | J74: =(J53/J11)*100 -> #REF! | ... N74: =(N53/N11)*100 -> #REF!
B75: Overheads | C75: =(C54/C12)*100 -> #REF! | D75: =(D54/D12)*100 -> #REF! | E75: =(E54/E12)*100 -> #REF! | F75: =(F54/F12)*100 -> #REF! | G75: =(G54/G12)*100 -> #REF! | H75: =(H54/H12)*100 -> #REF! | I75: =(I54/I12)*100 -> #REF! | J75: =(J54/J12)*100 -> #REF! | ... N75: =(N54/N12)*100 -> #REF!
A76: Surjek (4 Major Desal. Plants) | B76: Revenue | C76: =(C55/C13)*100 -> #REF! | D76: =(D55/D13)*100 -> #REF! | E76: =(E55/E13)*100 -> #REF! | F76: =(F55/F13)*100 -> #REF! | G76: =(G55/G13)*100 -> #REF! | H76: =(H55/H13)*100 -> #REF! | I76: =(I55/I13)*100 -> #REF! | J76: =(J55/J13)*100 -> #REF! | ... N76: =(N55/N13)*100 -> #REF!
B77: Production | C77: =(C56/C14)*100 -> #REF! | D77: =(D56/D14)*100 -> #REF! | E77: =(E56/E14)*100 -> #REF! | F77: =(F56/F14)*100 -> #REF! | G77: =(G56/G14)*100 -> #REF! | H77: =(H56/H14)*100 -> #REF! | I77: =(I56/I14)*100 -> #REF! | J77: =(J56/J14)*100 -> #REF! | ... N77: =(N56/N14)*100 -> #REF!
B78: Production Other | C78: =(C57/C15)*100 -> #REF! | D78: =(D57/D15)*100 -> #REF! | E78: =(E57/E15)*100 -> #REF! | F78: =(F57/F15)*100 -> #REF! | G78: =(G57/G15)*100 -> #REF! | H78: =(H57/H15)*100 -> #REF! | I78: =(I57/I15)*100 -> #REF! | J78: =(J57/J15)*100 -> #REF! | ... N78: =(N57/N15)*100 -> #REF!
B79: Overheads | C79: =(C58/C16)*100 -> #REF! | D79: =(D58/D16)*100 -> #REF! | E79: =(E58/E16)*100 -> #REF! | F79: =(F58/F16)*100 -> #REF! | G79: =(G58/G16)*100 -> #REF! | H79: =(H58/H16)*100 -> #REF! | I79: =(I58/I16)*100 -> #REF! | J79: =(J58/J16)*100 -> #REF! | ... N79: =(N58/N16)*100 -> #REF!
A80: Jutik Desalination Plant [Newest Desalination Plant] | B80: Revenue | C80: =(C59/C17)*100 -> #REF! | D80: =(D59/D17)*100 -> #REF! | E80: =(E59/E17)*100 -> #REF! | F80: =(F59/F17)*100 -> #REF! | G80: =(G59/G17)*100 -> #REF! | H80: =(H59/H17)*100 -> #REF! | I80: =(I59/I17)*100 -> #REF! | J80: =(J59/J17)*100 -> #REF! | ... N80: =(N59/N17)*100 -> #REF!
B81: Production | C81: =(C60/C18)*100 -> #REF! | D81: =(D60/D18)*100 -> #REF! | E81: =(E60/E18)*100 -> #REF! | F81: =(F60/F18)*100 -> #REF! | G81: =(G60/G18)*100 -> #REF! | H81: =(H60/H18)*100 -> #REF! | I81: =(I60/I18)*100 -> #REF! | J81: =(J60/J18)*100 -> #REF! | ... N81: =(N60/N18)*100 -> #REF!
B82: Production Other | C82: =(C61/C19)*100 -> #REF! | D82: =(D61/D19)*100 -> #REF! | E82: =(E61/E19)*100 -> #REF! | F82: =(F61/F19)*100 -> #REF! | G82: =(G61/G19)*100 -> #REF! | H82: =(H61/H19)*100 -> #REF! | I82: =(I61/I19)*100 -> #REF! | J82: =(J61/J19)*100 -> #REF! | ... N82: =(N61/N19)*100 -> #REF!
B83: Overheads | C83: =(C62/C20)*100 -> #REF! | D83: =(D62/D20)*100 -> #REF! | E83: =(E62/E20)*100 -> #REF! | F83: =(F62/F20)*100 -> #REF! | G83: =(G62/G20)*100 -> #REF! | H83: =(H62/H20)*100 -> #REF! | I83: =(I62/I20)*100 -> #REF! | J83: =(J62/J20)*100 -> #REF! | ... N83: =(N62/N20)*100 -> #REF!
A84: Desalination Plants [All] | B84: Revenue | C84: =(C63/C21)*100 -> #REF! | D84: =(D63/D21)*100 -> #REF! | E84: =(E63/E21)*100 -> #REF! | F84: =(F63/F21)*100 -> #REF! | G84: =(G63/G21)*100 -> #REF! | H84: =(H63/H21)*100 -> #REF! | I84: =(I63/I21)*100 -> #REF! | J84: =(J63/J21)*100 -> #REF! | ... N84: =(N63/N21)*100 -> #REF!
B85: Production | C85: =(C64/C22)*100 -> #REF! | D85: =(D64/D22)*100 -> #REF! | E85: =(E64/E22)*100 -> #REF! | F85: =(F64/F22)*100 -> #REF! | G85: =(G64/G22)*100 -> #REF! | H85: =(H64/H22)*100 -> #REF! | I85: =(I64/I22)*100 -> #REF! | J85: =(J64/J22)*100 -> #REF! | ... N85: =(N64/N22)*100 -> #REF!
B86: Production Other | C86: =(C65/C23)*100 -> #REF! | D86: =(D65/D23)*100 -> #REF! | E86: =(E65/E23)*100 -> #REF! | F86: =(F65/F23)*100 -> #REF! | G86: =(G65/G23)*100 -> #REF! | H86: =(H65/H23)*100 -> #REF! | I86: =(I65/I23)*100 -> #REF! | J86: =(J65/J23)*100 -> #REF! | ... N86: =(N65/N23)*100 -> #REF!
B87: Overheads | C87: =(C66/C24)*100 -> #REF! | D87: =(D66/D24)*100 -> #REF! | E87: =(E66/E24)*100 -> #REF! | F87: =(F66/F24)*100 -> #REF! | G87: =(G66/G24)*100 -> #REF! | H87: =(H66/H24)*100 -> #REF! | I87: =(I66/I24)*100 -> #REF! | J87: =(J66/J24)*100 -> #REF! | ... N87: =(N66/N24)*100 -> #REF!
A120: EBIT VARIANCE ANALYSIS | B120: 2013/Jul | C120: 2013/Aug | D120: 2013/Sep | E120: 2013/Oct | F120: 2013/Nov | G120: 2013/Dec | H120: 2014/Jan | I120: 2014/Feb | J120: 2014/Mar | K120: 2014/Apr | L120: 2014/May | M120: 2014/Jun
A121: Overheads [ ALL ] | B121: =EBIT!C7-EBIT!C36 -> #REF! | C121: =EBIT!D7-EBIT!D36 -> #REF! | D121: =EBIT!E7-EBIT!E36 -> #REF! | E121: =EBIT!F7-EBIT!F36 -> #REF! | F121: =EBIT!G7-EBIT!G36 -> #REF! | G121: =EBIT!H7-EBIT!H36 -> #REF! | H121: =EBIT!I7-EBIT!I36 -> #REF! | I121: =EBIT!J7-EBIT!J36 -> #REF! | ... M121: =EBIT!N7-EBIT!N36 -> #REF!
A122: Production Costs [ALL] | B122: =EBIT!C8-EBIT!C37 -> #REF! | C122: =EBIT!D8-EBIT!D37 -> #REF! | D122: =EBIT!E8-EBIT!E37 -> #REF! | E122: =EBIT!F8-EBIT!F37 -> #REF! | F122: =EBIT!G8-EBIT!G37 -> #REF! | G122: =EBIT!H8-EBIT!H37 -> #REF! | H122: =EBIT!I8-EBIT!I37 -> #REF! | I122: =EBIT!J8-EBIT!J37 -> #REF! | ... M122: =EBIT!N8-EBIT!N37 -> #REF!
A123: Other Production Costs [ALL] | B123: =EBIT!C9-EBIT!C38 -> #REF! | C123: =EBIT!D9-EBIT!D38 -> #REF! | D123: =EBIT!E9-EBIT!E38 -> #REF! | E123: =EBIT!F9-EBIT!F38 -> #REF! | F123: =EBIT!G9-EBIT!G38 -> #REF! | G123: =EBIT!H9-EBIT!H38 -> #REF! | H123: =EBIT!I9-EBIT!I38 -> #REF! | I123: =EBIT!J9-EBIT!J38 -> #REF! | ... M123: =EBIT!N9-EBIT!N38 -> #REF!
A124: Revenue | B124: =EBIT!C39-EBIT!C10 -> #REF! | C124: =EBIT!D39-EBIT!D10 -> #REF! | D124: =EBIT!E39-EBIT!E10 -> #REF! | E124: =EBIT!F39-EBIT!F10 -> #REF! | F124: =EBIT!G39-EBIT!G10 -> #REF! | G124: =EBIT!H39-EBIT!H10 -> #REF! | H124: =EBIT!I39-EBIT!I10 -> #REF! | I124: =EBIT!J39-EBIT!J10 -> #REF! | ... M124: =EBIT!N39-EBIT!N10 -> #REF!
A125: EBIT Variance | B125: =EBIT!C11-EBIT!C40 -> #REF! | C125: =EBIT!D11-EBIT!D40 -> #REF! | D125: =EBIT!E11-EBIT!E40 -> #REF! | E125: =EBIT!F11-EBIT!F40 -> #REF! | F125: =EBIT!G11-EBIT!G40 -> #REF! | G125: =EBIT!H11-EBIT!H40 -> #REF! | H125: =EBIT!I11-EBIT!I40 -> #REF! | I125: =EBIT!J11-EBIT!J40 -> #REF! | ... M125: =EBIT!N11-EBIT!N40 -> #REF!

Sheet Cost to Produce
A1: So why do we care about Cost to Produce? Cost to Produce is used as an financial indicator to identify how Cost Effective Southern Water Corp. is with producing Desalinated Water. Financial Analysts will use this data to indicate if Southern Water Corp is more or less cost effective than its immediate peers. If we didn't have this measure, we wouldn't be able to effectively gauge how cost effective Southern Water Corp is with respect to its water production.
A3: Cost to Produce Calculation
A4: (Overheads + Production Cost + Other Production Costs) / Gross Water Production
A5: Q1. Calculate the Actual Cost to Produce for each Desalination Unit (Kootha, Surjek, Jutik, Overall). Don't forget to reference the Variance Analysis Tab whilst using the SUMIFS Formula to extract the necessary Overheads, Production Costs and Other Production Cost Data! The first formula (row 12) has been done for you. Follow this approach for the rest of the Units. Note: The Water Production Data can be taken from the respective Water Production Actuals and Budget Tabs. Don't forget to do the CONVERSION into MEGA LITRES from GIGA LITRES.
A6: Kootha ACTUALS
A7: Desalinated Water Production Per Litre ($/ML) | B7: Units | C7: 2013/Jul | D7: 2013/Aug | E7: 2013/Sep | F7: 2013/Oct | G7: 2013/Nov | H7: 2013/Dec | I7: 2014/Jan | J7: 2014/Feb | K7: 2014/Mar | L7: 2014/Apr | M7: 2014/May | N7: 2014/Jun
A8: Overheads [ ALL ] | B8: $ | C8: =SUMIFS('Variance Analysis'!C$30:C$45,'Variance Analysis'!$B$30:$B$45,'Variance Analysis'!$B33,'Variance Analysis'!$A$30:$A$45,'Variance Analysis'!$A$30) -> #REF! | D8: =SUMIFS('Variance Analysis'!D$30:D$45,'Variance Analysis'!$B$30:$B$45,'Variance Analysis'!$B33,'Variance Analysis'!$A$30:$A$45,'Variance Analysis'!$A$30) -> #REF! | E8: =SUMIFS('Variance Analysis'!E$30:E$45,'Variance Analysis'!$B$30:$B$45,'Variance Analysis'!$B33,'Variance Analysis'!$A$30:$A$45,'Variance Analysis'!$A$30) -> #REF! | F8: =SUMIFS('Variance Analysis'!F$30:F$45,'Variance Analysis'!$B$30:$B$45,'Variance Analysis'!$B33,'Variance Analysis'!$A$30:$A$45,'Variance Analysis'!$A$30) -> #REF! | G8: =SUMIFS('Variance Analysis'!G$30:G$45,'Variance Analysis'!$B$30:$B$45,'Variance Analysis'!$B33,'Variance Analysis'!$A$30:$A$45,'Variance Analysis'!$A$30) -> #REF! | H8: =SUMIFS('Variance Analysis'!H$30:H$45,'Variance Analysis'!$B$30:$B$45,'Variance Analysis'!$B33,'Variance Analysis'!$A$30:$A$45,'Variance Analysis'!$A$30) -> #REF! | I8: =SUMIFS('Variance Analysis'!I$30:I$45,'Variance Analysis'!$B$30:$B$45,'Variance Analysis'!$B33,'Variance Analysis'!$A$30:$A$45,'Variance Analysis'!$A$30) -> #REF! | J8: =SUMIFS('Variance Analysis'!J$30:J$45,'Variance Analysis'!$B$30:$B$45,'Variance Analysis'!$B33,'Variance Analysis'!$A$30:$A$45,'Variance Analysis'!$A$30) -> #REF! | ... N8: =SUMIFS('Variance Analysis'!N$30:N$45,'Variance Analysis'!$B$30:$B$45,'Variance Analysis'!$B33,'Variance Analysis'!$A$30:$A$45,'Variance Analysis'!$A$30) -> #REF!
A9: Production Costs [ALL] | B9: $ | C9: =SUMIFS('Variance Analysis'!C$30:C$45,'Variance Analysis'!$B$30:$B$45,'Variance Analysis'!$B$31,'Variance Analysis'!$A$30:$A$45,'Variance Analysis'!$A$30) -> #REF! | D9: =SUMIFS('Variance Analysis'!D$30:D$45,'Variance Analysis'!$B$30:$B$45,'Variance Analysis'!$B$31,'Variance Analysis'!$A$30:$A$45,'Variance Analysis'!$A$30) -> #REF! | E9: =SUMIFS('Variance Analysis'!E$30:E$45,'Variance Analysis'!$B$30:$B$45,'Variance Analysis'!$B$31,'Variance Analysis'!$A$30:$A$45,'Variance Analysis'!$A$30) -> #REF! | F9: =SUMIFS('Variance Analysis'!F$30:F$45,'Variance Analysis'!$B$30:$B$45,'Variance Analysis'!$B$31,'Variance Analysis'!$A$30:$A$45,'Variance Analysis'!$A$30) -> #REF! | G9: =SUMIFS('Variance Analysis'!G$30:G$45,'Variance Analysis'!$B$30:$B$45,'Variance Analysis'!$B$31,'Variance Analysis'!$A$30:$A$45,'Variance Analysis'!$A$30) -> #REF! | H9: =SUMIFS('Variance Analysis'!H$30:H$45,'Variance Analysis'!$B$30:$B$45,'Variance Analysis'!$B$31,'Variance Analysis'!$A$30:$A$45,'Variance Analysis'!$A$30) -> #REF! | I9: =SUMIFS('Variance Analysis'!I$30:I$45,'Variance Analysis'!$B$30:$B$45,'Variance Analysis'!$B$31,'Variance Analysis'!$A$30:$A$45,'Variance Analysis'!$A$30) -> #REF! | J9: =SUMIFS('Variance Analysis'!J$30:J$45,'Variance Analysis'!$B$30:$B$45,'Variance Analysis'!$B$31,'Variance Analysis'!$A$30:$A$45,'Variance Analysis'!$A$30) -> #REF! | ... N9: =SUMIFS('Variance Analysis'!N$30:N$45,'Variance Analysis'!$B$30:$B$45,'Variance Analysis'!$B$31,'Variance Analysis'!$A$30:$A$45,'Variance Analysis'!$A$30) -> #REF!
A10: Other Production Costs [ALL] | B10: $ | C10: =SUMIFS('Variance Analysis'!C$30:C$45,'Variance Analysis'!$B$30:$B$45,'Variance Analysis'!$B32,'Variance Analysis'!$A$30:$A$45,'Variance Analysis'!$A$30) -> #REF! | D10: =SUMIFS('Variance Analysis'!D$30:D$45,'Variance Analysis'!$B$30:$B$45,'Variance Analysis'!$B32,'Variance Analysis'!$A$30:$A$45,'Variance Analysis'!$A$30) -> #REF! | E10: =SUMIFS('Variance Analysis'!E$30:E$45,'Variance Analysis'!$B$30:$B$45,'Variance Analysis'!$B32,'Variance Analysis'!$A$30:$A$45,'Variance Analysis'!$A$30) -> #REF! | F10: =SUMIFS('Variance Analysis'!F$30:F$45,'Variance Analysis'!$B$30:$B$45,'Variance Analysis'!$B32,'Variance Analysis'!$A$30:$A$45,'Variance Analysis'!$A$30) -> #REF! | G10: =SUMIFS('Variance Analysis'!G$30:G$45,'Variance Analysis'!$B$30:$B$45,'Variance Analysis'!$B32,'Variance Analysis'!$A$30:$A$45,'Variance Analysis'!$A$30) -> #REF! | H10: =SUMIFS('Variance Analysis'!H$30:H$45,'Variance Analysis'!$B$30:$B$45,'Variance Analysis'!$B32,'Variance Analysis'!$A$30:$A$45,'Variance Analysis'!$A$30) -> #REF! | I10: =SUMIFS('Variance Analysis'!I$30:I$45,'Variance Analysis'!$B$30:$B$45,'Variance Analysis'!$B32,'Variance Analysis'!$A$30:$A$45,'Variance Analysis'!$A$30) -> #REF! | J10: =SUMIFS('Variance Analysis'!J$30:J$45,'Variance Analysis'!$B$30:$B$45,'Variance Analysis'!$B32,'Variance Analysis'!$A$30:$A$45,'Variance Analysis'!$A$30) -> #REF! | ... N10: =SUMIFS('Variance Analysis'!N$30:N$45,'Variance Analysis'!$B$30:$B$45,'Variance Analysis'!$B32,'Variance Analysis'!$A$30:$A$45,'Variance Analysis'!$A$30) -> #REF!
A11: Kootha (1 Major Desal Unit) | B11: Mega-Litres (Needs to be converted from Giga-Litres) | C11: =#REF! -> #REF! | D11: =#REF! -> #REF! | E11: =#REF! -> #REF! | F11: =#REF! -> #REF! | G11: =#REF! -> #REF! | H11: =#REF! -> #REF! | I11: =#REF! -> #REF! | J11: =#REF! -> #REF! | ... N11: =#REF! -> #REF!
A12: Actual Cost to Produce (Rolling) | B12: $/Mega-Litres | C12: =SUM($C$8:C10)/(SUM($C$11:C11)*1000) -> #REF! | D12: =SUM($C$8:D10)/(SUM($C$11:D11)*1000) -> #REF! | E12: =SUM($C$8:E10)/(SUM($C$11:E11)*1000) -> #REF! | F12: =SUM($C$8:F10)/(SUM($C$11:F11)*1000) -> #REF! | G12: =SUM($C$8:G10)/(SUM($C$11:G11)*1000) -> #REF! | H12: =SUM($C$8:H10)/(SUM($C$11:H11)*1000) -> #REF! | I12: =SUM($C$8:I10)/(SUM($C$11:I11)*1000) -> #REF! | J12: =SUM($C$8:J10)/(SUM($C$11:J11)*1000) -> #REF! | ... N12: =SUM($C$8:N10)/(SUM($C$11:N11)*1000) -> #REF!
A14: Surjek ACTUALS
A15: Desalinated Water Production Per Litre ($/ML) | B15: Units | C15: 2013/Jul | D15: 2013/Aug | E15: 2013/Sep | F15: 2013/Oct | G15: 2013/Nov | H15: 2013/Dec | I15: 2014/Jan | J15: 2014/Feb | K15: 2014/Mar | L15: 2014/Apr | M15: 2014/May | N15: 2014/Jun
A16: Overheads [ ALL ] | B16: $ | C16: =SUMIFS('Variance Analysis'!C$30:C$45,'Variance Analysis'!$B$30:$B$45,'Variance Analysis'!$B37,'Variance Analysis'!$A$30:$A$45,'Variance Analysis'!$A$34) -> #REF! | D16: =SUMIFS('Variance Analysis'!D$30:D$45,'Variance Analysis'!$B$30:$B$45,'Variance Analysis'!$B37,'Variance Analysis'!$A$30:$A$45,'Variance Analysis'!$A$34) -> #REF! | E16: =SUMIFS('Variance Analysis'!E$30:E$45,'Variance Analysis'!$B$30:$B$45,'Variance Analysis'!$B37,'Variance Analysis'!$A$30:$A$45,'Variance Analysis'!$A$34) -> #REF! | F16: =SUMIFS('Variance Analysis'!F$30:F$45,'Variance Analysis'!$B$30:$B$45,'Variance Analysis'!$B37,'Variance Analysis'!$A$30:$A$45,'Variance Analysis'!$A$34) -> #REF! | G16: =SUMIFS('Variance Analysis'!G$30:G$45,'Variance Analysis'!$B$30:$B$45,'Variance Analysis'!$B37,'Variance Analysis'!$A$30:$A$45,'Variance Analysis'!$A$34) -> #REF! | H16: =SUMIFS('Variance Analysis'!H$30:H$45,'Variance Analysis'!$B$30:$B$45,'Variance Analysis'!$B37,'Variance Analysis'!$A$30:$A$45,'Variance Analysis'!$A$34) -> #REF! | I16: =SUMIFS('Variance Analysis'!I$30:I$45,'Variance Analysis'!$B$30:$B$45,'Variance Analysis'!$B37,'Variance Analysis'!$A$30:$A$45,'Variance Analysis'!$A$34) -> #REF! | J16: =SUMIFS('Variance Analysis'!J$30:J$45,'Variance Analysis'!$B$30:$B$45,'Variance Analysis'!$B37,'Variance Analysis'!$A$30:$A$45,'Variance Analysis'!$A$34) -> #REF! | ... N16: =SUMIFS('Variance Analysis'!N$30:N$45,'Variance Analysis'!$B$30:$B$45,'Variance Analysis'!$B37,'Variance Analysis'!$A$30:$A$45,'Variance Analysis'!$A$34) -> #REF!
A17: Production Costs [ALL] | B17: $ | C17: =SUMIFS('Variance Analysis'!C$30:C$45,'Variance Analysis'!$B$30:$B$45,'Variance Analysis'!$B$35,'Variance Analysis'!$A$30:$A$45,'Variance Analysis'!$A$34) -> #REF! | D17: =SUMIFS('Variance Analysis'!D$30:D$45,'Variance Analysis'!$B$30:$B$45,'Variance Analysis'!$B$35,'Variance Analysis'!$A$30:$A$45,'Variance Analysis'!$A$34) -> #REF! | E17: =SUMIFS('Variance Analysis'!E$30:E$45,'Variance Analysis'!$B$30:$B$45,'Variance Analysis'!$B$35,'Variance Analysis'!$A$30:$A$45,'Variance Analysis'!$A$34) -> #REF! | F17: =SUMIFS('Variance Analysis'!F$30:F$45,'Variance Analysis'!$B$30:$B$45,'Variance Analysis'!$B$35,'Variance Analysis'!$A$30:$A$45,'Variance Analysis'!$A$34) -> #REF! | G17: =SUMIFS('Variance Analysis'!G$30:G$45,'Variance Analysis'!$B$30:$B$45,'Variance Analysis'!$B$35,'Variance Analysis'!$A$30:$A$45,'Variance Analysis'!$A$34) -> #REF! | H17: =SUMIFS('Variance Analysis'!H$30:H$45,'Variance Analysis'!$B$30:$B$45,'Variance Analysis'!$B$35,'Variance Analysis'!$A$30:$A$45,'Variance Analysis'!$A$34) -> #REF! | I17: =SUMIFS('Variance Analysis'!I$30:I$45,'Variance Analysis'!$B$30:$B$45,'Variance Analysis'!$B$35,'Variance Analysis'!$A$30:$A$45,'Variance Analysis'!$A$34) -> #REF! | J17: =SUMIFS('Variance Analysis'!J$30:J$45,'Variance Analysis'!$B$30:$B$45,'Variance Analysis'!$B$35,'Variance Analysis'!$A$30:$A$45,'Variance Analysis'!$A$34) -> #REF! | ... N17: =SUMIFS('Variance Analysis'!N$30:N$45,'Variance Analysis'!$B$30:$B$45,'Variance Analysis'!$B$35,'Variance Analysis'!$A$30:$A$45,'Variance Analysis'!$A$34) -> #REF!
A18: Other Production Costs [ALL] | B18: $ | C18: =SUMIFS('Variance Analysis'!C$30:C$45,'Variance Analysis'!$B$30:$B$45,'Variance Analysis'!$B36,'Variance Analysis'!$A$30:$A$45,'Variance Analysis'!$A$34) -> #REF! | D18: =SUMIFS('Variance Analysis'!D$30:D$45,'Variance Analysis'!$B$30:$B$45,'Variance Analysis'!$B36,'Variance Analysis'!$A$30:$A$45,'Variance Analysis'!$A$34) -> #REF! | E18: =SUMIFS('Variance Analysis'!E$30:E$45,'Variance Analysis'!$B$30:$B$45,'Variance Analysis'!$B36,'Variance Analysis'!$A$30:$A$45,'Variance Analysis'!$A$34) -> #REF! | F18: =SUMIFS('Variance Analysis'!F$30:F$45,'Variance Analysis'!$B$30:$B$45,'Variance Analysis'!$B36,'Variance Analysis'!$A$30:$A$45,'Variance Analysis'!$A$34) -> #REF! | G18: =SUMIFS('Variance Analysis'!G$30:G$45,'Variance Analysis'!$B$30:$B$45,'Variance Analysis'!$B36,'Variance Analysis'!$A$30:$A$45,'Variance Analysis'!$A$34) -> #REF! | H18: =SUMIFS('Variance Analysis'!H$30:H$45,'Variance Analysis'!$B$30:$B$45,'Variance Analysis'!$B36,'Variance Analysis'!$A$30:$A$45,'Variance Analysis'!$A$34) -> #REF! | I18: =SUMIFS('Variance Analysis'!I$30:I$45,'Variance Analysis'!$B$30:$B$45,'Variance Analysis'!$B36,'Variance Analysis'!$A$30:$A$45,'Variance Analysis'!$A$34) -> #REF! | J18: =SUMIFS('Variance Analysis'!J$30:J$45,'Variance Analysis'!$B$30:$B$45,'Variance Analysis'!$B36,'Variance Analysis'!$A$30:$A$45,'Variance Analysis'!$A$34) -> #REF! | ... N18: =SUMIFS('Variance Analysis'!N$30:N$45,'Variance Analysis'!$B$30:$B$45,'Variance Analysis'!$B36,'Variance Analysis'!$A$30:$A$45,'Variance Analysis'!$A$34) -> #REF!
A19: Surjek (4 Major Desal. Plants) | B19: Mega-Litres (Needs to be converted from Giga-Litres) | C19: =#REF! -> #REF! | D19: =#REF! -> #REF! | E19: =#REF! -> #REF! | F19: =#REF! -> #REF! | G19: =#REF! -> #REF! | H19: =#REF! -> #REF! | I19: =#REF! -> #REF! | J19: =#REF! -> #REF! | ... N19: =#REF! -> #REF!
A20: Actual Cost to Produce (Rolling) | B20: $/Mega-Litres | C20: =SUM($C$16:C18)/(SUM($C$19:C19*1000)) -> #REF! | D20: =SUM($C$16:D18)/(SUM($C$19:D19)*1000) -> #REF! | E20: =SUM($C$16:E18)/(SUM($C$19:E19)*1000) -> #REF! | F20: =SUM($C$16:F18)/(SUM($C$19:F19)*1000) -> #REF! | G20: =SUM($C$16:G18)/(SUM($C$19:G19)*1000) -> #REF! | H20: =SUM($C$16:H18)/(SUM($C$19:H19)*1000) -> #REF! | I20: =SUM($C$16:I18)/(SUM($C$19:I19)*1000) -> #REF! | J20: =SUM($C$16:J18)/(SUM($C$19:J19)*1000) -> #REF! | K20: =SUM($C$16:K18)/(SUM($C$19:K19)*1000) -> #REF! | ... N20: =SUM($C$16:N18)/(SUM($C$19:N19)*1000) -> #REF!
A22: Jutik ACTUALS
A23: Desalinated Water Production Per Litre ($/ML) | B23: Units | C23: 2013/Jul | D23: 2013/Aug | E23: 2013/Sep | F23: 2013/Oct | G23: 2013/Nov | H23: 2013/Dec | I23: 2014/Jan | J23: 2014/Feb | K23: 2014/Mar | L23: 2014/Apr | M23: 2014/May | N23: 2014/Jun
A24: Overheads [ ALL ] | B24: $ | C24: =SUMIFS('Variance Analysis'!C$30:C$45,'Variance Analysis'!$B$30:$B$45,'Variance Analysis'!$B$41,'Variance Analysis'!$A$30:$A$45,'Variance Analysis'!$A$41) -> #REF! | D24: =SUMIFS('Variance Analysis'!D$30:D$45,'Variance Analysis'!$B$30:$B$45,'Variance Analysis'!$B$41,'Variance Analysis'!$A$30:$A$45,'Variance Analysis'!$A$41) -> #REF! | E24: =SUMIFS('Variance Analysis'!E$30:E$45,'Variance Analysis'!$B$30:$B$45,'Variance Analysis'!$B$41,'Variance Analysis'!$A$30:$A$45,'Variance Analysis'!$A$41) -> #REF! | F24: =SUMIFS('Variance Analysis'!F$30:F$45,'Variance Analysis'!$B$30:$B$45,'Variance Analysis'!$B$41,'Variance Analysis'!$A$30:$A$45,'Variance Analysis'!$A$41) -> #REF! | G24: =SUMIFS('Variance Analysis'!G$30:G$45,'Variance Analysis'!$B$30:$B$45,'Variance Analysis'!$B$41,'Variance Analysis'!$A$30:$A$45,'Variance Analysis'!$A$41) -> #REF! | H24: =SUMIFS('Variance Analysis'!H$30:H$45,'Variance Analysis'!$B$30:$B$45,'Variance Analysis'!$B$41,'Variance Analysis'!$A$30:$A$45,'Variance Analysis'!$A$41) -> #REF! | I24: =SUMIFS('Variance Analysis'!I$30:I$45,'Variance Analysis'!$B$30:$B$45,'Variance Analysis'!$B$41,'Variance Analysis'!$A$30:$A$45,'Variance Analysis'!$A$41) -> #REF! | J24: =SUMIFS('Variance Analysis'!J$30:J$45,'Variance Analysis'!$B$30:$B$45,'Variance Analysis'!$B$41,'Variance Analysis'!$A$30:$A$45,'Variance Analysis'!$A$41) -> #REF! | ... N24: =SUMIFS('Variance Analysis'!N$30:N$45,'Variance Analysis'!$B$30:$B$45,'Variance Analysis'!$B$41,'Variance Analysis'!$A$30:$A$45,'Variance Analysis'!$A$41) -> #REF!
A25: Production Costs [ALL] | B25: $ | C25: =SUMIFS('Variance Analysis'!C$30:C$45,'Variance Analysis'!$B$30:$B$45,'Variance Analysis'!$B$39,'Variance Analysis'!$A$30:$A$45,'Variance Analysis'!$A$41) -> #REF! | D25: =SUMIFS('Variance Analysis'!D$30:D$45,'Variance Analysis'!$B$30:$B$45,'Variance Analysis'!$B$39,'Variance Analysis'!$A$30:$A$45,'Variance Analysis'!$A$41) -> #REF! | E25: =SUMIFS('Variance Analysis'!E$30:E$45,'Variance Analysis'!$B$30:$B$45,'Variance Analysis'!$B$39,'Variance Analysis'!$A$30:$A$45,'Variance Analysis'!$A$41) -> #REF! | F25: =SUMIFS('Variance Analysis'!F$30:F$45,'Variance Analysis'!$B$30:$B$45,'Variance Analysis'!$B$39,'Variance Analysis'!$A$30:$A$45,'Variance Analysis'!$A$41) -> #REF! | G25: =SUMIFS('Variance Analysis'!G$30:G$45,'Variance Analysis'!$B$30:$B$45,'Variance Analysis'!$B$39,'Variance Analysis'!$A$30:$A$45,'Variance Analysis'!$A$41) -> #REF! | H25: =SUMIFS('Variance Analysis'!H$30:H$45,'Variance Analysis'!$B$30:$B$45,'Variance Analysis'!$B$39,'Variance Analysis'!$A$30:$A$45,'Variance Analysis'!$A$41) -> #REF! | I25: =SUMIFS('Variance Analysis'!I$30:I$45,'Variance Analysis'!$B$30:$B$45,'Variance Analysis'!$B$39,'Variance Analysis'!$A$30:$A$45,'Variance Analysis'!$A$41) -> #REF! | J25: =SUMIFS('Variance Analysis'!J$30:J$45,'Variance Analysis'!$B$30:$B$45,'Variance Analysis'!$B$39,'Variance Analysis'!$A$30:$A$45,'Variance Analysis'!$A$41) -> #REF! | ... N25: =SUMIFS('Variance Analysis'!N$30:N$45,'Variance Analysis'!$B$30:$B$45,'Variance Analysis'!$B$39,'Variance Analysis'!$A$30:$A$45,'Variance Analysis'!$A$41) -> #REF!
A26: Other Production Costs [ALL] | B26: $ | C26: =SUMIFS('Variance Analysis'!C$30:C$45,'Variance Analysis'!$B$30:$B$45,'Variance Analysis'!$B40,'Variance Analysis'!$A$30:$A$45,'Variance Analysis'!$A$40) -> #REF! | D26: =SUMIFS('Variance Analysis'!D$30:D$45,'Variance Analysis'!$B$30:$B$45,'Variance Analysis'!$B40,'Variance Analysis'!$A$30:$A$45,'Variance Analysis'!$A$40) -> #REF! | E26: =SUMIFS('Variance Analysis'!E$30:E$45,'Variance Analysis'!$B$30:$B$45,'Variance Analysis'!$B40,'Variance Analysis'!$A$30:$A$45,'Variance Analysis'!$A$40) -> #REF! | F26: =SUMIFS('Variance Analysis'!F$30:F$45,'Variance Analysis'!$B$30:$B$45,'Variance Analysis'!$B40,'Variance Analysis'!$A$30:$A$45,'Variance Analysis'!$A$40) -> #REF! | G26: =SUMIFS('Variance Analysis'!G$30:G$45,'Variance Analysis'!$B$30:$B$45,'Variance Analysis'!$B40,'Variance Analysis'!$A$30:$A$45,'Variance Analysis'!$A$40) -> #REF! | H26: =SUMIFS('Variance Analysis'!H$30:H$45,'Variance Analysis'!$B$30:$B$45,'Variance Analysis'!$B40,'Variance Analysis'!$A$30:$A$45,'Variance Analysis'!$A$40) -> #REF! | I26: =SUMIFS('Variance Analysis'!I$30:I$45,'Variance Analysis'!$B$30:$B$45,'Variance Analysis'!$B40,'Variance Analysis'!$A$30:$A$45,'Variance Analysis'!$A$40) -> #REF! | J26: =SUMIFS('Variance Analysis'!J$30:J$45,'Variance Analysis'!$B$30:$B$45,'Variance Analysis'!$B40,'Variance Analysis'!$A$30:$A$45,'Variance Analysis'!$A$40) -> #REF! | ... N26: =SUMIFS('Variance Analysis'!N$30:N$45,'Variance Analysis'!$B$30:$B$45,'Variance Analysis'!$B40,'Variance Analysis'!$A$30:$A$45,'Variance Analysis'!$A$40) -> #REF!
A27: Jutik Desalination Plant [Newest Desalination Plant] | B27: Mega-Litres (Needs to be converted from Giga-Litres) | C27: =#REF! -> #REF! | D27: =#REF! -> #REF! | E27: =#REF! -> #REF! | F27: =#REF! -> #REF! | G27: =#REF! -> #REF! | H27: =#REF! -> #REF! | I27: =#REF! -> #REF! | J27: =#REF! -> #REF! | ... N27: =#REF! -> #REF!
A28: Actual Cost to Produce (Rolling) | B28: $/Mega-Litres | C28: =SUM(C24:C26)/(C27*1000) -> #REF! | D28: =SUM($C$24:D26)/(SUM($C$27:D27)*1000) -> #REF! | E28: =SUM($C$24:E26)/(SUM($C$27:E27)*1000) -> #REF! | F28: =SUM($C$24:F26)/(SUM($C$27:F27)*1000) -> #REF! | G28: =SUM($C$24:G26)/(SUM($C$27:G27)*1000) -> #REF! | H28: =SUM($C$24:H26)/(SUM($C$27:H27)*1000) -> #REF! | I28: =SUM($C$24:I26)/(SUM($C$27:I27)*1000) -> #REF! | J28: =SUM($C$24:J26)/(SUM($C$27:J27)*1000) -> #REF! | K28: =SUM($C$24:K26)/(SUM($C$27:K27)*1000) -> #REF! | ... N28: =SUM($C$24:N26)/(SUM($C$27:N27)*1000) -> #REF!
A30: Overall ACTUALS
A31: Desalinated Water Production Per Litre ($/ML) | B31: Units | C31: 2013/Jul | D31: 2013/Aug | E31: 2013/Sep | F31: 2013/Oct | G31: 2013/Nov | H31: 2013/Dec | I31: 2014/Jan | J31: 2014/Feb | K31: 2014/Mar | L31: 2014/Apr | M31: 2014/May | N31: 2014/Jun
A32: Overheads [ ALL ] | B32: $ | C32: =SUMIFS('Variance Analysis'!C$42:C$45,'Variance Analysis'!$B$42:$B$45,'Variance Analysis'!$B$45) -> #REF! | D32: =SUMIFS('Variance Analysis'!D$42:D$45,'Variance Analysis'!$B$42:$B$45,'Variance Analysis'!$B$45) -> #REF! | E32: =SUMIFS('Variance Analysis'!E$42:E$45,'Variance Analysis'!$B$42:$B$45,'Variance Analysis'!$B$45) -> #REF! | F32: =SUMIFS('Variance Analysis'!F$42:F$45,'Variance Analysis'!$B$42:$B$45,'Variance Analysis'!$B$45) -> #REF! | G32: =SUMIFS('Variance Analysis'!G$42:G$45,'Variance Analysis'!$B$42:$B$45,'Variance Analysis'!$B$45) -> #REF! | H32: =SUMIFS('Variance Analysis'!H$42:H$45,'Variance Analysis'!$B$42:$B$45,'Variance Analysis'!$B$45) -> #REF! | I32: =SUMIFS('Variance Analysis'!I$42:I$45,'Variance Analysis'!$B$42:$B$45,'Variance Analysis'!$B$45) -> #REF! | J32: =SUMIFS('Variance Analysis'!J$42:J$45,'Variance Analysis'!$B$42:$B$45,'Variance Analysis'!$B$45) -> #REF! | ... N32: =SUMIFS('Variance Analysis'!N$42:N$45,'Variance Analysis'!$B$42:$B$45,'Variance Analysis'!$B$45) -> #REF!
A33: Production Costs [ALL] | B33: $ | C33: =SUMIFS('Variance Analysis'!C$42:C$45,'Variance Analysis'!$B$42:$B$45,'Variance Analysis'!$B$43) -> #REF! | D33: =SUMIFS('Variance Analysis'!D$42:D$45,'Variance Analysis'!$B$42:$B$45,'Variance Analysis'!$B$43) -> #REF! | E33: =SUMIFS('Variance Analysis'!E$42:E$45,'Variance Analysis'!$B$42:$B$45,'Variance Analysis'!$B$43) -> #REF! | F33: =SUMIFS('Variance Analysis'!F$42:F$45,'Variance Analysis'!$B$42:$B$45,'Variance Analysis'!$B$43) -> #REF! | G33: =SUMIFS('Variance Analysis'!G$42:G$45,'Variance Analysis'!$B$42:$B$45,'Variance Analysis'!$B$43) -> #REF! | H33: =SUMIFS('Variance Analysis'!H$42:H$45,'Variance Analysis'!$B$42:$B$45,'Variance Analysis'!$B$43) -> #REF! | I33: =SUMIFS('Variance Analysis'!I$42:I$45,'Variance Analysis'!$B$42:$B$45,'Variance Analysis'!$B$43) -> #REF! | J33: =SUMIFS('Variance Analysis'!J$42:J$45,'Variance Analysis'!$B$42:$B$45,'Variance Analysis'!$B$43) -> #REF! | ... N33: =SUMIFS('Variance Analysis'!N$42:N$45,'Variance Analysis'!$B$42:$B$45,'Variance Analysis'!$B$43) -> #REF!
A34: Other Production Costs [ALL] | B34: $ | C34: =SUMIFS('Variance Analysis'!C$42:C$45,'Variance Analysis'!$B$42:$B$45,'Variance Analysis'!$B$44) -> #REF! | D34: =SUMIFS('Variance Analysis'!D$42:D$45,'Variance Analysis'!$B$42:$B$45,'Variance Analysis'!$B$44) -> #REF! | E34: =SUMIFS('Variance Analysis'!E$42:E$45,'Variance Analysis'!$B$42:$B$45,'Variance Analysis'!$B$44) -> #REF! | F34: =SUMIFS('Variance Analysis'!F$42:F$45,'Variance Analysis'!$B$42:$B$45,'Variance Analysis'!$B$44) -> #REF! | G34: =SUMIFS('Variance Analysis'!G$42:G$45,'Variance Analysis'!$B$42:$B$45,'Variance Analysis'!$B$44) -> #REF! | H34: =SUMIFS('Variance Analysis'!H$42:H$45,'Variance Analysis'!$B$42:$B$45,'Variance Analysis'!$B$44) -> #REF! | I34: =SUMIFS('Variance Analysis'!I$42:I$45,'Variance Analysis'!$B$42:$B$45,'Variance Analysis'!$B$44) -> #REF! | J34: =SUMIFS('Variance Analysis'!J$42:J$45,'Variance Analysis'!$B$42:$B$45,'Variance Analysis'!$B$44) -> #REF! | ... N34: =SUMIFS('Variance Analysis'!N$42:N$45,'Variance Analysis'!$B$42:$B$45,'Variance Analysis'!$B$44) -> #REF!
A35: Kootha (1 Major Desal Unit) | B35: Mega-Litres (Needs to be converted from Giga-Litres) | C35: =#REF! -> #REF! | D35: =#REF! -> #REF! | E35: =#REF! -> #REF! | F35: =#REF! -> #REF! | G35: =#REF! -> #REF! | H35: =#REF! -> #REF! | I35: =#REF! -> #REF! | J35: =#REF! -> #REF! | ... N35: =#REF! -> #REF!
A36: Surjek (4 Major Desal. Plants) | B36: Mega-Litres (Needs to be converted from Giga-Litres) | C36: =#REF! -> #REF! | D36: =#REF! -> #REF! | E36: =#REF! -> #REF! | F36: =#REF! -> #REF! | G36: =#REF! -> #REF! | H36: =#REF! -> #REF! | I36: =#REF! -> #REF! | J36: =#REF! -> #REF! | ... N36: =#REF! -> #REF!
A37: Jutik Desalination Plant [Newest Desalination Plant] | B37: Mega-Litres (Needs to be converted from Giga-Litres) | C37: =#REF! -> #REF! | D37: =#REF! -> #REF! | E37: =#REF! -> #REF! | F37: =#REF! -> #REF! | G37: =#REF! -> #REF! | H37: =#REF! -> #REF! | I37: =#REF! -> #REF! | J37: =#REF! -> #REF! | ... N37: =#REF! -> #REF!
A38: Actual Cost to Produce (Rolling) | B38: $/Mega-Litres | C38: =SUM($C$32:C34)/(SUM($C$35:C37)*1000) -> #REF! | D38: =SUM($C$32:D34)/(SUM($C$35:D37)*1000) -> #REF! | E38: =SUM($C$32:E34)/(SUM($C$35:E37)*1000) -> #REF! | F38: =SUM($C$32:F34)/(SUM($C$35:F37)*1000) -> #REF! | G38: =SUM($C$32:G34)/(SUM($C$35:G37)*1000) -> #REF! | H38: =SUM($C$32:H34)/(SUM($C$35:H37)*1000) -> #REF! | I38: =SUM($C$32:I34)/(SUM($C$35:I37)*1000) -> #REF! | J38: =SUM($C$32:J34)/(SUM($C$35:J37)*1000) -> #REF! | ... N38: =SUM($C$32:N34)/(SUM($C$35:N37)*1000) -> #REF!
A40: Kootha BUDGET
A41: Desalinated Water Production Per Litre ($/ML) | C41: 2013/Jul | D41: 2013/Aug | E41: 2013/Sep | F41: 2013/Oct | G41: 2013/Nov | H41: 2013/Dec | I41: 2014/Jan | J41: 2014/Feb | K41: 2014/Mar | L41: 2014/Apr | M41: 2014/May | N41: 2014/Jun
A42: Overheads [ ALL ] | B42: $ | C42: =SUMIFS('Variance Analysis'!C$9:C$24,'Variance Analysis'!$B$9:$B$24,'Variance Analysis'!$B$12,'Variance Analysis'!$A$9:$A$24,'Variance Analysis'!$A$12) -> #REF! | D42: =SUMIFS('Variance Analysis'!D$9:D$24,'Variance Analysis'!$B$9:$B$24,'Variance Analysis'!$B$12,'Variance Analysis'!$A$9:$A$24,'Variance Analysis'!$A$12) -> #REF! | E42: =SUMIFS('Variance Analysis'!E$9:E$24,'Variance Analysis'!$B$9:$B$24,'Variance Analysis'!$B$12,'Variance Analysis'!$A$9:$A$24,'Variance Analysis'!$A$12) -> #REF! | F42: =SUMIFS('Variance Analysis'!F$9:F$24,'Variance Analysis'!$B$9:$B$24,'Variance Analysis'!$B$12,'Variance Analysis'!$A$9:$A$24,'Variance Analysis'!$A$12) -> #REF! | G42: =SUMIFS('Variance Analysis'!G$9:G$24,'Variance Analysis'!$B$9:$B$24,'Variance Analysis'!$B$12,'Variance Analysis'!$A$9:$A$24,'Variance Analysis'!$A$12) -> #REF! | H42: =SUMIFS('Variance Analysis'!H$9:H$24,'Variance Analysis'!$B$9:$B$24,'Variance Analysis'!$B$12,'Variance Analysis'!$A$9:$A$24,'Variance Analysis'!$A$12) -> #REF! | I42: =SUMIFS('Variance Analysis'!I$9:I$24,'Variance Analysis'!$B$9:$B$24,'Variance Analysis'!$B$12,'Variance Analysis'!$A$9:$A$24,'Variance Analysis'!$A$12) -> #REF! | J42: =SUMIFS('Variance Analysis'!J$9:J$24,'Variance Analysis'!$B$9:$B$24,'Variance Analysis'!$B$12,'Variance Analysis'!$A$9:$A$24,'Variance Analysis'!$A$12) -> #REF! | ... N42: =SUMIFS('Variance Analysis'!N$9:N$24,'Variance Analysis'!$B$9:$B$24,'Variance Analysis'!$B$12,'Variance Analysis'!$A$9:$A$24,'Variance Analysis'!$A$12) -> #REF!
A43: Production Costs [ALL] | B43: $ | C43: =SUMIFS('Variance Analysis'!C$9:C$24,'Variance Analysis'!$B$9:$B$24,'Variance Analysis'!$B$10,'Variance Analysis'!$A$9:$A$24,'Variance Analysis'!$A$10) -> #REF! | D43: =SUMIFS('Variance Analysis'!D$9:D$24,'Variance Analysis'!$B$9:$B$24,'Variance Analysis'!$B$10,'Variance Analysis'!$A$9:$A$24,'Variance Analysis'!$A$10) -> #REF! | E43: =SUMIFS('Variance Analysis'!E$9:E$24,'Variance Analysis'!$B$9:$B$24,'Variance Analysis'!$B$10,'Variance Analysis'!$A$9:$A$24,'Variance Analysis'!$A$10) -> #REF! | F43: =SUMIFS('Variance Analysis'!F$9:F$24,'Variance Analysis'!$B$9:$B$24,'Variance Analysis'!$B$10,'Variance Analysis'!$A$9:$A$24,'Variance Analysis'!$A$10) -> #REF! | G43: =SUMIFS('Variance Analysis'!G$9:G$24,'Variance Analysis'!$B$9:$B$24,'Variance Analysis'!$B$10,'Variance Analysis'!$A$9:$A$24,'Variance Analysis'!$A$10) -> #REF! | H43: =SUMIFS('Variance Analysis'!H$9:H$24,'Variance Analysis'!$B$9:$B$24,'Variance Analysis'!$B$10,'Variance Analysis'!$A$9:$A$24,'Variance Analysis'!$A$10) -> #REF! | I43: =SUMIFS('Variance Analysis'!I$9:I$24,'Variance Analysis'!$B$9:$B$24,'Variance Analysis'!$B$10,'Variance Analysis'!$A$9:$A$24,'Variance Analysis'!$A$10) -> #REF! | J43: =SUMIFS('Variance Analysis'!J$9:J$24,'Variance Analysis'!$B$9:$B$24,'Variance Analysis'!$B$10,'Variance Analysis'!$A$9:$A$24,'Variance Analysis'!$A$10) -> #REF! | ... N43: =SUMIFS('Variance Analysis'!N$9:N$24,'Variance Analysis'!$B$9:$B$24,'Variance Analysis'!$B$10,'Variance Analysis'!$A$9:$A$24,'Variance Analysis'!$A$10) -> #REF!
A44: Other Production Costs [ALL] | B44: $ | C44: =SUMIFS('Variance Analysis'!C$9:C$24,'Variance Analysis'!$B$9:$B$24,'Variance Analysis'!$B$11,'Variance Analysis'!$A$9:$A$24,'Variance Analysis'!$A$11) -> #REF! | D44: =SUMIFS('Variance Analysis'!D$9:D$24,'Variance Analysis'!$B$9:$B$24,'Variance Analysis'!$B$11,'Variance Analysis'!$A$9:$A$24,'Variance Analysis'!$A$11) -> #REF! | E44: =SUMIFS('Variance Analysis'!E$9:E$24,'Variance Analysis'!$B$9:$B$24,'Variance Analysis'!$B$11,'Variance Analysis'!$A$9:$A$24,'Variance Analysis'!$A$11) -> #REF! | F44: =SUMIFS('Variance Analysis'!F$9:F$24,'Variance Analysis'!$B$9:$B$24,'Variance Analysis'!$B$11,'Variance Analysis'!$A$9:$A$24,'Variance Analysis'!$A$11) -> #REF! | G44: =SUMIFS('Variance Analysis'!G$9:G$24,'Variance Analysis'!$B$9:$B$24,'Variance Analysis'!$B$11,'Variance Analysis'!$A$9:$A$24,'Variance Analysis'!$A$11) -> #REF! | H44: =SUMIFS('Variance Analysis'!H$9:H$24,'Variance Analysis'!$B$9:$B$24,'Variance Analysis'!$B$11,'Variance Analysis'!$A$9:$A$24,'Variance Analysis'!$A$11) -> #REF! | I44: =SUMIFS('Variance Analysis'!I$9:I$24,'Variance Analysis'!$B$9:$B$24,'Variance Analysis'!$B$11,'Variance Analysis'!$A$9:$A$24,'Variance Analysis'!$A$11) -> #REF! | J44: =SUMIFS('Variance Analysis'!J$9:J$24,'Variance Analysis'!$B$9:$B$24,'Variance Analysis'!$B$11,'Variance Analysis'!$A$9:$A$24,'Variance Analysis'!$A$11) -> #REF! | ... N44: =SUMIFS('Variance Analysis'!N$9:N$24,'Variance Analysis'!$B$9:$B$24,'Variance Analysis'!$B$11,'Variance Analysis'!$A$9:$A$24,'Variance Analysis'!$A$11) -> #REF!
A45: Kootha (1 Major Desal Unit) | B45: Mega-Litres (Needs to be converted from Giga-Litres) | C45: =#REF! -> #REF! | D45: =#REF! -> #REF! | E45: =#REF! -> #REF! | F45: =#REF! -> #REF! | G45: =#REF! -> #REF! | H45: =#REF! -> #REF! | I45: =#REF! -> #REF! | J45: =#REF! -> #REF! | ... N45: =#REF! -> #REF!
A46: Budget Cost to Produce (Rolling) | B46: $/Mega-Litres | C46: =SUM($C$42:C44)/(SUM($C$45:C45)*1000) -> #REF! | D46: =SUM($C$42:D44)/(SUM($C$45:D45)*1000) -> #REF! | E46: =SUM($C$42:E44)/(SUM($C$45:E45)*1000) -> #REF! | F46: =SUM($C$42:F44)/(SUM($C$45:F45)*1000) -> #REF! | G46: =SUM($C$42:G44)/(SUM($C$45:G45)*1000) -> #REF! | H46: =SUM($C$42:H44)/(SUM($C$45:H45)*1000) -> #REF! | I46: =SUM($C$42:I44)/(SUM($C$45:I45)*1000) -> #REF! | J46: =SUM($C$42:J44)/(SUM($C$45:J45)*1000) -> #REF! | ... N46: =SUM($C$42:N44)/(SUM($C$45:N45)*1000) -> #REF!
A48: Surjek BUDGET
A49: Desalinated Water Production Per Litre ($/ML) | C49: 2013/Jul | D49: 2013/Aug | E49: 2013/Sep | F49: 2013/Oct | G49: 2013/Nov | H49: 2013/Dec | I49: 2014/Jan | J49: 2014/Feb | K49: 2014/Mar | L49: 2014/Apr | M49: 2014/May | N49: 2014/Jun
A50: Overheads [ ALL ] | B50: $ | C50: =SUMIFS('Variance Analysis'!C$9:C$24,'Variance Analysis'!$B$9:$B$24,'Variance Analysis'!$B$12,'Variance Analysis'!$A$9:$A$24,'Variance Analysis'!$A$13) -> #REF! | D50: =SUMIFS('Variance Analysis'!D$9:D$24,'Variance Analysis'!$B$9:$B$24,'Variance Analysis'!$B$12,'Variance Analysis'!$A$9:$A$24,'Variance Analysis'!$A$13) -> #REF! | E50: =SUMIFS('Variance Analysis'!E$9:E$24,'Variance Analysis'!$B$9:$B$24,'Variance Analysis'!$B$12,'Variance Analysis'!$A$9:$A$24,'Variance Analysis'!$A$13) -> #REF! | F50: =SUMIFS('Variance Analysis'!F$9:F$24,'Variance Analysis'!$B$9:$B$24,'Variance Analysis'!$B$12,'Variance Analysis'!$A$9:$A$24,'Variance Analysis'!$A$13) -> #REF! | G50: =SUMIFS('Variance Analysis'!G$9:G$24,'Variance Analysis'!$B$9:$B$24,'Variance Analysis'!$B$12,'Variance Analysis'!$A$9:$A$24,'Variance Analysis'!$A$13) -> #REF! | H50: =SUMIFS('Variance Analysis'!H$9:H$24,'Variance Analysis'!$B$9:$B$24,'Variance Analysis'!$B$12,'Variance Analysis'!$A$9:$A$24,'Variance Analysis'!$A$13) -> #REF! | I50: =SUMIFS('Variance Analysis'!I$9:I$24,'Variance Analysis'!$B$9:$B$24,'Variance Analysis'!$B$12,'Variance Analysis'!$A$9:$A$24,'Variance Analysis'!$A$13) -> #REF! | J50: =SUMIFS('Variance Analysis'!J$9:J$24,'Variance Analysis'!$B$9:$B$24,'Variance Analysis'!$B$12,'Variance Analysis'!$A$9:$A$24,'Variance Analysis'!$A$13) -> #REF! | ... N50: =SUMIFS('Variance Analysis'!N$9:N$24,'Variance Analysis'!$B$9:$B$24,'Variance Analysis'!$B$12,'Variance Analysis'!$A$9:$A$24,'Variance Analysis'!$A$13) -> #REF!
A51: Production Costs [ALL] | B51: $ | C51: =SUMIFS('Variance Analysis'!C$9:C$24,'Variance Analysis'!$B$9:$B$24,'Variance Analysis'!$B$10,'Variance Analysis'!$A$9:$A$24,'Variance Analysis'!$A$13) -> #REF! | D51: =SUMIFS('Variance Analysis'!D$9:D$24,'Variance Analysis'!$B$9:$B$24,'Variance Analysis'!$B$10,'Variance Analysis'!$A$9:$A$24,'Variance Analysis'!$A$13) -> #REF! | E51: =SUMIFS('Variance Analysis'!E$9:E$24,'Variance Analysis'!$B$9:$B$24,'Variance Analysis'!$B$10,'Variance Analysis'!$A$9:$A$24,'Variance Analysis'!$A$13) -> #REF! | F51: =SUMIFS('Variance Analysis'!F$9:F$24,'Variance Analysis'!$B$9:$B$24,'Variance Analysis'!$B$10,'Variance Analysis'!$A$9:$A$24,'Variance Analysis'!$A$13) -> #REF! | G51: =SUMIFS('Variance Analysis'!G$9:G$24,'Variance Analysis'!$B$9:$B$24,'Variance Analysis'!$B$10,'Variance Analysis'!$A$9:$A$24,'Variance Analysis'!$A$13) -> #REF! | H51: =SUMIFS('Variance Analysis'!H$9:H$24,'Variance Analysis'!$B$9:$B$24,'Variance Analysis'!$B$10,'Variance Analysis'!$A$9:$A$24,'Variance Analysis'!$A$13) -> #REF! | I51: =SUMIFS('Variance Analysis'!I$9:I$24,'Variance Analysis'!$B$9:$B$24,'Variance Analysis'!$B$10,'Variance Analysis'!$A$9:$A$24,'Variance Analysis'!$A$13) -> #REF! | J51: =SUMIFS('Variance Analysis'!J$9:J$24,'Variance Analysis'!$B$9:$B$24,'Variance Analysis'!$B$10,'Variance Analysis'!$A$9:$A$24,'Variance Analysis'!$A$13) -> #REF! | ... N51: =SUMIFS('Variance Analysis'!N$9:N$24,'Variance Analysis'!$B$9:$B$24,'Variance Analysis'!$B$10,'Variance Analysis'!$A$9:$A$24,'Variance Analysis'!$A$13) -> #REF!
A52: Other Production Costs [ALL] | B52: $ | C52: =SUMIFS('Variance Analysis'!C$9:C$24,'Variance Analysis'!$B$9:$B$24,'Variance Analysis'!$B$11,'Variance Analysis'!$A$9:$A$24,'Variance Analysis'!$A$13) -> #REF! | D52: =SUMIFS('Variance Analysis'!D$9:D$24,'Variance Analysis'!$B$9:$B$24,'Variance Analysis'!$B$11,'Variance Analysis'!$A$9:$A$24,'Variance Analysis'!$A$13) -> #REF! | E52: =SUMIFS('Variance Analysis'!E$9:E$24,'Variance Analysis'!$B$9:$B$24,'Variance Analysis'!$B$11,'Variance Analysis'!$A$9:$A$24,'Variance Analysis'!$A$13) -> #REF! | F52: =SUMIFS('Variance Analysis'!F$9:F$24,'Variance Analysis'!$B$9:$B$24,'Variance Analysis'!$B$11,'Variance Analysis'!$A$9:$A$24,'Variance Analysis'!$A$13) -> #REF! | G52: =SUMIFS('Variance Analysis'!G$9:G$24,'Variance Analysis'!$B$9:$B$24,'Variance Analysis'!$B$11,'Variance Analysis'!$A$9:$A$24,'Variance Analysis'!$A$13) -> #REF! | H52: =SUMIFS('Variance Analysis'!H$9:H$24,'Variance Analysis'!$B$9:$B$24,'Variance Analysis'!$B$11,'Variance Analysis'!$A$9:$A$24,'Variance Analysis'!$A$13) -> #REF! | I52: =SUMIFS('Variance Analysis'!I$9:I$24,'Variance Analysis'!$B$9:$B$24,'Variance Analysis'!$B$11,'Variance Analysis'!$A$9:$A$24,'Variance Analysis'!$A$13) -> #REF! | J52: =SUMIFS('Variance Analysis'!J$9:J$24,'Variance Analysis'!$B$9:$B$24,'Variance Analysis'!$B$11,'Variance Analysis'!$A$9:$A$24,'Variance Analysis'!$A$13) -> #REF! | ... N52: =SUMIFS('Variance Analysis'!N$9:N$24,'Variance Analysis'!$B$9:$B$24,'Variance Analysis'!$B$11,'Variance Analysis'!$A$9:$A$24,'Variance Analysis'!$A$13) -> #REF!
A53: Surjek (4 Major Desal. Plants) | B53: Mega-Litres (Needs to be converted from Giga-Litres) | C53: =#REF! -> #REF! | D53: =#REF! -> #REF! | E53: =#REF! -> #REF! | F53: =#REF! -> #REF! | G53: =#REF! -> #REF! | H53: =#REF! -> #REF! | I53: =#REF! -> #REF! | J53: =#REF! -> #REF! | ... N53: =#REF! -> #REF!
A54: Budget Cost to Produce (Rolling) | B54: $/Mega-Litres | C54: =SUM($C$50:C52)/(SUM($C$53:C53)*1000) -> #REF! | D54: =SUM($C$50:D52)/(SUM($C$53:D53)*1000) -> #REF! | E54: =SUM($C$50:E52)/(SUM($C$53:E53)*1000) -> #REF! | F54: =SUM($C$50:F52)/(SUM($C$53:F53)*1000) -> #REF! | G54: =SUM($C$50:G52)/(SUM($C$53:G53)*1000) -> #REF! | H54: =SUM($C$50:H52)/(SUM($C$53:H53)*1000) -> #REF! | I54: =SUM($C$50:I52)/(SUM($C$53:I53)*1000) -> #REF! | J54: =SUM($C$50:J52)/(SUM($C$53:J53)*1000) -> #REF! | ... N54: =SUM($C$50:N52)/(SUM($C$53:N53)*1000) -> #REF!
A56: Jutik BUDGET
A57: Desalinated Water Production Per Litre ($/ML) | C57: 2013/Jul | D57: 2013/Aug | E57: 2013/Sep | F57: 2013/Oct | G57: 2013/Nov | H57: 2013/Dec | I57: 2014/Jan | J57: 2014/Feb | K57: 2014/Mar | L57: 2014/Apr | M57: 2014/May | N57: 2014/Jun
A58: Overheads [ ALL ] | B58: $ | C58: =SUMIFS('Variance Analysis'!C$9:C$24,'Variance Analysis'!$B$9:$B$24,'Variance Analysis'!$B$12,'Variance Analysis'!$A$9:$A$24,'Variance Analysis'!$A$17) -> #REF! | D58: =SUMIFS('Variance Analysis'!D$9:D$24,'Variance Analysis'!$B$9:$B$24,'Variance Analysis'!$B$12,'Variance Analysis'!$A$9:$A$24,'Variance Analysis'!$A$17) -> #REF! | E58: =SUMIFS('Variance Analysis'!E$9:E$24,'Variance Analysis'!$B$9:$B$24,'Variance Analysis'!$B$12,'Variance Analysis'!$A$9:$A$24,'Variance Analysis'!$A$17) -> #REF! | F58: =SUMIFS('Variance Analysis'!F$9:F$24,'Variance Analysis'!$B$9:$B$24,'Variance Analysis'!$B$12,'Variance Analysis'!$A$9:$A$24,'Variance Analysis'!$A$17) -> #REF! | G58: =SUMIFS('Variance Analysis'!G$9:G$24,'Variance Analysis'!$B$9:$B$24,'Variance Analysis'!$B$12,'Variance Analysis'!$A$9:$A$24,'Variance Analysis'!$A$17) -> #REF! | H58: =SUMIFS('Variance Analysis'!H$9:H$24,'Variance Analysis'!$B$9:$B$24,'Variance Analysis'!$B$12,'Variance Analysis'!$A$9:$A$24,'Variance Analysis'!$A$17) -> #REF! | I58: =SUMIFS('Variance Analysis'!I$9:I$24,'Variance Analysis'!$B$9:$B$24,'Variance Analysis'!$B$12,'Variance Analysis'!$A$9:$A$24,'Variance Analysis'!$A$17) -> #REF! | J58: =SUMIFS('Variance Analysis'!J$9:J$24,'Variance Analysis'!$B$9:$B$24,'Variance Analysis'!$B$12,'Variance Analysis'!$A$9:$A$24,'Variance Analysis'!$A$17) -> #REF! | ... N58: =SUMIFS('Variance Analysis'!N$9:N$24,'Variance Analysis'!$B$9:$B$24,'Variance Analysis'!$B$12,'Variance Analysis'!$A$9:$A$24,'Variance Analysis'!$A$17) -> #REF!
A59: Production Costs [ALL] | B59: $ | C59: =SUMIFS('Variance Analysis'!C$9:C$24,'Variance Analysis'!$B$9:$B$24,'Variance Analysis'!$B$10,'Variance Analysis'!$A$9:$A$24,'Variance Analysis'!$A$17) -> #REF! | D59: =SUMIFS('Variance Analysis'!D$9:D$24,'Variance Analysis'!$B$9:$B$24,'Variance Analysis'!$B$10,'Variance Analysis'!$A$9:$A$24,'Variance Analysis'!$A$17) -> #REF! | E59: =SUMIFS('Variance Analysis'!E$9:E$24,'Variance Analysis'!$B$9:$B$24,'Variance Analysis'!$B$10,'Variance Analysis'!$A$9:$A$24,'Variance Analysis'!$A$17) -> #REF! | F59: =SUMIFS('Variance Analysis'!F$9:F$24,'Variance Analysis'!$B$9:$B$24,'Variance Analysis'!$B$10,'Variance Analysis'!$A$9:$A$24,'Variance Analysis'!$A$17) -> #REF! | G59: =SUMIFS('Variance Analysis'!G$9:G$24,'Variance Analysis'!$B$9:$B$24,'Variance Analysis'!$B$10,'Variance Analysis'!$A$9:$A$24,'Variance Analysis'!$A$17) -> #REF! | H59: =SUMIFS('Variance Analysis'!H$9:H$24,'Variance Analysis'!$B$9:$B$24,'Variance Analysis'!$B$10,'Variance Analysis'!$A$9:$A$24,'Variance Analysis'!$A$17) -> #REF! | I59: =SUMIFS('Variance Analysis'!I$9:I$24,'Variance Analysis'!$B$9:$B$24,'Variance Analysis'!$B$10,'Variance Analysis'!$A$9:$A$24,'Variance Analysis'!$A$17) -> #REF! | J59: =SUMIFS('Variance Analysis'!J$9:J$24,'Variance Analysis'!$B$9:$B$24,'Variance Analysis'!$B$10,'Variance Analysis'!$A$9:$A$24,'Variance Analysis'!$A$17) -> #REF! | ... N59: =SUMIFS('Variance Analysis'!N$9:N$24,'Variance Analysis'!$B$9:$B$24,'Variance Analysis'!$B$10,'Variance Analysis'!$A$9:$A$24,'Variance Analysis'!$A$17) -> #REF!
A60: Other Production Costs [ALL] | B60: $ | C60: =SUMIFS('Variance Analysis'!C$9:C$24,'Variance Analysis'!$B$9:$B$24,'Variance Analysis'!$B$11,'Variance Analysis'!$A$9:$A$24,'Variance Analysis'!$A$17) -> #REF! | D60: =SUMIFS('Variance Analysis'!D$9:D$24,'Variance Analysis'!$B$9:$B$24,'Variance Analysis'!$B$11,'Variance Analysis'!$A$9:$A$24,'Variance Analysis'!$A$17) -> #REF! | E60: =SUMIFS('Variance Analysis'!E$9:E$24,'Variance Analysis'!$B$9:$B$24,'Variance Analysis'!$B$11,'Variance Analysis'!$A$9:$A$24,'Variance Analysis'!$A$17) -> #REF! | F60: =SUMIFS('Variance Analysis'!F$9:F$24,'Variance Analysis'!$B$9:$B$24,'Variance Analysis'!$B$11,'Variance Analysis'!$A$9:$A$24,'Variance Analysis'!$A$17) -> #REF! | G60: =SUMIFS('Variance Analysis'!G$9:G$24,'Variance Analysis'!$B$9:$B$24,'Variance Analysis'!$B$11,'Variance Analysis'!$A$9:$A$24,'Variance Analysis'!$A$17) -> #REF! | H60: =SUMIFS('Variance Analysis'!H$9:H$24,'Variance Analysis'!$B$9:$B$24,'Variance Analysis'!$B$11,'Variance Analysis'!$A$9:$A$24,'Variance Analysis'!$A$17) -> #REF! | I60: =SUMIFS('Variance Analysis'!I$9:I$24,'Variance Analysis'!$B$9:$B$24,'Variance Analysis'!$B$11,'Variance Analysis'!$A$9:$A$24,'Variance Analysis'!$A$17) -> #REF! | J60: =SUMIFS('Variance Analysis'!J$9:J$24,'Variance Analysis'!$B$9:$B$24,'Variance Analysis'!$B$11,'Variance Analysis'!$A$9:$A$24,'Variance Analysis'!$A$17) -> #REF! | ... N60: =SUMIFS('Variance Analysis'!N$9:N$24,'Variance Analysis'!$B$9:$B$24,'Variance Analysis'!$B$11,'Variance Analysis'!$A$9:$A$24,'Variance Analysis'!$A$17) -> #REF!
A61: Jutik Desalination Plant [Newest Desalination Plant] | B61: Mega-Litres (Needs to be converted from Giga-Litres) | C61: =#REF! -> #REF! | D61: =#REF! -> #REF! | E61: =#REF! -> #REF! | F61: =#REF! -> #REF! | G61: =#REF! -> #REF! | H61: =#REF! -> #REF! | I61: =#REF! -> #REF! | J61: =#REF! -> #REF! | ... N61: =#REF! -> #REF!
A62: Budget Cost to Produce (Rolling) | B62: $/Mega-Litres | C62: =SUM($C$58:C60)/(SUM($C$61:C61)*1000) -> #REF! | D62: =SUM($C$58:D60)/(SUM($C$61:D61)*1000) -> #REF! | E62: =SUM($C$58:E60)/(SUM($C$61:E61)*1000) -> #REF! | F62: =SUM($C$58:F60)/(SUM($C$61:F61)*1000) -> #REF! | G62: =SUM($C$58:G60)/(SUM($C$61:G61)*1000) -> #REF! | H62: =SUM($C$58:H60)/(SUM($C$61:H61)*1000) -> #REF! | I62: =SUM($C$58:I60)/(SUM($C$61:I61)*1000) -> #REF! | J62: =SUM($C$58:J60)/(SUM($C$61:J61)*1000) -> #REF! | ... N62: =SUM($C$58:N60)/(SUM($C$61:N61)*1000) -> #REF!
A64: Overall BUDGET
A65: Desalinated Water Production Per Litre ($/ML) | C65: 2013/Jul | D65: 2013/Aug | E65: 2013/Sep | F65: 2013/Oct | G65: 2013/Nov | H65: 2013/Dec | I65: 2014/Jan | J65: 2014/Feb | K65: 2014/Mar | L65: 2014/Apr | M65: 2014/May | N65: 2014/Jun
A66: Overheads [ ALL ] | B66: $ | C66: =SUMIFS('Variance Analysis'!C$9:C$24,'Variance Analysis'!$B$9:$B$24,'Variance Analysis'!$B$12,'Variance Analysis'!$A$9:$A$24,'Variance Analysis'!$A$21) -> #REF! | D66: =SUMIFS('Variance Analysis'!D$9:D$24,'Variance Analysis'!$B$9:$B$24,'Variance Analysis'!$B$12,'Variance Analysis'!$A$9:$A$24,'Variance Analysis'!$A$21) -> #REF! | E66: =SUMIFS('Variance Analysis'!E$9:E$24,'Variance Analysis'!$B$9:$B$24,'Variance Analysis'!$B$12,'Variance Analysis'!$A$9:$A$24,'Variance Analysis'!$A$21) -> #REF! | F66: =SUMIFS('Variance Analysis'!F$9:F$24,'Variance Analysis'!$B$9:$B$24,'Variance Analysis'!$B$12,'Variance Analysis'!$A$9:$A$24,'Variance Analysis'!$A$21) -> #REF! | G66: =SUMIFS('Variance Analysis'!G$9:G$24,'Variance Analysis'!$B$9:$B$24,'Variance Analysis'!$B$12,'Variance Analysis'!$A$9:$A$24,'Variance Analysis'!$A$21) -> #REF! | H66: =SUMIFS('Variance Analysis'!H$9:H$24,'Variance Analysis'!$B$9:$B$24,'Variance Analysis'!$B$12,'Variance Analysis'!$A$9:$A$24,'Variance Analysis'!$A$21) -> #REF! | I66: =SUMIFS('Variance Analysis'!I$9:I$24,'Variance Analysis'!$B$9:$B$24,'Variance Analysis'!$B$12,'Variance Analysis'!$A$9:$A$24,'Variance Analysis'!$A$21) -> #REF! | J66: =SUMIFS('Variance Analysis'!J$9:J$24,'Variance Analysis'!$B$9:$B$24,'Variance Analysis'!$B$12,'Variance Analysis'!$A$9:$A$24,'Variance Analysis'!$A$21) -> #REF! | ... N66: =SUMIFS('Variance Analysis'!N$9:N$24,'Variance Analysis'!$B$9:$B$24,'Variance Analysis'!$B$12,'Variance Analysis'!$A$9:$A$24,'Variance Analysis'!$A$21) -> #REF!
A67: Production Costs [ALL] | B67: $ | C67: =SUMIFS('Variance Analysis'!C$9:C$24,'Variance Analysis'!$B$9:$B$24,'Variance Analysis'!$B$10,'Variance Analysis'!$A$9:$A$24,'Variance Analysis'!$A$21) -> #REF! | D67: =SUMIFS('Variance Analysis'!D$9:D$24,'Variance Analysis'!$B$9:$B$24,'Variance Analysis'!$B$10,'Variance Analysis'!$A$9:$A$24,'Variance Analysis'!$A$21) -> #REF! | E67: =SUMIFS('Variance Analysis'!E$9:E$24,'Variance Analysis'!$B$9:$B$24,'Variance Analysis'!$B$10,'Variance Analysis'!$A$9:$A$24,'Variance Analysis'!$A$21) -> #REF! | F67: =SUMIFS('Variance Analysis'!F$9:F$24,'Variance Analysis'!$B$9:$B$24,'Variance Analysis'!$B$10,'Variance Analysis'!$A$9:$A$24,'Variance Analysis'!$A$21) -> #REF! | G67: =SUMIFS('Variance Analysis'!G$9:G$24,'Variance Analysis'!$B$9:$B$24,'Variance Analysis'!$B$10,'Variance Analysis'!$A$9:$A$24,'Variance Analysis'!$A$21) -> #REF! | H67: =SUMIFS('Variance Analysis'!H$9:H$24,'Variance Analysis'!$B$9:$B$24,'Variance Analysis'!$B$10,'Variance Analysis'!$A$9:$A$24,'Variance Analysis'!$A$21) -> #REF! | I67: =SUMIFS('Variance Analysis'!I$9:I$24,'Variance Analysis'!$B$9:$B$24,'Variance Analysis'!$B$10,'Variance Analysis'!$A$9:$A$24,'Variance Analysis'!$A$21) -> #REF! | J67: =SUMIFS('Variance Analysis'!J$9:J$24,'Variance Analysis'!$B$9:$B$24,'Variance Analysis'!$B$10,'Variance Analysis'!$A$9:$A$24,'Variance Analysis'!$A$21) -> #REF! | ... N67: =SUMIFS('Variance Analysis'!N$9:N$24,'Variance Analysis'!$B$9:$B$24,'Variance Analysis'!$B$10,'Variance Analysis'!$A$9:$A$24,'Variance Analysis'!$A$21) -> #REF!
A68: Other Production Costs [ALL] | B68: $ | C68: =SUMIFS('Variance Analysis'!C$9:C$24,'Variance Analysis'!$B$9:$B$24,'Variance Analysis'!$B$11,'Variance Analysis'!$A$9:$A$24,'Variance Analysis'!$A$21) -> #REF! | D68: =SUMIFS('Variance Analysis'!D$9:D$24,'Variance Analysis'!$B$9:$B$24,'Variance Analysis'!$B$11,'Variance Analysis'!$A$9:$A$24,'Variance Analysis'!$A$21) -> #REF! | E68: =SUMIFS('Variance Analysis'!E$9:E$24,'Variance Analysis'!$B$9:$B$24,'Variance Analysis'!$B$11,'Variance Analysis'!$A$9:$A$24,'Variance Analysis'!$A$21) -> #REF! | F68: =SUMIFS('Variance Analysis'!F$9:F$24,'Variance Analysis'!$B$9:$B$24,'Variance Analysis'!$B$11,'Variance Analysis'!$A$9:$A$24,'Variance Analysis'!$A$21) -> #REF! | G68: =SUMIFS('Variance Analysis'!G$9:G$24,'Variance Analysis'!$B$9:$B$24,'Variance Analysis'!$B$11,'Variance Analysis'!$A$9:$A$24,'Variance Analysis'!$A$21) -> #REF! | H68: =SUMIFS('Variance Analysis'!H$9:H$24,'Variance Analysis'!$B$9:$B$24,'Variance Analysis'!$B$11,'Variance Analysis'!$A$9:$A$24,'Variance Analysis'!$A$21) -> #REF! | I68: =SUMIFS('Variance Analysis'!I$9:I$24,'Variance Analysis'!$B$9:$B$24,'Variance Analysis'!$B$11,'Variance Analysis'!$A$9:$A$24,'Variance Analysis'!$A$21) -> #REF! | J68: =SUMIFS('Variance Analysis'!J$9:J$24,'Variance Analysis'!$B$9:$B$24,'Variance Analysis'!$B$11,'Variance Analysis'!$A$9:$A$24,'Variance Analysis'!$A$21) -> #REF! | ... N68: =SUMIFS('Variance Analysis'!N$9:N$24,'Variance Analysis'!$B$9:$B$24,'Variance Analysis'!$B$11,'Variance Analysis'!$A$9:$A$24,'Variance Analysis'!$A$21) -> #REF!
A69: Kootha (1 Major Desal Unit) | B69: Mega-Litres (Needs to be converted from Giga-Litres) | C69: =#REF! -> #REF! | D69: =#REF! -> #REF! | E69: =#REF! -> #REF! | F69: =#REF! -> #REF! | G69: =#REF! -> #REF! | H69: =#REF! -> #REF! | I69: =#REF! -> #REF! | J69: =#REF! -> #REF! | ... N69: =#REF! -> #REF!
A70: Surjek (4 Major Desal. Plants) | B70: Mega-Litres (Needs to be converted from Giga-Litres) | C70: =#REF! -> #REF! | D70: =#REF! -> #REF! | E70: =#REF! -> #REF! | F70: =#REF! -> #REF! | G70: =#REF! -> #REF! | H70: =#REF! -> #REF! | I70: =#REF! -> #REF! | J70: =#REF! -> #REF! | ... N70: =#REF! -> #REF!
A71: Jutik Desalination Plant [Newest Desalination Plant] | B71: Mega-Litres (Needs to be converted from Giga-Litres) | C71: =#REF! -> #REF! | D71: =#REF! -> #REF! | E71: =#REF! -> #REF! | F71: =#REF! -> #REF! | G71: =#REF! -> #REF! | H71: =#REF! -> #REF! | I71: =#REF! -> #REF! | J71: =#REF! -> #REF! | ... N71: =#REF! -> #REF!
A72: Budget Cost to Produce (Rolling) | B72: $/Mega-Litres | C72: =SUM($C$66:C68)/(SUM($C$69:C71)*1000) -> #REF! | D72: =SUM($C$66:D68)/(SUM($C$69:D71)*1000) -> #REF! | E72: =SUM($C$66:E68)/(SUM($C$69:E71)*1000) -> #REF! | F72: =SUM($C$66:F68)/(SUM($C$69:F71)*1000) -> #REF! | G72: =SUM($C$66:G68)/(SUM($C$69:G71)*1000) -> #REF! | H72: =SUM($C$66:H68)/(SUM($C$69:H71)*1000) -> #REF! | I72: =SUM($C$66:I68)/(SUM($C$69:I71)*1000) -> #REF! | J72: =SUM($C$66:J68)/(SUM($C$69:J71)*1000) -> #REF! | ... N72: =SUM($C$66:N68)/(SUM($C$69:N71)*1000) -> #REF!
A74: Q2. Create Line Charts Plotting out the Cost to Produce for each individual Unit (Kootha, Surjek, Jutik and Overall) and copy these graphs into a PowerPoint Slide Pack. What do the Cost to Produce Trends tell you?

Sheet EBIT
A1: So why do we care about EBIT? EBIT stands for Earnings Before Interest and Tax. In this case, Southern Water Corp's Management wants to be aware of the financial status of the company once the Production Costs and Other Production Costs have been removed. Wall Street commonly uses EBIT as a measure of financial health to see if a company is doing well or doign poorly. If the EBIT is positive, it's a good sign. If the EBIT Is negative, it indicates the costs are greater than the revenues and the company is likely heading for bankruptcy. Now that we know why EBIT is important - let's calculate this and see what the results look like for Southern Water Corp's Management Team!
A2: Hint: Don't forget to calculate EBIT you need to subtract the costs (Overheads, Production Costs and Other Production Costs). Note that we show that Revenues are currently being 'Debited' with a -ve. Don't forget to convert the Revenues to a +ve figure!
A4: Q1. Calculate Actual EBIT for Kootha, Surjek, Juitk and Overall (Kootha + Surjek + Jutik). Don't forget to populate the Overheads, Production Costs and Other Production Costs using the SUMIFS Formula, referencing the Variance Analysis Tab.
A5: Kootha
A6: EBIT ACTUALS | B6: Units | C6: 2013/Jul | D6: 2013/Aug | E6: 2013/Sep | F6: 2013/Oct | G6: 2013/Nov | H6: 2013/Dec | I6: 2014/Jan | J6: 2014/Feb | K6: 2014/Mar | L6: 2014/Apr | M6: 2014/May | N6: 2014/Jun
A7: Overheads | B7: $ | C7: =SUMIFS('Variance Analysis'!C$30:C$45,'Variance Analysis'!$B$30:$B$45,'Variance Analysis'!$B$33,'Variance Analysis'!$A$30:$A$45,'Variance Analysis'!$A$33) -> #REF! | D7: =SUMIFS('Variance Analysis'!D$30:D$45,'Variance Analysis'!$B$30:$B$45,'Variance Analysis'!$B$33,'Variance Analysis'!$A$30:$A$45,'Variance Analysis'!$A$33) -> #REF! | E7: =SUMIFS('Variance Analysis'!E$30:E$45,'Variance Analysis'!$B$30:$B$45,'Variance Analysis'!$B$33,'Variance Analysis'!$A$30:$A$45,'Variance Analysis'!$A$33) -> #REF! | F7: =SUMIFS('Variance Analysis'!F$30:F$45,'Variance Analysis'!$B$30:$B$45,'Variance Analysis'!$B$33,'Variance Analysis'!$A$30:$A$45,'Variance Analysis'!$A$33) -> #REF! | G7: =SUMIFS('Variance Analysis'!G$30:G$45,'Variance Analysis'!$B$30:$B$45,'Variance Analysis'!$B$33,'Variance Analysis'!$A$30:$A$45,'Variance Analysis'!$A$33) -> #REF! | H7: =SUMIFS('Variance Analysis'!H$30:H$45,'Variance Analysis'!$B$30:$B$45,'Variance Analysis'!$B$33,'Variance Analysis'!$A$30:$A$45,'Variance Analysis'!$A$33) -> #REF! | I7: =SUMIFS('Variance Analysis'!I$30:I$45,'Variance Analysis'!$B$30:$B$45,'Variance Analysis'!$B$33,'Variance Analysis'!$A$30:$A$45,'Variance Analysis'!$A$33) -> #REF! | J7: =SUMIFS('Variance Analysis'!J$30:J$45,'Variance Analysis'!$B$30:$B$45,'Variance Analysis'!$B$33,'Variance Analysis'!$A$30:$A$45,'Variance Analysis'!$A$33) -> #REF! | ... N7: =SUMIFS('Variance Analysis'!N$30:N$45,'Variance Analysis'!$B$30:$B$45,'Variance Analysis'!$B$33,'Variance Analysis'!$A$30:$A$45,'Variance Analysis'!$A$33) -> #REF!
A8: Production Costs | B8: $ | C8: =SUMIFS('Variance Analysis'!C$30:C$45,'Variance Analysis'!$B$30:$B$45,'Variance Analysis'!$B$31,'Variance Analysis'!$A$30:$A$45,'Variance Analysis'!$A$33) -> #REF! | D8: =SUMIFS('Variance Analysis'!D$30:D$45,'Variance Analysis'!$B$30:$B$45,'Variance Analysis'!$B$31,'Variance Analysis'!$A$30:$A$45,'Variance Analysis'!$A$33) -> #REF! | E8: =SUMIFS('Variance Analysis'!E$30:E$45,'Variance Analysis'!$B$30:$B$45,'Variance Analysis'!$B$31,'Variance Analysis'!$A$30:$A$45,'Variance Analysis'!$A$33) -> #REF! | F8: =SUMIFS('Variance Analysis'!F$30:F$45,'Variance Analysis'!$B$30:$B$45,'Variance Analysis'!$B$31,'Variance Analysis'!$A$30:$A$45,'Variance Analysis'!$A$33) -> #REF! | G8: =SUMIFS('Variance Analysis'!G$30:G$45,'Variance Analysis'!$B$30:$B$45,'Variance Analysis'!$B$31,'Variance Analysis'!$A$30:$A$45,'Variance Analysis'!$A$33) -> #REF! | H8: =SUMIFS('Variance Analysis'!H$30:H$45,'Variance Analysis'!$B$30:$B$45,'Variance Analysis'!$B$31,'Variance Analysis'!$A$30:$A$45,'Variance Analysis'!$A$33) -> #REF! | I8: =SUMIFS('Variance Analysis'!I$30:I$45,'Variance Analysis'!$B$30:$B$45,'Variance Analysis'!$B$31,'Variance Analysis'!$A$30:$A$45,'Variance Analysis'!$A$33) -> #REF! | J8: =SUMIFS('Variance Analysis'!J$30:J$45,'Variance Analysis'!$B$30:$B$45,'Variance Analysis'!$B$31,'Variance Analysis'!$A$30:$A$45,'Variance Analysis'!$A$33) -> #REF! | ... N8: =SUMIFS('Variance Analysis'!N$30:N$45,'Variance Analysis'!$B$30:$B$45,'Variance Analysis'!$B$31,'Variance Analysis'!$A$30:$A$45,'Variance Analysis'!$A$33) -> #REF!
A9: Other Production Costs | B9: $ | C9: =SUMIFS('Variance Analysis'!C$30:C$45,'Variance Analysis'!$B$30:$B$45,'Variance Analysis'!$B$32,'Variance Analysis'!$A$30:$A$45,'Variance Analysis'!$A$33) -> #REF! | D9: =SUMIFS('Variance Analysis'!D$30:D$45,'Variance Analysis'!$B$30:$B$45,'Variance Analysis'!$B$32,'Variance Analysis'!$A$30:$A$45,'Variance Analysis'!$A$33) -> #REF! | E9: =SUMIFS('Variance Analysis'!E$30:E$45,'Variance Analysis'!$B$30:$B$45,'Variance Analysis'!$B$32,'Variance Analysis'!$A$30:$A$45,'Variance Analysis'!$A$33) -> #REF! | F9: =SUMIFS('Variance Analysis'!F$30:F$45,'Variance Analysis'!$B$30:$B$45,'Variance Analysis'!$B$32,'Variance Analysis'!$A$30:$A$45,'Variance Analysis'!$A$33) -> #REF! | G9: =SUMIFS('Variance Analysis'!G$30:G$45,'Variance Analysis'!$B$30:$B$45,'Variance Analysis'!$B$32,'Variance Analysis'!$A$30:$A$45,'Variance Analysis'!$A$33) -> #REF! | H9: =SUMIFS('Variance Analysis'!H$30:H$45,'Variance Analysis'!$B$30:$B$45,'Variance Analysis'!$B$32,'Variance Analysis'!$A$30:$A$45,'Variance Analysis'!$A$33) -> #REF! | I9: =SUMIFS('Variance Analysis'!I$30:I$45,'Variance Analysis'!$B$30:$B$45,'Variance Analysis'!$B$32,'Variance Analysis'!$A$30:$A$45,'Variance Analysis'!$A$33) -> #REF! | J9: =SUMIFS('Variance Analysis'!J$30:J$45,'Variance Analysis'!$B$30:$B$45,'Variance Analysis'!$B$32,'Variance Analysis'!$A$30:$A$45,'Variance Analysis'!$A$33) -> #REF! | ... N9: =SUMIFS('Variance Analysis'!N$30:N$45,'Variance Analysis'!$B$30:$B$45,'Variance Analysis'!$B$32,'Variance Analysis'!$A$30:$A$45,'Variance Analysis'!$A$33) -> #REF!
A10: Revenue | B10: $ | C10: =SUMIFS('Variance Analysis'!C$30:C$45,'Variance Analysis'!$B$30:$B$45,'Variance Analysis'!$B$30,'Variance Analysis'!$A$30:$A$45,'Variance Analysis'!$A$33) -> #REF! | D10: =SUMIFS('Variance Analysis'!D$30:D$45,'Variance Analysis'!$B$30:$B$45,'Variance Analysis'!$B$30,'Variance Analysis'!$A$30:$A$45,'Variance Analysis'!$A$33) -> #REF! | E10: =SUMIFS('Variance Analysis'!E$30:E$45,'Variance Analysis'!$B$30:$B$45,'Variance Analysis'!$B$30,'Variance Analysis'!$A$30:$A$45,'Variance Analysis'!$A$33) -> #REF! | F10: =SUMIFS('Variance Analysis'!F$30:F$45,'Variance Analysis'!$B$30:$B$45,'Variance Analysis'!$B$30,'Variance Analysis'!$A$30:$A$45,'Variance Analysis'!$A$33) -> #REF! | G10: =SUMIFS('Variance Analysis'!G$30:G$45,'Variance Analysis'!$B$30:$B$45,'Variance Analysis'!$B$30,'Variance Analysis'!$A$30:$A$45,'Variance Analysis'!$A$33) -> #REF! | H10: =SUMIFS('Variance Analysis'!H$30:H$45,'Variance Analysis'!$B$30:$B$45,'Variance Analysis'!$B$30,'Variance Analysis'!$A$30:$A$45,'Variance Analysis'!$A$33) -> #REF! | I10: =SUMIFS('Variance Analysis'!I$30:I$45,'Variance Analysis'!$B$30:$B$45,'Variance Analysis'!$B$30,'Variance Analysis'!$A$30:$A$45,'Variance Analysis'!$A$33) -> #REF! | J10: =SUMIFS('Variance Analysis'!J$30:J$45,'Variance Analysis'!$B$30:$B$45,'Variance Analysis'!$B$30,'Variance Analysis'!$A$30:$A$45,'Variance Analysis'!$A$33) -> #REF! | ... N10: =SUMIFS('Variance Analysis'!N$30:N$45,'Variance Analysis'!$B$30:$B$45,'Variance Analysis'!$B$30,'Variance Analysis'!$A$30:$A$45,'Variance Analysis'!$A$33) -> #REF!
A11: EBIT | B11: $ | C11: =ABS(C10)-SUM(C7:C9) -> #REF! | D11: =ABS(D10)-SUM(D7:D9) -> #REF! | E11: =ABS(E10)-SUM(E7:E9) -> #REF! | F11: =ABS(F10)-SUM(F7:F9) -> #REF! | G11: =ABS(G10)-SUM(G7:G9) -> #REF! | H11: =ABS(H10)-SUM(H7:H9) -> #REF! | I11: =ABS(I10)-SUM(I7:I9) -> #REF! | J11: =ABS(J10)-SUM(J7:J9) -> #REF! | ... N11: =ABS(N10)-SUM(N7:N9) -> #REF!
A12: Surjek
A13: EBIT ACTUALS | B13: Units | C13: 2013/Jul | D13: 2013/Aug | E13: 2013/Sep | F13: 2013/Oct | G13: 2013/Nov | H13: 2013/Dec | I13: 2014/Jan | J13: 2014/Feb | K13: 2014/Mar | L13: 2014/Apr | M13: 2014/May | N13: 2014/Jun
A14: Overheads | B14: $ | C14: =SUMIFS('Variance Analysis'!C$30:C$45,'Variance Analysis'!$B$30:$B$45,'Variance Analysis'!$B$33,'Variance Analysis'!$A$30:$A$45,'Variance Analysis'!$A$34) -> #REF! | D14: =SUMIFS('Variance Analysis'!D$30:D$45,'Variance Analysis'!$B$30:$B$45,'Variance Analysis'!$B$33,'Variance Analysis'!$A$30:$A$45,'Variance Analysis'!$A$34) -> #REF! | E14: =SUMIFS('Variance Analysis'!E$30:E$45,'Variance Analysis'!$B$30:$B$45,'Variance Analysis'!$B$33,'Variance Analysis'!$A$30:$A$45,'Variance Analysis'!$A$34) -> #REF! | F14: =SUMIFS('Variance Analysis'!F$30:F$45,'Variance Analysis'!$B$30:$B$45,'Variance Analysis'!$B$33,'Variance Analysis'!$A$30:$A$45,'Variance Analysis'!$A$34) -> #REF! | G14: =SUMIFS('Variance Analysis'!G$30:G$45,'Variance Analysis'!$B$30:$B$45,'Variance Analysis'!$B$33,'Variance Analysis'!$A$30:$A$45,'Variance Analysis'!$A$34) -> #REF! | H14: =SUMIFS('Variance Analysis'!H$30:H$45,'Variance Analysis'!$B$30:$B$45,'Variance Analysis'!$B$33,'Variance Analysis'!$A$30:$A$45,'Variance Analysis'!$A$34) -> #REF! | I14: =SUMIFS('Variance Analysis'!I$30:I$45,'Variance Analysis'!$B$30:$B$45,'Variance Analysis'!$B$33,'Variance Analysis'!$A$30:$A$45,'Variance Analysis'!$A$34) -> #REF! | J14: =SUMIFS('Variance Analysis'!J$30:J$45,'Variance Analysis'!$B$30:$B$45,'Variance Analysis'!$B$33,'Variance Analysis'!$A$30:$A$45,'Variance Analysis'!$A$34) -> #REF! | ... N14: =SUMIFS('Variance Analysis'!N$30:N$45,'Variance Analysis'!$B$30:$B$45,'Variance Analysis'!$B$33,'Variance Analysis'!$A$30:$A$45,'Variance Analysis'!$A$34) -> #REF!
A15: Production Costs | B15: $ | C15: =SUMIFS('Variance Analysis'!C$30:C$45,'Variance Analysis'!$B$30:$B$45,'Variance Analysis'!$B$31,'Variance Analysis'!$A$30:$A$45,'Variance Analysis'!$A$34) -> #REF! | D15: =SUMIFS('Variance Analysis'!D$30:D$45,'Variance Analysis'!$B$30:$B$45,'Variance Analysis'!$B$31,'Variance Analysis'!$A$30:$A$45,'Variance Analysis'!$A$34) -> #REF! | E15: =SUMIFS('Variance Analysis'!E$30:E$45,'Variance Analysis'!$B$30:$B$45,'Variance Analysis'!$B$31,'Variance Analysis'!$A$30:$A$45,'Variance Analysis'!$A$34) -> #REF! | F15: =SUMIFS('Variance Analysis'!F$30:F$45,'Variance Analysis'!$B$30:$B$45,'Variance Analysis'!$B$31,'Variance Analysis'!$A$30:$A$45,'Variance Analysis'!$A$34) -> #REF! | G15: =SUMIFS('Variance Analysis'!G$30:G$45,'Variance Analysis'!$B$30:$B$45,'Variance Analysis'!$B$31,'Variance Analysis'!$A$30:$A$45,'Variance Analysis'!$A$34) -> #REF! | H15: =SUMIFS('Variance Analysis'!H$30:H$45,'Variance Analysis'!$B$30:$B$45,'Variance Analysis'!$B$31,'Variance Analysis'!$A$30:$A$45,'Variance Analysis'!$A$34) -> #REF! | I15: =SUMIFS('Variance Analysis'!I$30:I$45,'Variance Analysis'!$B$30:$B$45,'Variance Analysis'!$B$31,'Variance Analysis'!$A$30:$A$45,'Variance Analysis'!$A$34) -> #REF! | J15: =SUMIFS('Variance Analysis'!J$30:J$45,'Variance Analysis'!$B$30:$B$45,'Variance Analysis'!$B$31,'Variance Analysis'!$A$30:$A$45,'Variance Analysis'!$A$34) -> #REF! | ... N15: =SUMIFS('Variance Analysis'!N$30:N$45,'Variance Analysis'!$B$30:$B$45,'Variance Analysis'!$B$31,'Variance Analysis'!$A$30:$A$45,'Variance Analysis'!$A$34) -> #REF!
A16: Other Production Costs | B16: $ | C16: =SUMIFS('Variance Analysis'!C$30:C$45,'Variance Analysis'!$B$30:$B$45,'Variance Analysis'!$B$32,'Variance Analysis'!$A$30:$A$45,'Variance Analysis'!$A$34) -> #REF! | D16: =SUMIFS('Variance Analysis'!D$30:D$45,'Variance Analysis'!$B$30:$B$45,'Variance Analysis'!$B$32,'Variance Analysis'!$A$30:$A$45,'Variance Analysis'!$A$34) -> #REF! | E16: =SUMIFS('Variance Analysis'!E$30:E$45,'Variance Analysis'!$B$30:$B$45,'Variance Analysis'!$B$32,'Variance Analysis'!$A$30:$A$45,'Variance Analysis'!$A$34) -> #REF! | F16: =SUMIFS('Variance Analysis'!F$30:F$45,'Variance Analysis'!$B$30:$B$45,'Variance Analysis'!$B$32,'Variance Analysis'!$A$30:$A$45,'Variance Analysis'!$A$34) -> #REF! | G16: =SUMIFS('Variance Analysis'!G$30:G$45,'Variance Analysis'!$B$30:$B$45,'Variance Analysis'!$B$32,'Variance Analysis'!$A$30:$A$45,'Variance Analysis'!$A$34) -> #REF! | H16: =SUMIFS('Variance Analysis'!H$30:H$45,'Variance Analysis'!$B$30:$B$45,'Variance Analysis'!$B$32,'Variance Analysis'!$A$30:$A$45,'Variance Analysis'!$A$34) -> #REF! | I16: =SUMIFS('Variance Analysis'!I$30:I$45,'Variance Analysis'!$B$30:$B$45,'Variance Analysis'!$B$32,'Variance Analysis'!$A$30:$A$45,'Variance Analysis'!$A$34) -> #REF! | J16: =SUMIFS('Variance Analysis'!J$30:J$45,'Variance Analysis'!$B$30:$B$45,'Variance Analysis'!$B$32,'Variance Analysis'!$A$30:$A$45,'Variance Analysis'!$A$34) -> #REF! | ... N16: =SUMIFS('Variance Analysis'!N$30:N$45,'Variance Analysis'!$B$30:$B$45,'Variance Analysis'!$B$32,'Variance Analysis'!$A$30:$A$45,'Variance Analysis'!$A$34) -> #REF!
A17: Revenue | B17: $ | C17: =SUMIFS('Variance Analysis'!C$30:C$45,'Variance Analysis'!$B$30:$B$45,'Variance Analysis'!$B$30,'Variance Analysis'!$A$30:$A$45,'Variance Analysis'!$A$34) -> #REF! | D17: =SUMIFS('Variance Analysis'!D$30:D$45,'Variance Analysis'!$B$30:$B$45,'Variance Analysis'!$B$30,'Variance Analysis'!$A$30:$A$45,'Variance Analysis'!$A$34) -> #REF! | E17: =SUMIFS('Variance Analysis'!E$30:E$45,'Variance Analysis'!$B$30:$B$45,'Variance Analysis'!$B$30,'Variance Analysis'!$A$30:$A$45,'Variance Analysis'!$A$34) -> #REF! | F17: =SUMIFS('Variance Analysis'!F$30:F$45,'Variance Analysis'!$B$30:$B$45,'Variance Analysis'!$B$30,'Variance Analysis'!$A$30:$A$45,'Variance Analysis'!$A$34) -> #REF! | G17: =SUMIFS('Variance Analysis'!G$30:G$45,'Variance Analysis'!$B$30:$B$45,'Variance Analysis'!$B$30,'Variance Analysis'!$A$30:$A$45,'Variance Analysis'!$A$34) -> #REF! | H17: =SUMIFS('Variance Analysis'!H$30:H$45,'Variance Analysis'!$B$30:$B$45,'Variance Analysis'!$B$30,'Variance Analysis'!$A$30:$A$45,'Variance Analysis'!$A$34) -> #REF! | I17: =SUMIFS('Variance Analysis'!I$30:I$45,'Variance Analysis'!$B$30:$B$45,'Variance Analysis'!$B$30,'Variance Analysis'!$A$30:$A$45,'Variance Analysis'!$A$34) -> #REF! | J17: =SUMIFS('Variance Analysis'!J$30:J$45,'Variance Analysis'!$B$30:$B$45,'Variance Analysis'!$B$30,'Variance Analysis'!$A$30:$A$45,'Variance Analysis'!$A$34) -> #REF! | ... N17: =SUMIFS('Variance Analysis'!N$30:N$45,'Variance Analysis'!$B$30:$B$45,'Variance Analysis'!$B$30,'Variance Analysis'!$A$30:$A$45,'Variance Analysis'!$A$34) -> #REF!
A18: EBIT | B18: $ | C18: =ABS(C17)-SUM(C14:C16) -> #REF! | D18: =ABS(D17)-SUM(D14:D16) -> #REF! | E18: =ABS(E17)-SUM(E14:E16) -> #REF! | F18: =ABS(F17)-SUM(F14:F16) -> #REF! | G18: =ABS(G17)-SUM(G14:G16) -> #REF! | H18: =ABS(H17)-SUM(H14:H16) -> #REF! | I18: =ABS(I17)-SUM(I14:I16) -> #REF! | J18: =ABS(J17)-SUM(J14:J16) -> #REF! | ... N18: =ABS(N17)-SUM(N14:N16) -> #REF!
A19: Jutik
A20: EBIT ACTUALS | B20: Units | C20: 2013/Jul | D20: 2013/Aug | E20: 2013/Sep | F20: 2013/Oct | G20: 2013/Nov | H20: 2013/Dec | I20: 2014/Jan | J20: 2014/Feb | K20: 2014/Mar | L20: 2014/Apr | M20: 2014/May | N20: 2014/Jun
A21: Overheads | B21: $ | C21: =SUMIFS('Variance Analysis'!C$30:C$45,'Variance Analysis'!$B$30:$B$45,'Variance Analysis'!$B$33,'Variance Analysis'!$A$30:$A$45,'Variance Analysis'!$A$38) -> #REF! | D21: =SUMIFS('Variance Analysis'!D$30:D$45,'Variance Analysis'!$B$30:$B$45,'Variance Analysis'!$B$33,'Variance Analysis'!$A$30:$A$45,'Variance Analysis'!$A$38) -> #REF! | E21: =SUMIFS('Variance Analysis'!E$30:E$45,'Variance Analysis'!$B$30:$B$45,'Variance Analysis'!$B$33,'Variance Analysis'!$A$30:$A$45,'Variance Analysis'!$A$38) -> #REF! | F21: =SUMIFS('Variance Analysis'!F$30:F$45,'Variance Analysis'!$B$30:$B$45,'Variance Analysis'!$B$33,'Variance Analysis'!$A$30:$A$45,'Variance Analysis'!$A$38) -> #REF! | G21: =SUMIFS('Variance Analysis'!G$30:G$45,'Variance Analysis'!$B$30:$B$45,'Variance Analysis'!$B$33,'Variance Analysis'!$A$30:$A$45,'Variance Analysis'!$A$38) -> #REF! | H21: =SUMIFS('Variance Analysis'!H$30:H$45,'Variance Analysis'!$B$30:$B$45,'Variance Analysis'!$B$33,'Variance Analysis'!$A$30:$A$45,'Variance Analysis'!$A$38) -> #REF! | I21: =SUMIFS('Variance Analysis'!I$30:I$45,'Variance Analysis'!$B$30:$B$45,'Variance Analysis'!$B$33,'Variance Analysis'!$A$30:$A$45,'Variance Analysis'!$A$38) -> #REF! | J21: =SUMIFS('Variance Analysis'!J$30:J$45,'Variance Analysis'!$B$30:$B$45,'Variance Analysis'!$B$33,'Variance Analysis'!$A$30:$A$45,'Variance Analysis'!$A$38) -> #REF! | ... N21: =SUMIFS('Variance Analysis'!N$30:N$45,'Variance Analysis'!$B$30:$B$45,'Variance Analysis'!$B$33,'Variance Analysis'!$A$30:$A$45,'Variance Analysis'!$A$38) -> #REF!
A22: Production Costs | B22: $ | C22: =SUMIFS('Variance Analysis'!C$30:C$45,'Variance Analysis'!$B$30:$B$45,'Variance Analysis'!$B$31,'Variance Analysis'!$A$30:$A$45,'Variance Analysis'!$A$38) -> #REF! | D22: =SUMIFS('Variance Analysis'!D$30:D$45,'Variance Analysis'!$B$30:$B$45,'Variance Analysis'!$B$31,'Variance Analysis'!$A$30:$A$45,'Variance Analysis'!$A$38) -> #REF! | E22: =SUMIFS('Variance Analysis'!E$30:E$45,'Variance Analysis'!$B$30:$B$45,'Variance Analysis'!$B$31,'Variance Analysis'!$A$30:$A$45,'Variance Analysis'!$A$38) -> #REF! | F22: =SUMIFS('Variance Analysis'!F$30:F$45,'Variance Analysis'!$B$30:$B$45,'Variance Analysis'!$B$31,'Variance Analysis'!$A$30:$A$45,'Variance Analysis'!$A$38) -> #REF! | G22: =SUMIFS('Variance Analysis'!G$30:G$45,'Variance Analysis'!$B$30:$B$45,'Variance Analysis'!$B$31,'Variance Analysis'!$A$30:$A$45,'Variance Analysis'!$A$38) -> #REF! | H22: =SUMIFS('Variance Analysis'!H$30:H$45,'Variance Analysis'!$B$30:$B$45,'Variance Analysis'!$B$31,'Variance Analysis'!$A$30:$A$45,'Variance Analysis'!$A$38) -> #REF! | I22: =SUMIFS('Variance Analysis'!I$30:I$45,'Variance Analysis'!$B$30:$B$45,'Variance Analysis'!$B$31,'Variance Analysis'!$A$30:$A$45,'Variance Analysis'!$A$38) -> #REF! | J22: =SUMIFS('Variance Analysis'!J$30:J$45,'Variance Analysis'!$B$30:$B$45,'Variance Analysis'!$B$31,'Variance Analysis'!$A$30:$A$45,'Variance Analysis'!$A$38) -> #REF! | ... N22: =SUMIFS('Variance Analysis'!N$30:N$45,'Variance Analysis'!$B$30:$B$45,'Variance Analysis'!$B$31,'Variance Analysis'!$A$30:$A$45,'Variance Analysis'!$A$38) -> #REF!
A23: Other Production Costs | B23: $ | C23: =SUMIFS('Variance Analysis'!C$30:C$45,'Variance Analysis'!$B$30:$B$45,'Variance Analysis'!$B$32,'Variance Analysis'!$A$30:$A$45,'Variance Analysis'!$A$38) -> #REF! | D23: =SUMIFS('Variance Analysis'!D$30:D$45,'Variance Analysis'!$B$30:$B$45,'Variance Analysis'!$B$32,'Variance Analysis'!$A$30:$A$45,'Variance Analysis'!$A$38) -> #REF! | E23: =SUMIFS('Variance Analysis'!E$30:E$45,'Variance Analysis'!$B$30:$B$45,'Variance Analysis'!$B$32,'Variance Analysis'!$A$30:$A$45,'Variance Analysis'!$A$38) -> #REF! | F23: =SUMIFS('Variance Analysis'!F$30:F$45,'Variance Analysis'!$B$30:$B$45,'Variance Analysis'!$B$32,'Variance Analysis'!$A$30:$A$45,'Variance Analysis'!$A$38) -> #REF! | G23: =SUMIFS('Variance Analysis'!G$30:G$45,'Variance Analysis'!$B$30:$B$45,'Variance Analysis'!$B$32,'Variance Analysis'!$A$30:$A$45,'Variance Analysis'!$A$38) -> #REF! | H23: =SUMIFS('Variance Analysis'!H$30:H$45,'Variance Analysis'!$B$30:$B$45,'Variance Analysis'!$B$32,'Variance Analysis'!$A$30:$A$45,'Variance Analysis'!$A$38) -> #REF! | I23: =SUMIFS('Variance Analysis'!I$30:I$45,'Variance Analysis'!$B$30:$B$45,'Variance Analysis'!$B$32,'Variance Analysis'!$A$30:$A$45,'Variance Analysis'!$A$38) -> #REF! | J23: =SUMIFS('Variance Analysis'!J$30:J$45,'Variance Analysis'!$B$30:$B$45,'Variance Analysis'!$B$32,'Variance Analysis'!$A$30:$A$45,'Variance Analysis'!$A$38) -> #REF! | ... N23: =SUMIFS('Variance Analysis'!N$30:N$45,'Variance Analysis'!$B$30:$B$45,'Variance Analysis'!$B$32,'Variance Analysis'!$A$30:$A$45,'Variance Analysis'!$A$38) -> #REF!
A24: Revenue | B24: $ | C24: =SUMIFS('Variance Analysis'!C$30:C$45,'Variance Analysis'!$B$30:$B$45,'Variance Analysis'!$B$30,'Variance Analysis'!$A$30:$A$45,'Variance Analysis'!$A$38) -> #REF! | D24: =SUMIFS('Variance Analysis'!D$30:D$45,'Variance Analysis'!$B$30:$B$45,'Variance Analysis'!$B$30,'Variance Analysis'!$A$30:$A$45,'Variance Analysis'!$A$38) -> #REF! | E24: =SUMIFS('Variance Analysis'!E$30:E$45,'Variance Analysis'!$B$30:$B$45,'Variance Analysis'!$B$30,'Variance Analysis'!$A$30:$A$45,'Variance Analysis'!$A$38) -> #REF! | F24: =SUMIFS('Variance Analysis'!F$30:F$45,'Variance Analysis'!$B$30:$B$45,'Variance Analysis'!$B$30,'Variance Analysis'!$A$30:$A$45,'Variance Analysis'!$A$38) -> #REF! | G24: =SUMIFS('Variance Analysis'!G$30:G$45,'Variance Analysis'!$B$30:$B$45,'Variance Analysis'!$B$30,'Variance Analysis'!$A$30:$A$45,'Variance Analysis'!$A$38) -> #REF! | H24: =SUMIFS('Variance Analysis'!H$30:H$45,'Variance Analysis'!$B$30:$B$45,'Variance Analysis'!$B$30,'Variance Analysis'!$A$30:$A$45,'Variance Analysis'!$A$38) -> #REF! | I24: =SUMIFS('Variance Analysis'!I$30:I$45,'Variance Analysis'!$B$30:$B$45,'Variance Analysis'!$B$30,'Variance Analysis'!$A$30:$A$45,'Variance Analysis'!$A$38) -> #REF! | J24: =SUMIFS('Variance Analysis'!J$30:J$45,'Variance Analysis'!$B$30:$B$45,'Variance Analysis'!$B$30,'Variance Analysis'!$A$30:$A$45,'Variance Analysis'!$A$38) -> #REF! | ... N24: =SUMIFS('Variance Analysis'!N$30:N$45,'Variance Analysis'!$B$30:$B$45,'Variance Analysis'!$B$30,'Variance Analysis'!$A$30:$A$45,'Variance Analysis'!$A$38) -> #REF!
A25: EBIT | B25: $ | C25: =ABS(C24)-SUM(C21:C23) -> #REF! | D25: =ABS(D24)-SUM(D21:D23) -> #REF! | E25: =ABS(E24)-SUM(E21:E23) -> #REF! | F25: =ABS(F24)-SUM(F21:F23) -> #REF! | G25: =ABS(G24)-SUM(G21:G23) -> #REF! | H25: =ABS(H24)-SUM(H21:H23) -> #REF! | I25: =ABS(I24)-SUM(I21:I23) -> #REF! | J25: =ABS(J24)-SUM(J21:J23) -> #REF! | ... N25: =ABS(N24)-SUM(N21:N23) -> #REF!
A26: OVERALL
A27: EBIT ACTUALS | B27: Units | C27: 2013/Jul | D27: 2013/Aug | E27: 2013/Sep | F27: 2013/Oct | G27: 2013/Nov | H27: 2013/Dec | I27: 2014/Jan | J27: 2014/Feb | K27: 2014/Mar | L27: 2014/Apr | M27: 2014/May | N27: 2014/Jun
A28: Overheads | B28: $ | C28: =SUMIFS('Variance Analysis'!C$30:C$45,'Variance Analysis'!$B$30:$B$45,'Variance Analysis'!$B$33,'Variance Analysis'!$A$30:$A$45,'Variance Analysis'!$A$42) -> #REF! | D28: =SUMIFS('Variance Analysis'!D$30:D$45,'Variance Analysis'!$B$30:$B$45,'Variance Analysis'!$B$33,'Variance Analysis'!$A$30:$A$45,'Variance Analysis'!$A$42) -> #REF! | E28: =SUMIFS('Variance Analysis'!E$30:E$45,'Variance Analysis'!$B$30:$B$45,'Variance Analysis'!$B$33,'Variance Analysis'!$A$30:$A$45,'Variance Analysis'!$A$42) -> #REF! | F28: =SUMIFS('Variance Analysis'!F$30:F$45,'Variance Analysis'!$B$30:$B$45,'Variance Analysis'!$B$33,'Variance Analysis'!$A$30:$A$45,'Variance Analysis'!$A$42) -> #REF! | G28: =SUMIFS('Variance Analysis'!G$30:G$45,'Variance Analysis'!$B$30:$B$45,'Variance Analysis'!$B$33,'Variance Analysis'!$A$30:$A$45,'Variance Analysis'!$A$42) -> #REF! | H28: =SUMIFS('Variance Analysis'!H$30:H$45,'Variance Analysis'!$B$30:$B$45,'Variance Analysis'!$B$33,'Variance Analysis'!$A$30:$A$45,'Variance Analysis'!$A$42) -> #REF! | I28: =SUMIFS('Variance Analysis'!I$30:I$45,'Variance Analysis'!$B$30:$B$45,'Variance Analysis'!$B$33,'Variance Analysis'!$A$30:$A$45,'Variance Analysis'!$A$42) -> #REF! | J28: =SUMIFS('Variance Analysis'!J$30:J$45,'Variance Analysis'!$B$30:$B$45,'Variance Analysis'!$B$33,'Variance Analysis'!$A$30:$A$45,'Variance Analysis'!$A$42) -> #REF! | ... N28: =SUMIFS('Variance Analysis'!N$30:N$45,'Variance Analysis'!$B$30:$B$45,'Variance Analysis'!$B$33,'Variance Analysis'!$A$30:$A$45,'Variance Analysis'!$A$42) -> #REF!
A29: Production Costs | B29: $ | C29: =SUMIFS('Variance Analysis'!C$30:C$45,'Variance Analysis'!$B$30:$B$45,'Variance Analysis'!$B$31,'Variance Analysis'!$A$30:$A$45,'Variance Analysis'!$A$42) -> #REF! | D29: =SUMIFS('Variance Analysis'!D$30:D$45,'Variance Analysis'!$B$30:$B$45,'Variance Analysis'!$B$31,'Variance Analysis'!$A$30:$A$45,'Variance Analysis'!$A$42) -> #REF! | E29: =SUMIFS('Variance Analysis'!E$30:E$45,'Variance Analysis'!$B$30:$B$45,'Variance Analysis'!$B$31,'Variance Analysis'!$A$30:$A$45,'Variance Analysis'!$A$42) -> #REF! | F29: =SUMIFS('Variance Analysis'!F$30:F$45,'Variance Analysis'!$B$30:$B$45,'Variance Analysis'!$B$31,'Variance Analysis'!$A$30:$A$45,'Variance Analysis'!$A$42) -> #REF! | G29: =SUMIFS('Variance Analysis'!G$30:G$45,'Variance Analysis'!$B$30:$B$45,'Variance Analysis'!$B$31,'Variance Analysis'!$A$30:$A$45,'Variance Analysis'!$A$42) -> #REF! | H29: =SUMIFS('Variance Analysis'!H$30:H$45,'Variance Analysis'!$B$30:$B$45,'Variance Analysis'!$B$31,'Variance Analysis'!$A$30:$A$45,'Variance Analysis'!$A$42) -> #REF! | I29: =SUMIFS('Variance Analysis'!I$30:I$45,'Variance Analysis'!$B$30:$B$45,'Variance Analysis'!$B$31,'Variance Analysis'!$A$30:$A$45,'Variance Analysis'!$A$42) -> #REF! | J29: =SUMIFS('Variance Analysis'!J$30:J$45,'Variance Analysis'!$B$30:$B$45,'Variance Analysis'!$B$31,'Variance Analysis'!$A$30:$A$45,'Variance Analysis'!$A$42) -> #REF! | ... N29: =SUMIFS('Variance Analysis'!N$30:N$45,'Variance Analysis'!$B$30:$B$45,'Variance Analysis'!$B$31,'Variance Analysis'!$A$30:$A$45,'Variance Analysis'!$A$42) -> #REF!
A30: Other Production Costs | B30: $ | C30: =SUMIFS('Variance Analysis'!C$30:C$45,'Variance Analysis'!$B$30:$B$45,'Variance Analysis'!$B$32,'Variance Analysis'!$A$30:$A$45,'Variance Analysis'!$A$42) -> #REF! | D30: =SUMIFS('Variance Analysis'!D$30:D$45,'Variance Analysis'!$B$30:$B$45,'Variance Analysis'!$B$32,'Variance Analysis'!$A$30:$A$45,'Variance Analysis'!$A$42) -> #REF! | E30: =SUMIFS('Variance Analysis'!E$30:E$45,'Variance Analysis'!$B$30:$B$45,'Variance Analysis'!$B$32,'Variance Analysis'!$A$30:$A$45,'Variance Analysis'!$A$42) -> #REF! | F30: =SUMIFS('Variance Analysis'!F$30:F$45,'Variance Analysis'!$B$30:$B$45,'Variance Analysis'!$B$32,'Variance Analysis'!$A$30:$A$45,'Variance Analysis'!$A$42) -> #REF! | G30: =SUMIFS('Variance Analysis'!G$30:G$45,'Variance Analysis'!$B$30:$B$45,'Variance Analysis'!$B$32,'Variance Analysis'!$A$30:$A$45,'Variance Analysis'!$A$42) -> #REF! | H30: =SUMIFS('Variance Analysis'!H$30:H$45,'Variance Analysis'!$B$30:$B$45,'Variance Analysis'!$B$32,'Variance Analysis'!$A$30:$A$45,'Variance Analysis'!$A$42) -> #REF! | I30: =SUMIFS('Variance Analysis'!I$30:I$45,'Variance Analysis'!$B$30:$B$45,'Variance Analysis'!$B$32,'Variance Analysis'!$A$30:$A$45,'Variance Analysis'!$A$42) -> #REF! | J30: =SUMIFS('Variance Analysis'!J$30:J$45,'Variance Analysis'!$B$30:$B$45,'Variance Analysis'!$B$32,'Variance Analysis'!$A$30:$A$45,'Variance Analysis'!$A$42) -> #REF! | ... N30: =SUMIFS('Variance Analysis'!N$30:N$45,'Variance Analysis'!$B$30:$B$45,'Variance Analysis'!$B$32,'Variance Analysis'!$A$30:$A$45,'Variance Analysis'!$A$42) -> #REF!
A31: Revenue | B31: $ | C31: =SUMIFS('Variance Analysis'!C$30:C$45,'Variance Analysis'!$B$30:$B$45,'Variance Analysis'!$B$30,'Variance Analysis'!$A$30:$A$45,'Variance Analysis'!$A$42) -> #REF! | D31: =SUMIFS('Variance Analysis'!D$30:D$45,'Variance Analysis'!$B$30:$B$45,'Variance Analysis'!$B$30,'Variance Analysis'!$A$30:$A$45,'Variance Analysis'!$A$42) -> #REF! | E31: =SUMIFS('Variance Analysis'!E$30:E$45,'Variance Analysis'!$B$30:$B$45,'Variance Analysis'!$B$30,'Variance Analysis'!$A$30:$A$45,'Variance Analysis'!$A$42) -> #REF! | F31: =SUMIFS('Variance Analysis'!F$30:F$45,'Variance Analysis'!$B$30:$B$45,'Variance Analysis'!$B$30,'Variance Analysis'!$A$30:$A$45,'Variance Analysis'!$A$42) -> #REF! | G31: =SUMIFS('Variance Analysis'!G$30:G$45,'Variance Analysis'!$B$30:$B$45,'Variance Analysis'!$B$30,'Variance Analysis'!$A$30:$A$45,'Variance Analysis'!$A$42) -> #REF! | H31: =SUMIFS('Variance Analysis'!H$30:H$45,'Variance Analysis'!$B$30:$B$45,'Variance Analysis'!$B$30,'Variance Analysis'!$A$30:$A$45,'Variance Analysis'!$A$42) -> #REF! | I31: =SUMIFS('Variance Analysis'!I$30:I$45,'Variance Analysis'!$B$30:$B$45,'Variance Analysis'!$B$30,'Variance Analysis'!$A$30:$A$45,'Variance Analysis'!$A$42) -> #REF! | J31: =SUMIFS('Variance Analysis'!J$30:J$45,'Variance Analysis'!$B$30:$B$45,'Variance Analysis'!$B$30,'Variance Analysis'!$A$30:$A$45,'Variance Analysis'!$A$42) -> #REF! | ... N31: =SUMIFS('Variance Analysis'!N$30:N$45,'Variance Analysis'!$B$30:$B$45,'Variance Analysis'!$B$30,'Variance Analysis'!$A$30:$A$45,'Variance Analysis'!$A$42) -> #REF!
A32: EBIT | B32: $ | C32: =ABS(C31)-SUM(C28:C30) -> #REF! | D32: =ABS(D31)-SUM(D28:D30) -> #REF! | E32: =ABS(E31)-SUM(E28:E30) -> #REF! | F32: =ABS(F31)-SUM(F28:F30) -> #REF! | G32: =ABS(G31)-SUM(G28:G30) -> #REF! | H32: =ABS(H31)-SUM(H28:H30) -> #REF! | I32: =ABS(I31)-SUM(I28:I30) -> #REF! | J32: =ABS(J31)-SUM(J28:J30) -> #REF! | ... N32: =ABS(N31)-SUM(N28:N30) -> #REF!
A33: BUDGET
A35: Kootha | B35: Units | C35: 2013/Jul | D35: 2013/Aug | E35: 2013/Sep | F35: 2013/Oct | G35: 2013/Nov | H35: 2013/Dec | I35: 2014/Jan | J35: 2014/Feb | K35: 2014/Mar | L35: 2014/Apr | M35: 2014/May | N35: 2014/Jun
A36: Overheads | B36: $ | C36: =SUMIFS('Variance Analysis'!C$9:C$24,'Variance Analysis'!$B$9:$B$24,'Variance Analysis'!$B$12,'Variance Analysis'!$A$9:$A$24,'Variance Analysis'!$A$12) -> #REF! | D36: =SUMIFS('Variance Analysis'!D$9:D$24,'Variance Analysis'!$B$9:$B$24,'Variance Analysis'!$B$12,'Variance Analysis'!$A$9:$A$24,'Variance Analysis'!$A$12) -> #REF! | E36: =SUMIFS('Variance Analysis'!E$9:E$24,'Variance Analysis'!$B$9:$B$24,'Variance Analysis'!$B$12,'Variance Analysis'!$A$9:$A$24,'Variance Analysis'!$A$12) -> #REF! | F36: =SUMIFS('Variance Analysis'!F$9:F$24,'Variance Analysis'!$B$9:$B$24,'Variance Analysis'!$B$12,'Variance Analysis'!$A$9:$A$24,'Variance Analysis'!$A$12) -> #REF! | G36: =SUMIFS('Variance Analysis'!G$9:G$24,'Variance Analysis'!$B$9:$B$24,'Variance Analysis'!$B$12,'Variance Analysis'!$A$9:$A$24,'Variance Analysis'!$A$12) -> #REF! | H36: =SUMIFS('Variance Analysis'!H$9:H$24,'Variance Analysis'!$B$9:$B$24,'Variance Analysis'!$B$12,'Variance Analysis'!$A$9:$A$24,'Variance Analysis'!$A$12) -> #REF! | I36: =SUMIFS('Variance Analysis'!I$9:I$24,'Variance Analysis'!$B$9:$B$24,'Variance Analysis'!$B$12,'Variance Analysis'!$A$9:$A$24,'Variance Analysis'!$A$12) -> #REF! | J36: =SUMIFS('Variance Analysis'!J$9:J$24,'Variance Analysis'!$B$9:$B$24,'Variance Analysis'!$B$12,'Variance Analysis'!$A$9:$A$24,'Variance Analysis'!$A$12) -> #REF! | ... N36: =SUMIFS('Variance Analysis'!N$9:N$24,'Variance Analysis'!$B$9:$B$24,'Variance Analysis'!$B$12,'Variance Analysis'!$A$9:$A$24,'Variance Analysis'!$A$12) -> #REF!
A37: Production Costs | B37: $ | C37: =SUMIFS('Variance Analysis'!C$9:C$24,'Variance Analysis'!$B$9:$B$24,'Variance Analysis'!$B$10,'Variance Analysis'!$A$9:$A$24,'Variance Analysis'!$A$12) -> #REF! | D37: =SUMIFS('Variance Analysis'!D$9:D$24,'Variance Analysis'!$B$9:$B$24,'Variance Analysis'!$B$10,'Variance Analysis'!$A$9:$A$24,'Variance Analysis'!$A$12) -> #REF! | E37: =SUMIFS('Variance Analysis'!E$9:E$24,'Variance Analysis'!$B$9:$B$24,'Variance Analysis'!$B$10,'Variance Analysis'!$A$9:$A$24,'Variance Analysis'!$A$12) -> #REF! | F37: =SUMIFS('Variance Analysis'!F$9:F$24,'Variance Analysis'!$B$9:$B$24,'Variance Analysis'!$B$10,'Variance Analysis'!$A$9:$A$24,'Variance Analysis'!$A$12) -> #REF! | G37: =SUMIFS('Variance Analysis'!G$9:G$24,'Variance Analysis'!$B$9:$B$24,'Variance Analysis'!$B$10,'Variance Analysis'!$A$9:$A$24,'Variance Analysis'!$A$12) -> #REF! | H37: =SUMIFS('Variance Analysis'!H$9:H$24,'Variance Analysis'!$B$9:$B$24,'Variance Analysis'!$B$10,'Variance Analysis'!$A$9:$A$24,'Variance Analysis'!$A$12) -> #REF! | I37: =SUMIFS('Variance Analysis'!I$9:I$24,'Variance Analysis'!$B$9:$B$24,'Variance Analysis'!$B$10,'Variance Analysis'!$A$9:$A$24,'Variance Analysis'!$A$12) -> #REF! | J37: =SUMIFS('Variance Analysis'!J$9:J$24,'Variance Analysis'!$B$9:$B$24,'Variance Analysis'!$B$10,'Variance Analysis'!$A$9:$A$24,'Variance Analysis'!$A$12) -> #REF! | ... N37: =SUMIFS('Variance Analysis'!N$9:N$24,'Variance Analysis'!$B$9:$B$24,'Variance Analysis'!$B$10,'Variance Analysis'!$A$9:$A$24,'Variance Analysis'!$A$12) -> #REF!
A38: Other Production Costs | B38: $ | C38: =SUMIFS('Variance Analysis'!C$9:C$24,'Variance Analysis'!$B$9:$B$24,'Variance Analysis'!$B$11,'Variance Analysis'!$A$9:$A$24,'Variance Analysis'!$A$12) -> #REF! | D38: =SUMIFS('Variance Analysis'!D$9:D$24,'Variance Analysis'!$B$9:$B$24,'Variance Analysis'!$B$11,'Variance Analysis'!$A$9:$A$24,'Variance Analysis'!$A$12) -> #REF! | E38: =SUMIFS('Variance Analysis'!E$9:E$24,'Variance Analysis'!$B$9:$B$24,'Variance Analysis'!$B$11,'Variance Analysis'!$A$9:$A$24,'Variance Analysis'!$A$12) -> #REF! | F38: =SUMIFS('Variance Analysis'!F$9:F$24,'Variance Analysis'!$B$9:$B$24,'Variance Analysis'!$B$11,'Variance Analysis'!$A$9:$A$24,'Variance Analysis'!$A$12) -> #REF! | G38: =SUMIFS('Variance Analysis'!G$9:G$24,'Variance Analysis'!$B$9:$B$24,'Variance Analysis'!$B$11,'Variance Analysis'!$A$9:$A$24,'Variance Analysis'!$A$12) -> #REF! | H38: =SUMIFS('Variance Analysis'!H$9:H$24,'Variance Analysis'!$B$9:$B$24,'Variance Analysis'!$B$11,'Variance Analysis'!$A$9:$A$24,'Variance Analysis'!$A$12) -> #REF! | I38: =SUMIFS('Variance Analysis'!I$9:I$24,'Variance Analysis'!$B$9:$B$24,'Variance Analysis'!$B$11,'Variance Analysis'!$A$9:$A$24,'Variance Analysis'!$A$12) -> #REF! | J38: =SUMIFS('Variance Analysis'!J$9:J$24,'Variance Analysis'!$B$9:$B$24,'Variance Analysis'!$B$11,'Variance Analysis'!$A$9:$A$24,'Variance Analysis'!$A$12) -> #REF! | ... N38: =SUMIFS('Variance Analysis'!N$9:N$24,'Variance Analysis'!$B$9:$B$24,'Variance Analysis'!$B$11,'Variance Analysis'!$A$9:$A$24,'Variance Analysis'!$A$12) -> #REF!
A39: Revenue | B39: $ | C39: =SUMIFS('Variance Analysis'!C$9:C$24,'Variance Analysis'!$B$9:$B$24,'Variance Analysis'!$B$9,'Variance Analysis'!$A$9:$A$24,'Variance Analysis'!$A$12) -> #REF! | D39: =SUMIFS('Variance Analysis'!D$9:D$24,'Variance Analysis'!$B$9:$B$24,'Variance Analysis'!$B$9,'Variance Analysis'!$A$9:$A$24,'Variance Analysis'!$A$12) -> #REF! | E39: =SUMIFS('Variance Analysis'!E$9:E$24,'Variance Analysis'!$B$9:$B$24,'Variance Analysis'!$B$9,'Variance Analysis'!$A$9:$A$24,'Variance Analysis'!$A$12) -> #REF! | F39: =SUMIFS('Variance Analysis'!F$9:F$24,'Variance Analysis'!$B$9:$B$24,'Variance Analysis'!$B$9,'Variance Analysis'!$A$9:$A$24,'Variance Analysis'!$A$12) -> #REF! | G39: =SUMIFS('Variance Analysis'!G$9:G$24,'Variance Analysis'!$B$9:$B$24,'Variance Analysis'!$B$9,'Variance Analysis'!$A$9:$A$24,'Variance Analysis'!$A$12) -> #REF! | H39: =SUMIFS('Variance Analysis'!H$9:H$24,'Variance Analysis'!$B$9:$B$24,'Variance Analysis'!$B$9,'Variance Analysis'!$A$9:$A$24,'Variance Analysis'!$A$12) -> #REF! | I39: =SUMIFS('Variance Analysis'!I$9:I$24,'Variance Analysis'!$B$9:$B$24,'Variance Analysis'!$B$9,'Variance Analysis'!$A$9:$A$24,'Variance Analysis'!$A$12) -> #REF! | J39: =SUMIFS('Variance Analysis'!J$9:J$24,'Variance Analysis'!$B$9:$B$24,'Variance Analysis'!$B$9,'Variance Analysis'!$A$9:$A$24,'Variance Analysis'!$A$12) -> #REF! | ... N39: =SUMIFS('Variance Analysis'!N$9:N$24,'Variance Analysis'!$B$9:$B$24,'Variance Analysis'!$B$9,'Variance Analysis'!$A$9:$A$24,'Variance Analysis'!$A$12) -> #REF!
A40: EBIT | B40: $ | C40: =ABS(C39)-SUM(C36:C38) -> #REF! | D40: =ABS(D39)-SUM(D36:D38) -> #REF! | E40: =ABS(E39)-SUM(E36:E38) -> #REF! | F40: =ABS(F39)-SUM(F36:F38) -> #REF! | G40: =ABS(G39)-SUM(G36:G38) -> #REF! | H40: =ABS(H39)-SUM(H36:H38) -> #REF! | I40: =ABS(I39)-SUM(I36:I38) -> #REF! | J40: =ABS(J39)-SUM(J36:J38) -> #REF! | ... N40: =ABS(N39)-SUM(N36:N38) -> #REF!
A43: Surjek | B43: Units | C43: 2013/Jul | D43: 2013/Aug | E43: 2013/Sep | F43: 2013/Oct | G43: 2013/Nov | H43: 2013/Dec | I43: 2014/Jan | J43: 2014/Feb | K43: 2014/Mar | L43: 2014/Apr | M43: 2014/May | N43: 2014/Jun
A44: Overheads | B44: $ | C44: =SUMIFS('Variance Analysis'!C$9:C$24,'Variance Analysis'!$B$9:$B$24,'Variance Analysis'!$B$12,'Variance Analysis'!$A$9:$A$24,'Variance Analysis'!$A$13) -> #REF! | D44: =SUMIFS('Variance Analysis'!D$9:D$24,'Variance Analysis'!$B$9:$B$24,'Variance Analysis'!$B$12,'Variance Analysis'!$A$9:$A$24,'Variance Analysis'!$A$13) -> #REF! | E44: =SUMIFS('Variance Analysis'!E$9:E$24,'Variance Analysis'!$B$9:$B$24,'Variance Analysis'!$B$12,'Variance Analysis'!$A$9:$A$24,'Variance Analysis'!$A$13) -> #REF! | F44: =SUMIFS('Variance Analysis'!F$9:F$24,'Variance Analysis'!$B$9:$B$24,'Variance Analysis'!$B$12,'Variance Analysis'!$A$9:$A$24,'Variance Analysis'!$A$13) -> #REF! | G44: =SUMIFS('Variance Analysis'!G$9:G$24,'Variance Analysis'!$B$9:$B$24,'Variance Analysis'!$B$12,'Variance Analysis'!$A$9:$A$24,'Variance Analysis'!$A$13) -> #REF! | H44: =SUMIFS('Variance Analysis'!H$9:H$24,'Variance Analysis'!$B$9:$B$24,'Variance Analysis'!$B$12,'Variance Analysis'!$A$9:$A$24,'Variance Analysis'!$A$13) -> #REF! | I44: =SUMIFS('Variance Analysis'!I$9:I$24,'Variance Analysis'!$B$9:$B$24,'Variance Analysis'!$B$12,'Variance Analysis'!$A$9:$A$24,'Variance Analysis'!$A$13) -> #REF! | J44: =SUMIFS('Variance Analysis'!J$9:J$24,'Variance Analysis'!$B$9:$B$24,'Variance Analysis'!$B$12,'Variance Analysis'!$A$9:$A$24,'Variance Analysis'!$A$13) -> #REF! | ... N44: =SUMIFS('Variance Analysis'!N$9:N$24,'Variance Analysis'!$B$9:$B$24,'Variance Analysis'!$B$12,'Variance Analysis'!$A$9:$A$24,'Variance Analysis'!$A$13) -> #REF!
A45: Production Costs | B45: $ | C45: =SUMIFS('Variance Analysis'!C$9:C$24,'Variance Analysis'!$B$9:$B$24,'Variance Analysis'!$B$10,'Variance Analysis'!$A$9:$A$24,'Variance Analysis'!$A$13) -> #REF! | D45: =SUMIFS('Variance Analysis'!D$9:D$24,'Variance Analysis'!$B$9:$B$24,'Variance Analysis'!$B$10,'Variance Analysis'!$A$9:$A$24,'Variance Analysis'!$A$13) -> #REF! | E45: =SUMIFS('Variance Analysis'!E$9:E$24,'Variance Analysis'!$B$9:$B$24,'Variance Analysis'!$B$10,'Variance Analysis'!$A$9:$A$24,'Variance Analysis'!$A$13) -> #REF! | F45: =SUMIFS('Variance Analysis'!F$9:F$24,'Variance Analysis'!$B$9:$B$24,'Variance Analysis'!$B$10,'Variance Analysis'!$A$9:$A$24,'Variance Analysis'!$A$13) -> #REF! | G45: =SUMIFS('Variance Analysis'!G$9:G$24,'Variance Analysis'!$B$9:$B$24,'Variance Analysis'!$B$10,'Variance Analysis'!$A$9:$A$24,'Variance Analysis'!$A$13) -> #REF! | H45: =SUMIFS('Variance Analysis'!H$9:H$24,'Variance Analysis'!$B$9:$B$24,'Variance Analysis'!$B$10,'Variance Analysis'!$A$9:$A$24,'Variance Analysis'!$A$13) -> #REF! | I45: =SUMIFS('Variance Analysis'!I$9:I$24,'Variance Analysis'!$B$9:$B$24,'Variance Analysis'!$B$10,'Variance Analysis'!$A$9:$A$24,'Variance Analysis'!$A$13) -> #REF! | J45: =SUMIFS('Variance Analysis'!J$9:J$24,'Variance Analysis'!$B$9:$B$24,'Variance Analysis'!$B$10,'Variance Analysis'!$A$9:$A$24,'Variance Analysis'!$A$13) -> #REF! | ... N45: =SUMIFS('Variance Analysis'!N$9:N$24,'Variance Analysis'!$B$9:$B$24,'Variance Analysis'!$B$10,'Variance Analysis'!$A$9:$A$24,'Variance Analysis'!$A$13) -> #REF!
A46: Other Production Costs | B46: $ | C46: =SUMIFS('Variance Analysis'!C$9:C$24,'Variance Analysis'!$B$9:$B$24,'Variance Analysis'!$B$11,'Variance Analysis'!$A$9:$A$24,'Variance Analysis'!$A$13) -> #REF! | D46: =SUMIFS('Variance Analysis'!D$9:D$24,'Variance Analysis'!$B$9:$B$24,'Variance Analysis'!$B$11,'Variance Analysis'!$A$9:$A$24,'Variance Analysis'!$A$13) -> #REF! | E46: =SUMIFS('Variance Analysis'!E$9:E$24,'Variance Analysis'!$B$9:$B$24,'Variance Analysis'!$B$11,'Variance Analysis'!$A$9:$A$24,'Variance Analysis'!$A$13) -> #REF! | F46: =SUMIFS('Variance Analysis'!F$9:F$24,'Variance Analysis'!$B$9:$B$24,'Variance Analysis'!$B$11,'Variance Analysis'!$A$9:$A$24,'Variance Analysis'!$A$13) -> #REF! | G46: =SUMIFS('Variance Analysis'!G$9:G$24,'Variance Analysis'!$B$9:$B$24,'Variance Analysis'!$B$11,'Variance Analysis'!$A$9:$A$24,'Variance Analysis'!$A$13) -> #REF! | H46: =SUMIFS('Variance Analysis'!H$9:H$24,'Variance Analysis'!$B$9:$B$24,'Variance Analysis'!$B$11,'Variance Analysis'!$A$9:$A$24,'Variance Analysis'!$A$13) -> #REF! | I46: =SUMIFS('Variance Analysis'!I$9:I$24,'Variance Analysis'!$B$9:$B$24,'Variance Analysis'!$B$11,'Variance Analysis'!$A$9:$A$24,'Variance Analysis'!$A$13) -> #REF! | J46: =SUMIFS('Variance Analysis'!J$9:J$24,'Variance Analysis'!$B$9:$B$24,'Variance Analysis'!$B$11,'Variance Analysis'!$A$9:$A$24,'Variance Analysis'!$A$13) -> #REF! | ... N46: =SUMIFS('Variance Analysis'!N$9:N$24,'Variance Analysis'!$B$9:$B$24,'Variance Analysis'!$B$11,'Variance Analysis'!$A$9:$A$24,'Variance Analysis'!$A$13) -> #REF!
A47: Revenue | B47: $ | C47: =SUMIFS('Variance Analysis'!C$9:C$24,'Variance Analysis'!$B$9:$B$24,'Variance Analysis'!$B$9,'Variance Analysis'!$A$9:$A$24,'Variance Analysis'!$A$13) -> #REF! | D47: =SUMIFS('Variance Analysis'!D$9:D$24,'Variance Analysis'!$B$9:$B$24,'Variance Analysis'!$B$9,'Variance Analysis'!$A$9:$A$24,'Variance Analysis'!$A$13) -> #REF! | E47: =SUMIFS('Variance Analysis'!E$9:E$24,'Variance Analysis'!$B$9:$B$24,'Variance Analysis'!$B$9,'Variance Analysis'!$A$9:$A$24,'Variance Analysis'!$A$13) -> #REF! | F47: =SUMIFS('Variance Analysis'!F$9:F$24,'Variance Analysis'!$B$9:$B$24,'Variance Analysis'!$B$9,'Variance Analysis'!$A$9:$A$24,'Variance Analysis'!$A$13) -> #REF! | G47: =SUMIFS('Variance Analysis'!G$9:G$24,'Variance Analysis'!$B$9:$B$24,'Variance Analysis'!$B$9,'Variance Analysis'!$A$9:$A$24,'Variance Analysis'!$A$13) -> #REF! | H47: =SUMIFS('Variance Analysis'!H$9:H$24,'Variance Analysis'!$B$9:$B$24,'Variance Analysis'!$B$9,'Variance Analysis'!$A$9:$A$24,'Variance Analysis'!$A$13) -> #REF! | I47: =SUMIFS('Variance Analysis'!I$9:I$24,'Variance Analysis'!$B$9:$B$24,'Variance Analysis'!$B$9,'Variance Analysis'!$A$9:$A$24,'Variance Analysis'!$A$13) -> #REF! | J47: =SUMIFS('Variance Analysis'!J$9:J$24,'Variance Analysis'!$B$9:$B$24,'Variance Analysis'!$B$9,'Variance Analysis'!$A$9:$A$24,'Variance Analysis'!$A$13) -> #REF! | ... N47: =SUMIFS('Variance Analysis'!N$9:N$24,'Variance Analysis'!$B$9:$B$24,'Variance Analysis'!$B$9,'Variance Analysis'!$A$9:$A$24,'Variance Analysis'!$A$13) -> #REF!
A48: EBIT | B48: $ | C48: =ABS(C47)-SUM(C44:C46) -> #REF! | D48: =ABS(D47)-SUM(D44:D46) -> #REF! | E48: =ABS(E47)-SUM(E44:E46) -> #REF! | F48: =ABS(F47)-SUM(F44:F46) -> #REF! | G48: =ABS(G47)-SUM(G44:G46) -> #REF! | H48: =ABS(H47)-SUM(H44:H46) -> #REF! | I48: =ABS(I47)-SUM(I44:I46) -> #REF! | J48: =ABS(J47)-SUM(J44:J46) -> #REF! | ... N48: =ABS(N47)-SUM(N44:N46) -> #REF!
A51: Jutik | B51: Units | C51: 2013/Jul | D51: 2013/Aug | E51: 2013/Sep | F51: 2013/Oct | G51: 2013/Nov | H51: 2013/Dec | I51: 2014/Jan | J51: 2014/Feb | K51: 2014/Mar | L51: 2014/Apr | M51: 2014/May | N51: 2014/Jun
A52: Overheads | B52: $ | C52: =SUMIFS('Variance Analysis'!C$9:C$24,'Variance Analysis'!$B$9:$B$24,'Variance Analysis'!$B$12,'Variance Analysis'!$A$9:$A$24,'Variance Analysis'!$A$17) -> #REF! | D52: =SUMIFS('Variance Analysis'!D$9:D$24,'Variance Analysis'!$B$9:$B$24,'Variance Analysis'!$B$12,'Variance Analysis'!$A$9:$A$24,'Variance Analysis'!$A$17) -> #REF! | E52: =SUMIFS('Variance Analysis'!E$9:E$24,'Variance Analysis'!$B$9:$B$24,'Variance Analysis'!$B$12,'Variance Analysis'!$A$9:$A$24,'Variance Analysis'!$A$17) -> #REF! | F52: =SUMIFS('Variance Analysis'!F$9:F$24,'Variance Analysis'!$B$9:$B$24,'Variance Analysis'!$B$12,'Variance Analysis'!$A$9:$A$24,'Variance Analysis'!$A$17) -> #REF! | G52: =SUMIFS('Variance Analysis'!G$9:G$24,'Variance Analysis'!$B$9:$B$24,'Variance Analysis'!$B$12,'Variance Analysis'!$A$9:$A$24,'Variance Analysis'!$A$17) -> #REF! | H52: =SUMIFS('Variance Analysis'!H$9:H$24,'Variance Analysis'!$B$9:$B$24,'Variance Analysis'!$B$12,'Variance Analysis'!$A$9:$A$24,'Variance Analysis'!$A$17) -> #REF! | I52: =SUMIFS('Variance Analysis'!I$9:I$24,'Variance Analysis'!$B$9:$B$24,'Variance Analysis'!$B$12,'Variance Analysis'!$A$9:$A$24,'Variance Analysis'!$A$17) -> #REF! | J52: =SUMIFS('Variance Analysis'!J$9:J$24,'Variance Analysis'!$B$9:$B$24,'Variance Analysis'!$B$12,'Variance Analysis'!$A$9:$A$24,'Variance Analysis'!$A$17) -> #REF! | ... N52: =SUMIFS('Variance Analysis'!N$9:N$24,'Variance Analysis'!$B$9:$B$24,'Variance Analysis'!$B$12,'Variance Analysis'!$A$9:$A$24,'Variance Analysis'!$A$17) -> #REF!
A53: Production Costs | B53: $ | C53: =SUMIFS('Variance Analysis'!C$9:C$24,'Variance Analysis'!$B$9:$B$24,'Variance Analysis'!$B$10,'Variance Analysis'!$A$9:$A$24,'Variance Analysis'!$A$17) -> #REF! | D53: =SUMIFS('Variance Analysis'!D$9:D$24,'Variance Analysis'!$B$9:$B$24,'Variance Analysis'!$B$10,'Variance Analysis'!$A$9:$A$24,'Variance Analysis'!$A$17) -> #REF! | E53: =SUMIFS('Variance Analysis'!E$9:E$24,'Variance Analysis'!$B$9:$B$24,'Variance Analysis'!$B$10,'Variance Analysis'!$A$9:$A$24,'Variance Analysis'!$A$17) -> #REF! | F53: =SUMIFS('Variance Analysis'!F$9:F$24,'Variance Analysis'!$B$9:$B$24,'Variance Analysis'!$B$10,'Variance Analysis'!$A$9:$A$24,'Variance Analysis'!$A$17) -> #REF! | G53: =SUMIFS('Variance Analysis'!G$9:G$24,'Variance Analysis'!$B$9:$B$24,'Variance Analysis'!$B$10,'Variance Analysis'!$A$9:$A$24,'Variance Analysis'!$A$17) -> #REF! | H53: =SUMIFS('Variance Analysis'!H$9:H$24,'Variance Analysis'!$B$9:$B$24,'Variance Analysis'!$B$10,'Variance Analysis'!$A$9:$A$24,'Variance Analysis'!$A$17) -> #REF! | I53: =SUMIFS('Variance Analysis'!I$9:I$24,'Variance Analysis'!$B$9:$B$24,'Variance Analysis'!$B$10,'Variance Analysis'!$A$9:$A$24,'Variance Analysis'!$A$17) -> #REF! | J53: =SUMIFS('Variance Analysis'!J$9:J$24,'Variance Analysis'!$B$9:$B$24,'Variance Analysis'!$B$10,'Variance Analysis'!$A$9:$A$24,'Variance Analysis'!$A$17) -> #REF! | ... N53: =SUMIFS('Variance Analysis'!N$9:N$24,'Variance Analysis'!$B$9:$B$24,'Variance Analysis'!$B$10,'Variance Analysis'!$A$9:$A$24,'Variance Analysis'!$A$17) -> #REF!
A54: Other Production Costs | B54: $ | C54: =SUMIFS('Variance Analysis'!C$9:C$24,'Variance Analysis'!$B$9:$B$24,'Variance Analysis'!$B$11,'Variance Analysis'!$A$9:$A$24,'Variance Analysis'!$A$17) -> #REF! | D54: =SUMIFS('Variance Analysis'!D$9:D$24,'Variance Analysis'!$B$9:$B$24,'Variance Analysis'!$B$11,'Variance Analysis'!$A$9:$A$24,'Variance Analysis'!$A$17) -> #REF! | E54: =SUMIFS('Variance Analysis'!E$9:E$24,'Variance Analysis'!$B$9:$B$24,'Variance Analysis'!$B$11,'Variance Analysis'!$A$9:$A$24,'Variance Analysis'!$A$17) -> #REF! | F54: =SUMIFS('Variance Analysis'!F$9:F$24,'Variance Analysis'!$B$9:$B$24,'Variance Analysis'!$B$11,'Variance Analysis'!$A$9:$A$24,'Variance Analysis'!$A$17) -> #REF! | G54: =SUMIFS('Variance Analysis'!G$9:G$24,'Variance Analysis'!$B$9:$B$24,'Variance Analysis'!$B$11,'Variance Analysis'!$A$9:$A$24,'Variance Analysis'!$A$17) -> #REF! | H54: =SUMIFS('Variance Analysis'!H$9:H$24,'Variance Analysis'!$B$9:$B$24,'Variance Analysis'!$B$11,'Variance Analysis'!$A$9:$A$24,'Variance Analysis'!$A$17) -> #REF! | I54: =SUMIFS('Variance Analysis'!I$9:I$24,'Variance Analysis'!$B$9:$B$24,'Variance Analysis'!$B$11,'Variance Analysis'!$A$9:$A$24,'Variance Analysis'!$A$17) -> #REF! | J54: =SUMIFS('Variance Analysis'!J$9:J$24,'Variance Analysis'!$B$9:$B$24,'Variance Analysis'!$B$11,'Variance Analysis'!$A$9:$A$24,'Variance Analysis'!$A$17) -> #REF! | ... N54: =SUMIFS('Variance Analysis'!N$9:N$24,'Variance Analysis'!$B$9:$B$24,'Variance Analysis'!$B$11,'Variance Analysis'!$A$9:$A$24,'Variance Analysis'!$A$17) -> #REF!
A55: Revenue | B55: $ | C55: =SUMIFS('Variance Analysis'!C$9:C$24,'Variance Analysis'!$B$9:$B$24,'Variance Analysis'!$B$9,'Variance Analysis'!$A$9:$A$24,'Variance Analysis'!$A$17) -> #REF! | D55: =SUMIFS('Variance Analysis'!D$9:D$24,'Variance Analysis'!$B$9:$B$24,'Variance Analysis'!$B$9,'Variance Analysis'!$A$9:$A$24,'Variance Analysis'!$A$17) -> #REF! | E55: =SUMIFS('Variance Analysis'!E$9:E$24,'Variance Analysis'!$B$9:$B$24,'Variance Analysis'!$B$9,'Variance Analysis'!$A$9:$A$24,'Variance Analysis'!$A$17) -> #REF! | F55: =SUMIFS('Variance Analysis'!F$9:F$24,'Variance Analysis'!$B$9:$B$24,'Variance Analysis'!$B$9,'Variance Analysis'!$A$9:$A$24,'Variance Analysis'!$A$17) -> #REF! | G55: =SUMIFS('Variance Analysis'!G$9:G$24,'Variance Analysis'!$B$9:$B$24,'Variance Analysis'!$B$9,'Variance Analysis'!$A$9:$A$24,'Variance Analysis'!$A$17) -> #REF! | H55: =SUMIFS('Variance Analysis'!H$9:H$24,'Variance Analysis'!$B$9:$B$24,'Variance Analysis'!$B$9,'Variance Analysis'!$A$9:$A$24,'Variance Analysis'!$A$17) -> #REF! | I55: =SUMIFS('Variance Analysis'!I$9:I$24,'Variance Analysis'!$B$9:$B$24,'Variance Analysis'!$B$9,'Variance Analysis'!$A$9:$A$24,'Variance Analysis'!$A$17) -> #REF! | J55: =SUMIFS('Variance Analysis'!J$9:J$24,'Variance Analysis'!$B$9:$B$24,'Variance Analysis'!$B$9,'Variance Analysis'!$A$9:$A$24,'Variance Analysis'!$A$17) -> #REF! | ... N55: =SUMIFS('Variance Analysis'!N$9:N$24,'Variance Analysis'!$B$9:$B$24,'Variance Analysis'!$B$9,'Variance Analysis'!$A$9:$A$24,'Variance Analysis'!$A$17) -> #REF!
A56: EBIT | B56: $ | C56: =ABS(C55)-SUM(C52:C54) -> #REF! | D56: =ABS(D55)-SUM(D52:D54) -> #REF! | E56: =ABS(E55)-SUM(E52:E54) -> #REF! | F56: =ABS(F55)-SUM(F52:F54) -> #REF! | G56: =ABS(G55)-SUM(G52:G54) -> #REF! | H56: =ABS(H55)-SUM(H52:H54) -> #REF! | I56: =ABS(I55)-SUM(I52:I54) -> #REF! | J56: =ABS(J55)-SUM(J52:J54) -> #REF! | ... N56: =ABS(N55)-SUM(N52:N54) -> #REF!
A58: OVERALL | B58: Units | C58: 2013/Jul | D58: 2013/Aug | E58: 2013/Sep | F58: 2013/Oct | G58: 2013/Nov | H58: 2013/Dec | I58: 2014/Jan | J58: 2014/Feb | K58: 2014/Mar | L58: 2014/Apr | M58: 2014/May | N58: 2014/Jun
